Workbook

Sheet Hall of Fame
A1: Saturday Xmas Challenge Cup | J1: The Cherry Lodge Trophy | S1: The Morrow Masters
A4: 2006 | E4: Kevin Fletcher | J4: 2006 | S4: 2006
A6: 2007 | E6: Graham Mitchell | J6: 2007 | S6: 2007
A8: 2008 | D8: 44 | E8: Ian Roy | J8: 2008 | M8: 27 | N8: Michael Folb | S8: 2008
A10: 2009 | D10: 39 | E10: Alan Dossett | J10: 2009 | M10: 24 | N10: Paul Mason | S10: 2009
A12: =A10+1 -> 2010 | D12: 40 | E12: Chris Bowden | J12: =J10+1 -> 2010 | M12: 25 | N12: Jeffery Millins | S12: =S10+1 -> 2010
A14: =A12+1 -> 2011 | D14: 37 | E14: Ray Hasler | J14: =J12+1 -> 2011 | M14: 24 | N14: Ivan Hook | S14: =S12+1 -> 2011
A16: =A14+1 -> 2012 | D16: 42 | E16: Rick Morrison | J16: =J14+1 -> 2012 | M16: 22 | N16: Peter Bucknell | S16: =S14+1 -> 2012
A18: =A16+1 -> 2013 | D18: 37 | E18: Terry Walker | J18: =J16+1 -> 2013 | M18: 21 | N18: Phil Cook | S18: =S16+1 -> 2013
A20: =A18+1 -> 2014 | D20: 41 | E20: Norman Rose | J20: =J18+1 -> 2014 | M20: 20 | N20: Andy Thompson | S20: =S18+1 -> 2014
A22: =A20+1 -> 2015 | D22: 42 | E22: Scott Lineard | J22: =J20+1 -> 2015 | N22: Pat Coleman | S22: =S20+1 -> 2015
A24: =A22+1 -> 2016 | E24: No contest due to fog | J24: =J22+1 -> 2016 | N24: No contest due to fog | S24: =S22+1 -> 2016
A26: =A24+1 -> 2017 | D26: 37 | E26: Graham Cole | J26: =J24+1 -> 2017 | M26: 20 | N26: Andy Thompson & Rob Harley | S26: =S24+1 -> 2017 | W26: Richard Minnis
A28: =A26+1 -> 2018 | D28: 46 | E28: Graham Cole | J28: =J26+1 -> 2018 | M28: 20 | N28: Dan Hunt | S28: =S26+1 -> 2018
A30: =A28+1 -> 2019 | E30: No contest due to waterlogged course | J30: =J28+1 -> 2019 | N30: No contest due to waterlogged course | S30: =S28+1 -> 2019 | W30: Phil Cook
A32: =A30+1 -> 2020 | E32: No contest due to Covid | J32: =J30+1 -> 2020 | N32: No contest due to Covid | S32: =S30+1 -> 2020
A34: =A32+1 -> 2021 | D34: 35 | E34: Phil Cook, Dickie Moxon, Dan Callingham & Steve Wheeler | J34: =J32+1 -> 2021 | N34: No contested | S34: =S32+1 -> 2021
A36: =A34+1 -> 2022 | D36: 40 | E36: Stuart Gay, Andy Thompson | J36: =J34+1 -> 2022 | M36: 24 | N36: Steve Wheeler | S36: =S34+1 -> 2022
A38: =A36+1 -> 2023 | E38: No contest due to waterlogged course | J38: =J36+1 -> 2023 | N38: Mike Forrest (Based on Order of Merit) | S38: =S36+1 -> 2023 | W38: Paul Clarke
A40: 2024 | J40: 2024 | M40: 0 | N40: Ross Fraser (Was DQ'd from the day) | S40: 2024
A42: 2025 | D42: 36 | E42: Chris Smith (Based on Arm Wrestle decider) | J42: 2025 | M42: 18 | N42: Archie Fraser | S42: 2025

Sheet Name List
D3: Scoring | F3: Date
D4: average | F4: 46025 | H4: Entry | I4: 5
D5: 2 from 3 | F5: =F4+7 -> 46032
B6: Stuart Anderson | D6: all scores count | F6: =F5+7 -> 46039
B7: Max Ball | D7: individual | F7: =F6+7 -> 46046
B8: Harley Bishop | D8: None | F8: =F7+7 -> 46053
B9: Chris Burroughs | F9: =F8+7 -> 46060
B10: George Burton | F10: =F9+7 -> 46067
B11: Tom Burton | F11: =F10+7 -> 46074
B12: Mike Chubb | F12: =F11+7 -> 46081
B13: George Clarke | F13: =F12+7 -> 46088
B14: Paul Clarke | D14: Format | F14: =F13+7 -> 46095
B15: Martin Coomber | D15: Swindle | F15: =F14+7 -> 46102
B16: Dominic Coughlin | D16: Monthly Stableford | F16: =F15+7 -> 46109
B17: Gareth Davies | D17: Monthly Medal | F17: =F16+7 -> 46116
B18: Peter Donovan | D18: Club Competition | F18: =F17+7 -> 46123
B19: James Dunn | F19: =F18+7 -> 46130
B20: Gordon Fielding | F20: =F19+7 -> 46137
B21: Paul Fitzgerald | F21: =F20+7 -> 46144
B22: Ben Fleet | F22: =F21+7 -> 46151
B23: Mike Forrest | F23: =F22+7 -> 46158
B24: Tony Forsyth-James | F24: =F23+7 -> 46165
B25: Archie Fraser | F25: =F24+7 -> 46172
B26: Ross Fraser | F26: =F25+7 -> 46179
B27: Nick Garner | F27: =F26+7 -> 46186
B28: Stuart Gay | F28: =F27+7 -> 46193
B29: Jordan Hall | F29: =F28+7 -> 46200
B30: Gary Hall | F30: =F29+7 -> 46207
... B55: Rory Thompson | F55: =F54+7 -> 46382
B56: Sonny Thompson
B57: Kevin Tribley
B58: Russell Turner
B59: Peter Vallely
B60: Ryan Vaughan
B61: Jason Wale
B62: Terry Walker
B63: Finn Wheeler
B64: Steve Wheeler
B65: Brad Whitehead
B66: Dave Woodget
B67: Jonathan Kanareck
... B74: Kyle Deane
B75: 1
B76: 2
B77: 3
B78: 4
B79: 5
B80: 6
B81: 7
B82: 8
B83: 9
B84: 10
B85: 11
B86: 12
... B105: 31

Sheet Scores and stats
QT1: Across All Play Types | QY1: Norm + Monthlys | RK1: Norm + Monthlys
C2: =$A$2+1 -> 1 | F2: Eagles | G2: Birdies | H2: Pars | I2: Blobs | J2: Entry fee | L2: =$C$2+1 -> 2 | O2: Eagles | P2: Birdies | Q2: Pars | R2: Blobs | S2: Entry fee | U2: 3 | X2: Eagles | Y2: Birdies | Z2: Pars | AA2: Blobs | AB2: Entry fee | AD2: 4 | AG2: Eagles | AH2: Birdies | AI2: Pars | AJ2: Blobs | AK2: Entry fee | AM2: =AD2+1 -> 5 | AP2: Eagles | AQ2: Birdies | AR2: Pars | AS2: Blobs | AT2: Entry fee | AV2: =AM2+1 -> 6 | AY2: Eagles | AZ2: Birdies | BA2: Pars | BB2: Blobs | BC2: Entry fee | BE2: =AV2+1 -> 7 | BH2: Eagles | BI2: Birdies | BJ2: Pars | BK2: Blobs | BL2: Entry fee | BN2: =BE2+1 -> 8 | BQ2: Eagles | BR2: Birdies | BS2: Pars | BT2: Blobs | BU2: Entry fee | BW2: =BN2+1 -> 9 | BZ2: Eagles | CA2: Birdies | CB2: Pars | CC2: Blobs | CD2: Entry fee | CF2: =BW2+1 -> 10 | CI2: Eagles | CJ2: Birdies | CK2: Pars | CL2: Blobs | CM2: Entry fee | CO2: =CF2+1 -> 11 | CR2: Eagles | CS2: Birdies | CT2: Pars | CU2: Blobs | CV2: Entry fee | CX2: =CO2+1 -> 12 | DA2: Eagles | DB2: Birdies | DC2: Pars | DD2: Blobs | DE2: Entry fee | DG2: =CX2+1 -> 13 | DJ2: Eagles | DK2: Birdies | DL2: Pars | DM2: Blobs | DN2: Entry fee | DP2: =DG2+1 -> 14 | DS2: Eagles | DT2: Birdies | DU2: Pars | DV2: Blobs | DW2: Entry fee | DY2: =DP2+1 -> 15 | EB2: Eagles | EC2: Birdies | ED2: Pars | EE2: Blobs | EF2: Entry fee | EH2: =DY2+1 -> 16 | EK2: Eagles | EL2: Birdies | EM2: Pars | EN2: Blobs | EO2: Entry fee | EQ2: =EH2+1 -> 17 | ET2: Eagles | EU2: Birdies | EV2: Pars | EW2: Blobs | EX2: Entry fee | EZ2: =EQ2+1 -> 18 | FC2: Eagles | FD2: Birdies | FE2: Pars | FF2: Blobs | FG2: Entry fee | FI2: =EZ2+1 -> 19 | FL2: Eagles | FM2: Birdies | FN2: Pars | FO2: Blobs | FP2: Entry fee | FR2: =FI2+1 -> 20 | FU2: Eagles | FV2: Birdies | FW2: Pars | FX2: Blobs | FY2: Entry fee | GA2: =FR2+1 -> 21 | GD2: Eagles | GE2: Birdies | GF2: Pars | GG2: Blobs | GH2: Entry fee | GJ2: =GA2+1 -> 22 | GM2: Eagles | GN2: Birdies | GO2: Pars | GP2: Blobs | GQ2: Entry fee | GS2: =GJ2+1 -> 23 | GV2: Eagles | GW2: Birdies | GX2: Pars | GY2: Blobs | GZ2: Entry fee | HB2: =GS2+1 -> 24 | HE2: Eagles | HF2: Birdies | HG2: Pars | HH2: Blobs | HI2: Entry fee | HK2: =HB2+1 -> 25 | HN2: Eagles | HO2: Birdies | HP2: Pars | HQ2: Blobs | HR2: Entry fee | HT2: =HK2+1 -> 26 | HW2: Eagles | HX2: Birdies | HY2: Pars | HZ2: Blobs | IA2: Entry fee | IC2: =HT2+1 -> 27 | IF2: Eagles | IG2: Birdies | IH2: Pars | II2: Blobs | IJ2: Entry fee | IL2: =IC2+1 -> 28 | IO2: Eagles | IP2: Birdies | IQ2: Pars | IR2: Blobs | IS2: Entry fee | IU2: =IL2+1 -> 29 | IX2: Eagles | IY2: Birdies | IZ2: Pars | JA2: Blobs | JB2: Entry fee | JD2: =IU2+1 -> 30 | JG2: Eagles | JH2: Birdies | JI2: Pars | JJ2: Blobs | JK2: Entry fee | JM2: =JD2+1 -> 31 | JP2: Eagles | JQ2: Birdies | JR2: Pars | JS2: Blobs | JT2: Entry fee | JV2: =JM2+1 -> 32 | JY2: Eagles | JZ2: Birdies | KA2: Pars | KB2: Blobs | KC2: Entry fee | KE2: =JV2+1 -> 33 | KH2: Eagles | KI2: Birdies | KJ2: Pars | KK2: Blobs | KL2: Entry fee | KN2: =KE2+1 -> 34 | KQ2: Eagles | KR2: Birdies | KS2: Pars | KT2: Blobs | KU2: Entry fee | KW2: =KN2+1 -> 35 | KZ2: Eagles | LA2: Birdies | LB2: Pars | LC2: Blobs | LD2: Entry fee | LF2: =KW2+1 -> 36 | LI2: Eagles | LJ2: Birdies | LK2: Pars | LL2: Blobs | LM2: Entry fee | LO2: =LF2+1 -> 37 | LR2: Eagles | LS2: Birdies | LT2: Pars | LU2: Blobs | LV2: Entry fee | LX2: =LO2+1 -> 38 | MA2: Eagles | MB2: Birdies | MC2: Pars | MD2: Blobs | ME2: Entry fee | MG2: =LX2+1 -> 39 | MJ2: Eagles | MK2: Birdies | ML2: Pars | MM2: Blobs | MN2: Entry fee | MP2: =MG2+1 -> 40 | MS2: Eagles | MT2: Birdies | MU2: Pars | MV2: Blobs | MW2: Entry fee | MY2: =MP2+1 -> 41 | NB2: Eagles | NC2: Birdies | ND2: Pars | NE2: Blobs | NF2: Entry fee | NH2: =MY2+1 -> 42 | NK2: Eagles | NL2: Birdies | NM2: Pars | NN2: Blobs | NO2: Entry fee | NQ2: =NH2+1 -> 43 | NT2: Eagles | NU2: Birdies | NV2: Pars | NW2: Blobs | NX2: Entry fee | NZ2: =NQ2+1 -> 44 | OC2: Eagles | OD2: Birdies | OE2: Pars | OF2: Blobs | OG2: Entry fee | OI2: =NZ2+1 -> 45 | OL2: Eagles | OM2: Birdies | ON2: Pars | OO2: Blobs | OP2: Entry fee | OR2: =OI2+1 -> 46 | OU2: Eagles | OV2: Birdies | OW2: Pars | OX2: Blobs | OY2: Entry fee | PA2: =OR2+1 -> 47 | PD2: Eagles | PE2: Birdies | PF2: Pars | PG2: Blobs | PH2: Entry fee | PJ2: =PA2+1 -> 48 | PM2: Eagles | PN2: Birdies | PO2: Pars | PP2: Blobs | PQ2: Entry fee | PS2: =PJ2+1 -> 49 | PV2: Eagles | PW2: Birdies | PX2: Pars | PY2: Blobs | PZ2: Entry fee | QB2: =PS2+1 -> 50 | QE2: Eagles | QF2: Birdies | QG2: Pars | QH2: Blobs | QI2: Entry fee | QK2: =QB2+1 -> 51 | QN2: Eagles | QO2: Birdies | QP2: Pars | QQ2: Blobs | QR2: Entry fee | QT2: Eagles | QU2: Birdies | QV2: Pars | QW2: Blobs | QY2: Stablefords played | RA2: Best Swindle Stableford Front 9 | RB2: Best Swindle Stableford Back 9 | RC2: Best Swindle stableford score | RD2: Worst Swindle Stableford Front 9 | RE2: Worst Swindle Stableford Back 9 | RF2: Worst Swindle stableford score | RH2: Best Monthly stableford score | RI2: Worst Monthly stableford score | RK2: Average stableford score | RM2: Best Medal score | RN2: Worst Medal score | RP2: Medals played
C3: 46025 | L3: 46032 | U3: 46039 | AD3: 46046 | AM3: =AD3+7 -> 46053 | AV3: =AM3+7 -> 46060 | BE3: =AV3+7 -> 46067 | BN3: =BE3+7 -> 46074 | BW3: =BN3+7 -> 46081 | CF3: =BW3+7 -> 46088 | CO3: =CF3+7 -> 46095 | CX3: =CO3+7 -> 46102 | DG3: =CX3+7 -> 46109 | DP3: =DG3+7 -> 46116 | DY3: =DP3+7 -> 46123 | EH3: =DY3+7 -> 46130 | EQ3: =EH3+7 -> 46137 | EZ3: =EQ3+7 -> 46144 | FI3: =EZ3+7 -> 46151 | FR3: =FI3+7 -> 46158 | GA3: =FR3+7 -> 46165 | GJ3: =GA3+7 -> 46172 | GS3: =GJ3+7 -> 46179 | HB3: =GS3+7 -> 46186 | HK3: =HB3+7 -> 46193 | HT3: =HK3+7 -> 46200 | IC3: =HT3+7 -> 46207 | IL3: =IC3+7 -> 46214 | IU3: =IL3+7 -> 46221 | JD3: =IU3+7 -> 46228 | JM3: =JD3+7 -> 46235 | JV3: =JM3+7 -> 46242 | KE3: =JV3+7 -> 46249 | KN3: =KE3+7 -> 46256 | KW3: =KN3+7 -> 46263 | LF3: =KW3+7 -> 46270 | LO3: =LF3+7 -> 46277 | LX3: =LO3+7 -> 46284 | MG3: =LX3+7 -> 46291 | MP3: =MG3+7 -> 46298 | MY3: =MP3+7 -> 46305 | NH3: =MY3+7 -> 46312 | NQ3: =NH3+7 -> 46319 | NZ3: 46326 | OI3: =NZ3+7 -> 46333 | OR3: =OI3+7 -> 46340 | PA3: =OR3+7 -> 46347 | PJ3: =PA3+7 -> 46354 | PS3: =PJ3+7 -> 46361 | QB3: =PS3+7 -> 46368 | QK3: =QB3+7 -> 46375
C4: Swindle | L4: Swindle | U4: Monthly Stableford | AD4: Swindle | AM4: Swindle | AV4: Monthly Stableford | BE4: Swindle | BN4: Swindle | BW4: Swindle | CF4: Club Competition | CO4: Monthly Stableford | CX4: Swindle | DG4: Swindle | DP4: Swindle | DY4: Swindle | EH4: Swindle | EQ4: Monthly Medal | EZ4: Club Competition | FI4: Swindle | FR4: Swindle | GA4: Swindle | GJ4: Swindle | GS4: Club Competition | HB4: Swindle | HK4: Monthly Stableford | HT4: Club Competition | IC4: Monthly Medal | IL4: Swindle | IU4: Swindle | JD4: Swindle | JM4: Swindle | JV4: Swindle | KE4: Swindle | KN4: Club Competition | KW4: Swindle | LF4: Monthly Stableford | LO4: Swindle | LX4: Swindle | MG4: Swindle | MP4: Swindle | MY4: Swindle | NH4: Swindle | NQ4: Swindle | NZ4: Monthly Stableford | OI4: Swindle | OR4: Monthly Stableford | PA4: Swindle | PJ4: Club Competition | PS4: Swindle | QB4: Monthly Stableford | QK4: Club Competition
A5: Name | C5: Front | D5: Back | E5: Score | L5: Front | M5: Back | N5: Score | U5: Front | V5: Back | W5: Score | AD5: Front | AE5: Back | AF5: Score | AM5: Front | AN5: Back | AO5: Score | AV5: Front | AW5: Back | AX5: Score | BE5: Front | BF5: Back | BG5: Score | BN5: Front | BO5: Back | BP5: Score | BW5: Front | BX5: Back | BY5: Score | CF5: Front | CG5: Back | CH5: Score | CO5: Front | CP5: Back | CQ5: Score | CX5: Front | CY5: Back | CZ5: Score | DG5: Front | DH5: Back | DI5: Score | DP5: Front | DQ5: Back | DR5: Score | DY5: Front | DZ5: Back | EA5: Score | EH5: Front | EI5: Back | EJ5: Score | EQ5: Front | ER5: Back | ES5: Score | EZ5: Front | FA5: Back | FB5: Score | FI5: Front | FJ5: Back | FK5: Score | FR5: Front | FS5: Back | FT5: Score | GA5: Front | GB5: Back | GC5: Score | GJ5: Front | GK5: Back | GL5: Score | GS5: Front | GT5: Back | GU5: Score | HB5: Front | HC5: Back | HD5: Score | HK5: Front | HL5: Back | HM5: Score | HT5: Front | HU5: Back | HV5: Score | IC5: Front | ID5: Back | IE5: Score | IL5: Front | IM5: Back | IN5: Score | IU5: Front | IV5: Back | IW5: Score | JD5: Front | JE5: Back | JF5: Score | JM5: Front | JN5: Back | JO5: Score | JV5: Front | JW5: Back | JX5: Score | KE5: Front | KF5: Back | KG5: Score | KN5: Front | KO5: Back | KP5: Score | KW5: Front | KX5: Back | KY5: Score | LF5: Front | LG5: Back | LH5: Score | LO5: Front | LP5: Back | LQ5: Score | LX5: Front | LY5: Back | LZ5: Score | MG5: Front | MH5: Back | MI5: Score | MP5: Front | MQ5: Back | MR5: Score | MY5: Front | MZ5: Back | NA5: Score | NH5: Front | NI5: Back | NJ5: Score | NQ5: Front | NR5: Back | NS5: Score | NZ5: Front | OA5: Back | OB5: Score | OI5: Front | OJ5: Back | OK5: Score | OR5: Front | OS5: Back | OT5: Score | PA5: Front | PB5: Back | PC5: Score | PJ5: Front | PK5: Back | PL5: Score | PS5: Front | PT5: Back | PU5: Score | QB5: Front | QC5: Back | QD5: Score | QK5: Front | QL5: Back | QM5: Score
A6: ='Name List'!B6 -> Stuart Anderson | E6: =IF(C6=0,"",C6+D6) | J6: =IF(E6="","",'Name List'!$I$4) | N6: =IF(L6=0,"",L6+M6) | S6: =IF(N6="","",'Name List'!$I$4) | W6: =IF(U6=0,"",U6+V6) | AB6: =IF(W6="","",'Name List'!$I$4) | AF6: =IF(AD6=0,"",AD6+AE6) | AK6: =IF(AF6="","",'Name List'!$I$4) | AO6: =IF(AM6=0,"",AM6+AN6) | AT6: =IF(AO6="","",'Name List'!$I$4) | AX6: =IF(AV6=0,"",AV6+AW6) | BC6: =IF(AX6="","",'Name List'!$I$4) | BG6: =IF(BE6=0,"",BE6+BF6) | BL6: =IF(BG6="","",'Name List'!$I$4) | BP6: =IF(BN6=0,"",BN6+BO6) | BU6: =IF(BP6="","",'Name List'!$I$4) | BY6: =IF(BW6=0,"",BW6+BX6) | CD6: =IF(BY6="","",'Name List'!$I$4) | CH6: =IF(CF6=0,"",CF6+CG6) | CM6: =IF(CH6="","",'Name List'!$I$4) | CQ6: =IF(CO6=0,"",CO6+CP6) | CV6: =IF(CQ6="","",'Name List'!$I$4) | CZ6: =IF(CX6=0,"",CX6+CY6) | DE6: =IF(CZ6="","",'Name List'!$I$4) | DI6: =IF(DG6=0,"",DG6+DH6) | DN6: =IF(DI6="","",'Name List'!$I$4) | DR6: =IF(DP6=0,"",DP6+DQ6) | DW6: =IF(DR6="","",'Name List'!$I$4) | EA6: =IF(DY6=0,"",DY6+DZ6) | EF6: =IF(EA6="","",'Name List'!$I$4) | EJ6: =IF(EH6=0,"",EH6+EI6) | EO6: =IF(EJ6="","",'Name List'!$I$4) | EX6: =IF(ES6="","",'Name List'!$I$4) | FB6: =IF(EZ6=0,"",EZ6+FA6) | FG6: =IF(FB6="","",'Name List'!$I$4) | FK6: =IF(FI6=0,"",FI6+FJ6) | FP6: =IF(FK6="","",'Name List'!$I$4) | FT6: =IF(FR6=0,"",FR6+FS6) | FY6: =IF(FT6="","",'Name List'!$I$4) | GC6: =IF(GA6=0,"",GA6+GB6) | GH6: =IF(GC6="","",'Name List'!$I$4) | GL6: =IF(GJ6=0,"",GJ6+GK6) | GQ6: =IF(GL6="","",'Name List'!$I$4) | GU6: =IF(GS6=0,"",GS6+GT6) | GZ6: =IF(GU6="","",'Name List'!$I$4) | HD6: =IF(HB6=0,"",HB6+HC6) | HI6: =IF(HD6="","",'Name List'!$I$4) | HM6: =IF(HK6=0,"",HK6+HL6) | HR6: =IF(HM6="","",'Name List'!$I$4) | HV6: =IF(HT6=0,"",HT6+HU6) | IA6: =IF(HV6="","",'Name List'!$I$4) | IJ6: =IF(IE6="","",'Name List'!$I$4) | IN6: =IF(IL6=0,"",IL6+IM6) | IS6: =IF(IN6="","",'Name List'!$I$4) | IW6: =IF(IU6=0,"",IU6+IV6) | JB6: =IF(IW6="","",'Name List'!$I$4) | JF6: =IF(JD6=0,"",JD6+JE6) | JK6: =IF(JF6="","",'Name List'!$I$4) | JO6: =IF(JM6=0,"",JM6+JN6) | JT6: =IF(JO6="","",'Name List'!$I$4) | JX6: =IF(JV6=0,"",JV6+JW6) | KC6: =IF(JX6="","",'Name List'!$I$4) | KG6: =IF(KE6=0,"",KE6+KF6) | KL6: =IF(KG6="","",'Name List'!$I$4) | KP6: =IF(KN6=0,"",KN6+KO6) | KU6: =IF(KP6="","",'Name List'!$I$4) | KY6: =IF(KW6=0,"",KW6+KX6) | LD6: =IF(KY6="","",'Name List'!$I$4) | LH6: =IF(LF6=0,"",LF6+LG6) | LM6: =IF(LH6="","",'Name List'!$I$4) | LQ6: =IF(LO6=0,"",LO6+LP6) | LV6: =IF(LQ6="","",'Name List'!$I$4) | LZ6: =IF(LX6=0,"",LX6+LY6) | ME6: =IF(LZ6="","",'Name List'!$I$4) | MI6: =IF(MG6=0,"",MG6+MH6) | MN6: =IF(MI6="","",'Name List'!$I$4) | MR6: =IF(MP6=0,"",MP6+MQ6) | MW6: =IF(MR6="","",'Name List'!$I$4) | NA6: =IF(MY6=0,"",MY6+MZ6) | NF6: =IF(NA6="","",'Name List'!$I$4) | NJ6: =IF(NH6=0,"",NH6+NI6) | NO6: =IF(NJ6="","",'Name List'!$I$4) | NS6: =IF(NQ6=0,"",NQ6+NR6) | NX6: =IF(NS6="","",'Name List'!$I$4) | OB6: =IF(NZ6=0,"",NZ6+OA6) | OG6: =IF(OB6="","",'Name List'!$I$4) | OK6: =IF(OI6=0,"",OI6+OJ6) | OP6: =IF(OK6="","",'Name List'!$I$4) | OT6: =IF(OR6=0,"",OR6+OS6) | OY6: =IF(OT6="","",'Name List'!$I$4) | PC6: =IF(PA6=0,"",PA6+PB6) | PH6: =IF(PC6="","",'Name List'!$I$4) | PL6: =IF(PJ6=0,"",PJ6+PK6) | PQ6: =IF(PL6="","",'Name List'!$I$4) | PU6: =IF(PS6=0,"",PS6+PT6) | PZ6: =IF(PU6="","",'Name List'!$I$4) | QD6: =IF(QB6=0,"",QB6+QC6) | QI6: =IF(QD6="","",'Name List'!$I$4) | QM6: =IF(QK6=0,"",QK6+QL6) | QR6: =IF(QM6="","",'Name List'!$I$4) | QT6: =SUM(F6+O6+X6+AG6+AP6+AY6+BH6+BQ6+BZ6+CI6+CR6+DA6+DJ6+DS6+EB6+EK6+ET6+FC6+FL6+FU6+GD6+GM6+GV6+HE6+HN6+HW6+IF6+IO6+IX6+JG6+JP6+JY6+KH6+KQ6+KZ6+LI6+LR6+MA6+MJ6+MS6+NB6+NK6+NT6+OC6+OL6+OU6+PD6+PM6+PV6+QE6+QN6) -> 0 | QU6: =SUM(G6+P6+Y6+AH6+AQ6+AZ6+BI6+BR6+CA6+CJ6+CS6+DB6+DK6+DT6+EC6+EL6+EU6+FD6+FM6+FV6+GE6+GN6+GW6+HF6+HO6+HX6+IG6+IP6+IY6+JH6+JQ6+JZ6+KI6+KR6+LA6+LJ6+LS6+MB6+MK6+MT6+NC6+NL6+NU6+OD6+OM6+OV6+PE6+PN6+PW6+QF6+QO6) -> 0 | QV6: =SUM(H6+Q6+Z6+AI6+AR6+BA6+BJ6+BS6+CB6+CK6+CT6+DC6+DL6+DU6+ED6+EM6+EV6+FE6+FN6+FW6+GF6+GO6+GX6+HG6+HP6+HY6+IH6+IQ6+IZ6+JI6+JR6+KA6+KJ6+KS6+LB6+LK6+LT6+MC6+ML6+MU6+ND6+NM6+NV6+OE6+ON6+OW6+PF6+PO6+PX6+QG6+QP6) -> 0 | QW6: =SUM(I6+R6+AA6+AJ6+AS6+BB6+BK6+BT6+CC6+CL6+CU6+DD6+DM6+DV6+EE6+EN6+EW6+FF6+FO6+FX6+GG6+GP6+GY6+HH6+HQ6+HZ6+II6+IR6+JA6+JJ6+JS6+KB6+KK6+KT6+LC6+LL6+LU6+MD6+MM6+MV6+NE6+NN6+NW6+OF6+OO6+OX6+PG6+PP6+PY6+QH6+QQ6) -> 0 | QY6: =SUM(J6,S6,AB6,AK6,AT6,BC6,BL6,BU6,CD6,CM6,CV6,DE6,DN6,DW6,EF6,EO6,FP6,FY6,GH6,GQ6,HI6,HR6,IS6,JB6,JK6,JT6,KC6,KL6,KU6,LD6,LM6,LV6,ME6,MN6,MW6,NF6,NO6,NX6,OG6,OP6,OY6,PH6,PZ6)/5 -> 0 | RA6: =MAX(C6,L6,AD6,AM6,AV6,BN6,BW6,CF6,CX6,DG6,DP6,DY6,EH6,FI6,FR6,GA6,GJ6,HB6,IL6,IU6,JD6,JM6,JV6,KE6,KW6,LO6,LX6,MG6,MP6,MY6,NH6,NQ6,OI6,PA6,PS6) -> 0 | RB6: =MAX(D6,M6,AE6,AN6,AW6,BO6,BX6,CG6,CY6,DH6,DQ6,DZ6,EI6,FJ6,FS6,GB6,GK6,HC6,IM6,IV6,JE6,JN6,JW6,KF6,KX6,LP6,LY6,MH6,MQ6,MZ6,NI6,NR6,OJ6,PB6,PT6) -> 0 | RC6: =MAX(E6,N6,AF6,AO6,AX6,BP6,BY6,CH6,CZ6,DI6,DR6,EA6,EJ6,FK6,FT6,GC6,GL6,HD6,IN6,IW6,JF6,JO6,JX6,KG6,KY6,LQ6,LZ6,MI6,MR6,NA6,NJ6,NS6,OK6,PC6,PU6) -> 0 | RD6: =MIN(C6,L6,AD6,AM6,AV6,BN6,BW6,CF6,CX6,DG6,DP6,DY6,EH6,FI6,FR6,GA6,GJ6,HB6,IL6,IU6,JD6,JM6,JV6,KE6,KW6,LO6,LX6,MG6,MP6,MY6,NH6,NQ6,OI6,PA6,PS6) -> 0 | RE6: =MIN(D6,M6,AE6,AN6,AW6,BO6,BX6,CG6,CY6,DH6,DQ6,DZ6,EI6,FJ6,FS6,GB6,GK6,HC6,IM6,IV6,JE6,JN6,JW6,KF6,KX6,LP6,LY6,MH6,MQ6,MZ6,NI6,NR6,OJ6,PB6,PT6) -> 0 | RF6: =MIN(E6,N6,AF6,AO6,AX6,BP6,BY6,CH6,CZ6,DI6,DR6,EA6,EJ6,FK6,FT6,GC6,GL6,HD6,IN6,IW6,JF6,JO6,JX6,KG6,KY6,LQ6,LZ6,MI6,MR6,NA6,NJ6,NS6,OK6,PC6,PU6) -> 0 | RH6: =MAX(W6,BG6,CQ6,HM6,LH6,OB6,OT6) -> 0 | RI6: =MIN(W6,BG6,CQ6,HM6,LH6,OB6,OT6) -> 0 | RK6: =IFERROR(SUM(E6,N6,W6,AF6,AO6,AX6,BG6,BP6,BY6,CH6,CQ6,CZ6,DI6,DR6,EA6,EJ6,FK6,GC6,GL6,HD6,HM6,IN6,IW6,JF6,JO6,JX6,KG6,KY6,LH6,LQ6,LZ6,MI6,MR6,NA6,NJ6,NS6,OB6,OK6,OT6,PC6,)/QY6,0) -> 0 | RM6: =MAX(ES6,IE6) -> 0 | RN6: =MIN(ES6,IE6) -> 0 | RP6: =SUM(EX6,IJ6)/5 -> 0
A7: ='Name List'!B7 -> Max Ball | E7: =IF(C7=0,"",C7+D7) | J7: =IF(E7="","",'Name List'!$I$4) | W7: =IF(U7=0,"",U7+V7) | AB7: =IF(W7="","",'Name List'!$I$4) | AF7: =IF(AD7=0,"",AD7+AE7) | AK7: =IF(AF7="","",'Name List'!$I$4) | AO7: =IF(AM7=0,"",AM7+AN7) | AT7: =IF(AO7="","",'Name List'!$I$4) | AV7: 16 | AW7: 20 | AX7: =IF(AV7=0,"",AV7+AW7) -> 36 | AY7: 0 | AZ7: 1 | BA7: 10 | BB7: 1 | BC7: =IF(AX7="","",'Name List'!$I$4) -> 5 | BG7: =IF(BE7=0,"",BE7+BF7) | BL7: =IF(BG7="","",'Name List'!$I$4) | BW7: 20 | BX7: 21 | BY7: =IF(BW7=0,"",BW7+BX7) -> 41 | BZ7: 0 | CA7: 2 | CB7: 11 | CC7: 0 | CD7: =IF(BY7="","",'Name List'!$I$4) -> 5 | CF7: 14 | CG7: 20 | CH7: =IF(CF7=0,"",CF7+CG7) -> 34 | CI7: 0 | CJ7: 2 | CK7: 6 | CL7: 1 | CM7: =IF(CH7="","",'Name List'!$I$4) -> 5 | CO7: 13 | CP7: 22 | CQ7: =IF(CO7=0,"",CO7+CP7) -> 35 | CR7: 0 | CS7: 1 | CT7: 9 | CU7: 0 | CV7: =IF(CQ7="","",'Name List'!$I$4) -> 5 | CZ7: =IF(CX7=0,"",CX7+CY7) | DE7: =IF(CZ7="","",'Name List'!$I$4) | DG7: 17 | DH7: 18 | DI7: =IF(DG7=0,"",DG7+DH7) -> 35 | DJ7: 0 | DK7: 2 | DL7: 8 | DM7: 1 | DN7: =IF(DI7="","",'Name List'!$I$4) -> 5 | DR7: =IF(DP7=0,"",DP7+DQ7) | DW7: =IF(DR7="","",'Name List'!$I$4) | DY7: 18 | DZ7: 17 | EA7: =IF(DY7=0,"",DY7+DZ7) -> 35 | EB7: 0 | EC7: 1 | ED7: 9 | EE7: 0 | EF7: =IF(EA7="","",'Name List'!$I$4) -> 5 | EJ7: =IF(EH7=0,"",EH7+EI7) | EO7: =IF(EJ7="","",'Name List'!$I$4) | ES7: 83 | ET7: 0 | EU7: 0 | EV7: 8 | EX7: =IF(ES7="","",'Name List'!$I$4) -> 5 | FK7: =IF(FI7=0,"",FI7+FJ7) | FP7: =IF(FK7="","",'Name List'!$I$4) | FT7: =IF(FR7=0,"",FR7+FS7) | FY7: =IF(FT7="","",'Name List'!$I$4) | GC7: =IF(GA7=0,"",GA7+GB7) | GH7: =IF(GC7="","",'Name List'!$I$4) | GJ7: 20 | GK7: 15 | GL7: =IF(GJ7=0,"",GJ7+GK7) -> 35 | GM7: 0 | GN7: 1 | GO7: 12 | GP7: 2 | GQ7: =IF(GL7="","",'Name List'!$I$4) -> 5 | HB7: 19 | HC7: 18 | HD7: =IF(HB7=0,"",HB7+HC7) -> 37 | HE7: 0 | HF7: 3 | HG7: 7 | HH7: 1 | HI7: =IF(HD7="","",'Name List'!$I$4) -> 5 | HK7: 16 | HL7: 21 | HM7: =IF(HK7=0,"",HK7+HL7) -> 37 | HN7: 0 | HO7: 3 | HP7: 5 | HQ7: 1 | HR7: =IF(HM7="","",'Name List'!$I$4) -> 5 | IJ7: =IF(IE7="","",'Name List'!$I$4) | QR7: =IF(QM7="","",'Name List'!$I$4) | QT7: =SUM(F7+O7+X7+AG7+AP7+AY7+BH7+BQ7+BZ7+CI7+CR7+DA7+DJ7+DS7+EB7+EK7+ET7+FC7+FL7+FU7+GD7+GM7+GV7+HE7+HN7+HW7+IF7+IO7+IX7+JG7+JP7+JY7+KH7+KQ7+KZ7+LI7+LR7+MA7+MJ7+MS7+NB7+NK7+NT7+OC7+OL7+OU7+PD7+PM7+PV7+QE7+QN7) -> 0 | QU7: =SUM(G7+P7+Y7+AH7+AQ7+AZ7+BI7+BR7+CA7+CJ7+CS7+DB7+DK7+DT7+EC7+EL7+EU7+FD7+FM7+FV7+GE7+GN7+GW7+HF7+HO7+HX7+IG7+IP7+IY7+JH7+JQ7+JZ7+KI7+KR7+LA7+LJ7+LS7+MB7+MK7+MT7+NC7+NL7+NU7+OD7+OM7+OV7+PE7+PN7+PW7+QF7+QO7) -> 16 | QV7: =SUM(H7+Q7+Z7+AI7+AR7+BA7+BJ7+BS7+CB7+CK7+CT7+DC7+DL7+DU7+ED7+EM7+EV7+FE7+FN7+FW7+GF7+GO7+GX7+HG7+HP7+HY7+IH7+IQ7+IZ7+JI7+JR7+KA7+KJ7+KS7+LB7+LK7+LT7+MC7+ML7+MU7+ND7+NM7+NV7+OE7+ON7+OW7+PF7+PO7+PX7+QG7+QP7) -> 85 | QW7: =SUM(I7+R7+AA7+AJ7+AS7+BB7+BK7+BT7+CC7+CL7+CU7+DD7+DM7+DV7+EE7+EN7+EW7+FF7+FO7+FX7+GG7+GP7+GY7+HH7+HQ7+HZ7+II7+IR7+JA7+JJ7+JS7+KB7+KK7+KT7+LC7+LL7+LU7+MD7+MM7+MV7+NE7+NN7+NW7+OF7+OO7+OX7+PG7+PP7+PY7+QH7+QQ7) -> 7 | QY7: =SUM(J7,S7,AB7,AK7,AT7,BC7,BL7,BU7,CD7,CM7,CV7,DE7,DN7,DW7,EF7,EO7,FP7,FY7,GH7,GQ7,HI7,HR7,IS7,JB7,JK7,JT7,KC7,KL7,KU7,LD7,LM7,LV7,ME7,MN7,MW7,NF7,NO7,NX7,OG7,OP7,OY7,PH7,PZ7)/5 -> 9 | RA7: =MAX(C7,L7,AD7,AM7,AV7,BN7,BW7,CF7,CX7,DG7,DP7,DY7,EH7,FI7,FR7,GA7,GJ7,HK7,IL7,IU7,JD7,JM7,JV7,KE7,KW7,LO7,LX7,MG7,MP7,MY7,NH7,NQ7,OI7,PA7,PS7) -> 20 | RB7: =MAX(D7,M7,AE7,AN7,AW7,BO7,BX7,CG7,CY7,DH7,DQ7,DZ7,EI7,FJ7,FS7,GB7,GK7,HL7,IM7,IV7,JE7,JN7,JW7,KF7,KX7,LP7,LY7,MH7,MQ7,MZ7,NI7,NR7,OJ7,PB7,PT7) -> 21 | RC7: =MAX(E7,N7,AF7,AO7,AX7,BP7,BY7,CH7,CZ7,DI7,DR7,EA7,EJ7,FK7,FT7,GC7,GL7,HM7,IN7,IW7,JF7,JO7,JX7,KG7,KY7,LQ7,LZ7,MI7,MR7,NA7,NJ7,NS7,OK7,PC7,PU7) -> 41 | RD7: =MIN(C7,L7,AD7,AM7,AV7,BN7,BW7,CF7,CX7,DG7,DP7,DY7,EH7,FI7,FR7,GA7,GJ7,HK7,IL7,IU7,JD7,JM7,JV7,KE7,KW7,LO7,LX7,MG7,MP7,MY7,NH7,NQ7,OI7,PA7,PS7) -> 14 | RE7: =MIN(D7,M7,AE7,AN7,AW7,BO7,BX7,CG7,CY7,DH7,DQ7,DZ7,EI7,FJ7,FS7,GB7,GK7,HL7,IM7,IV7,JE7,JN7,JW7,KF7,KX7,LP7,LY7,MH7,MQ7,MZ7,NI7,NR7,OJ7,PB7,PT7) -> 15 | RF7: =MIN(E7,N7,AF7,AO7,AX7,BP7,BY7,CH7,CZ7,DI7,DR7,EA7,EJ7,FK7,FT7,GC7,GL7,HM7,IN7,IW7,JF7,JO7,JX7,KG7,KY7,LQ7,LZ7,MI7,MR7,NA7,NJ7,NS7,OK7,PC7,PU7) -> 34 | RH7: =MAX(W7,BG7,CQ7,HD7,LH7,OB7,OT7) -> 37 | RI7: =MIN(W7,BG7,CQ7,HD7,LH7,OB7,OT7) -> 35 | RK7: =IFERROR(SUM(E7,N7,W7,AF7,AO7,AX7,BG7,BP7,BY7,CH7,CQ7,CZ7,DI7,DR7,EA7,EJ7,FK7,GC7,GL7,HD7,HM7,IN7,IW7,JF7,JO7,JX7,KG7,KY7,LH7,LQ7,LZ7,MI7,MR7,NA7,NJ7,NS7,OB7,OK7,OT7,PC7,)/QY7,0) -> 36.111111 | RM7: =MAX(ES7,IE7) -> 83 | RN7: =MIN(ES7,IE7) -> 83 | RP7: =SUM(EX7,IJ7)/5 -> 1
A8: ='Name List'!B8 -> Harley Bishop | E8: =IF(C8=0,"",C8+D8) | J8: =IF(E8="","",'Name List'!$I$4) | U8: 12 | V8: 13 | W8: =IF(U8=0,"",U8+V8) -> 25 | X8: 0 | Y8: 0 | Z8: 2 | AA8: 2 | AB8: =IF(W8="","",'Name List'!$I$4) -> 5 | AD8: 18 | AE8: 9 | AF8: =IF(AD8=0,"",AD8+AE8) -> 27 | AG8: 0 | AH8: 1 | AI8: 4 | AJ8: 3 | AK8: =IF(AF8="","",'Name List'!$I$4) -> 5 | AM8: 13 | AN8: 16 | AO8: =IF(AM8=0,"",AM8+AN8) -> 29 | AP8: 0 | AQ8: 0 | AR8: 5 | AS8: 2 | AT8: =IF(AO8="","",'Name List'!$I$4) -> 5 | AX8: =IF(AV8=0,"",AV8+AW8) | BC8: =IF(AX8="","",'Name List'!$I$4) | BG8: =IF(BE8=0,"",BE8+BF8) | BL8: =IF(BG8="","",'Name List'!$I$4) | BY8: =IF(BW8=0,"",BW8+BX8) | CD8: =IF(BY8="","",'Name List'!$I$4) | CF8: 13 | CG8: 13 | CH8: =IF(CF8=0,"",CF8+CG8) -> 26 | CI8: 0 | CJ8: 1 | CK8: 3 | CL8: 5 | CM8: =IF(CH8="","",'Name List'!$I$4) -> 5 | CO8: 17 | CP8: 17 | CQ8: =IF(CO8=0,"",CO8+CP8) -> 34 | CR8: 0 | CS8: 1 | CT8: 7 | CU8: 3 | CV8: =IF(CQ8="","",'Name List'!$I$4) -> 5 | CZ8: =IF(CX8=0,"",CX8+CY8) | DE8: =IF(CZ8="","",'Name List'!$I$4) | DG8: 9 | DH8: 17 | DI8: =IF(DG8=0,"",DG8+DH8) -> 26 | DJ8: 0 | DK8: 0 | DL8: 5 | DM8: 4 | DN8: =IF(DI8="","",'Name List'!$I$4) -> 5 | DR8: =IF(DP8=0,"",DP8+DQ8) | DW8: =IF(DR8="","",'Name List'!$I$4) | EA8: =IF(DY8=0,"",DY8+DZ8) | EF8: =IF(EA8="","",'Name List'!$I$4) | EJ8: =IF(EH8=0,"",EH8+EI8) | EO8: =IF(EJ8="","",'Name List'!$I$4) | EX8: =IF(ES8="","",'Name List'!$I$4) | FI8: 16 | FJ8: 17 | FK8: =IF(FI8=0,"",FI8+FJ8) -> 33 | FL8: 0 | FM8: 1 | FN8: 4 | FO8: 0 | FP8: =IF(FK8="","",'Name List'!$I$4) -> 5 | FT8: =IF(FR8=0,"",FR8+FS8) | FY8: =IF(FT8="","",'Name List'!$I$4) | GC8: =IF(GA8=0,"",GA8+GB8) | GH8: =IF(GC8="","",'Name List'!$I$4) | GL8: =IF(GJ8=0,"",GJ8+GK8) | GQ8: =IF(GL8="","",'Name List'!$I$4) | HD8: =IF(HB8=0,"",HB8+HC8) | HI8: =IF(HD8="","",'Name List'!$I$4) | HM8: =IF(HK8=0,"",HK8+HL8) | HR8: =IF(HM8="","",'Name List'!$I$4) | IJ8: =IF(IE8="","",'Name List'!$I$4) | QR8: =IF(QM8="","",'Name List'!$I$4) | QT8: =SUM(F8+O8+X8+AG8+AP8+AY8+BH8+BQ8+BZ8+CI8+CR8+DA8+DJ8+DS8+EB8+EK8+ET8+FC8+FL8+FU8+GD8+GM8+GV8+HE8+HN8+HW8+IF8+IO8+IX8+JG8+JP8+JY8+KH8+KQ8+KZ8+LI8+LR8+MA8+MJ8+MS8+NB8+NK8+NT8+OC8+OL8+OU8+PD8+PM8+PV8+QE8+QN8) -> 0 | QU8: =SUM(G8+P8+Y8+AH8+AQ8+AZ8+BI8+BR8+CA8+CJ8+CS8+DB8+DK8+DT8+EC8+EL8+EU8+FD8+FM8+FV8+GE8+GN8+GW8+HF8+HO8+HX8+IG8+IP8+IY8+JH8+JQ8+JZ8+KI8+KR8+LA8+LJ8+LS8+MB8+MK8+MT8+NC8+NL8+NU8+OD8+OM8+OV8+PE8+PN8+PW8+QF8+QO8) -> 4 | QV8: =SUM(H8+Q8+Z8+AI8+AR8+BA8+BJ8+BS8+CB8+CK8+CT8+DC8+DL8+DU8+ED8+EM8+EV8+FE8+FN8+FW8+GF8+GO8+GX8+HG8+HP8+HY8+IH8+IQ8+IZ8+JI8+JR8+KA8+KJ8+KS8+LB8+LK8+LT8+MC8+ML8+MU8+ND8+NM8+NV8+OE8+ON8+OW8+PF8+PO8+PX8+QG8+QP8) -> 30 | QW8: =SUM(I8+R8+AA8+AJ8+AS8+BB8+BK8+BT8+CC8+CL8+CU8+DD8+DM8+DV8+EE8+EN8+EW8+FF8+FO8+FX8+GG8+GP8+GY8+HH8+HQ8+HZ8+II8+IR8+JA8+JJ8+JS8+KB8+KK8+KT8+LC8+LL8+LU8+MD8+MM8+MV8+NE8+NN8+NW8+OF8+OO8+OX8+PG8+PP8+PY8+QH8+QQ8) -> 19 | QY8: =SUM(J8,S8,AB8,AK8,AT8,BC8,BL8,BU8,CD8,CM8,CV8,DE8,DN8,DW8,EF8,EO8,FP8,FY8,GH8,GQ8,HI8,HR8,IS8,JB8,JK8,JT8,KC8,KL8,KU8,LD8,LM8,LV8,ME8,MN8,MW8,NF8,NO8,NX8,OG8,OP8,OY8,PH8,PZ8)/5 -> 7 | RA8: =MAX(C8,L8,AD8,AM8,AV8,BN8,BW8,CF8,CX8,DG8,DP8,DY8,EH8,FI8,FR8,GA8,GJ8,HK8,IL8,IU8,JD8,JM8,JV8,KE8,KW8,LO8,LX8,MG8,MP8,MY8,NH8,NQ8,OI8,PA8,PS8) -> 18 | RB8: =MAX(D8,M8,AE8,AN8,AW8,BO8,BX8,CG8,CY8,DH8,DQ8,DZ8,EI8,FJ8,FS8,GB8,GK8,HL8,IM8,IV8,JE8,JN8,JW8,KF8,KX8,LP8,LY8,MH8,MQ8,MZ8,NI8,NR8,OJ8,PB8,PT8) -> 17 | RC8: =MAX(E8,N8,AF8,AO8,AX8,BP8,BY8,CH8,CZ8,DI8,DR8,EA8,EJ8,FK8,FT8,GC8,GL8,HM8,IN8,IW8,JF8,JO8,JX8,KG8,KY8,LQ8,LZ8,MI8,MR8,NA8,NJ8,NS8,OK8,PC8,PU8) -> 33 | RD8: =MIN(C8,L8,AD8,AM8,AV8,BN8,BW8,CF8,CX8,DG8,DP8,DY8,EH8,FI8,FR8,GA8,GJ8,HK8,IL8,IU8,JD8,JM8,JV8,KE8,KW8,LO8,LX8,MG8,MP8,MY8,NH8,NQ8,OI8,PA8,PS8) -> 9 | RE8: =MIN(D8,M8,AE8,AN8,AW8,BO8,BX8,CG8,CY8,DH8,DQ8,DZ8,EI8,FJ8,FS8,GB8,GK8,HL8,IM8,IV8,JE8,JN8,JW8,KF8,KX8,LP8,LY8,MH8,MQ8,MZ8,NI8,NR8,OJ8,PB8,PT8) -> 9 | RF8: =MIN(E8,N8,AF8,AO8,AX8,BP8,BY8,CH8,CZ8,DI8,DR8,EA8,EJ8,FK8,FT8,GC8,GL8,HM8,IN8,IW8,JF8,JO8,JX8,KG8,KY8,LQ8,LZ8,MI8,MR8,NA8,NJ8,NS8,OK8,PC8,PU8) -> 26 | RH8: =MAX(W8,BG8,CQ8,HD8,LH8,OB8,OT8) -> 34 | RI8: =MIN(W8,BG8,CQ8,HD8,LH8,OB8,OT8) -> 25 | RK8: =IFERROR(SUM(E8,N8,W8,AF8,AO8,AX8,BG8,BP8,BY8,CH8,CQ8,CZ8,DI8,DR8,EA8,EJ8,FK8,GC8,GL8,HD8,HM8,IN8,IW8,JF8,JO8,JX8,KG8,KY8,LH8,LQ8,LZ8,MI8,MR8,NA8,NJ8,NS8,OB8,OK8,OT8,PC8,)/QY8,0) -> 28.571429 | RM8: =MAX(ES8,IE8) -> 0 | RN8: =MIN(ES8,IE8) -> 0 | RP8: =SUM(EX8,IJ8)/5 -> 0
A9: ='Name List'!B9 -> Chris Burroughs | E9: =IF(C9=0,"",C9+D9) | J9: =IF(E9="","",'Name List'!$I$4) | U9: 18 | V9: 18 | W9: =IF(U9=0,"",U9+V9) -> 36 | X9: 0 | Y9: 2 | Z9: 9 | AA9: 0 | AB9: =IF(W9="","",'Name List'!$I$4) -> 5 | AF9: =IF(AD9=0,"",AD9+AE9) | AK9: =IF(AF9="","",'Name List'!$I$4) | AO9: =IF(AM9=0,"",AM9+AN9) | AT9: =IF(AO9="","",'Name List'!$I$4) | AX9: =IF(AV9=0,"",AV9+AW9) | BC9: =IF(AX9="","",'Name List'!$I$4) | BG9: =IF(BE9=0,"",BE9+BF9) | BL9: =IF(BG9="","",'Name List'!$I$4) | BY9: =IF(BW9=0,"",BW9+BX9) | CD9: =IF(BY9="","",'Name List'!$I$4) | CH9: =IF(CF9=0,"",CF9+CG9) | CM9: =IF(CH9="","",'Name List'!$I$4) | CQ9: =IF(CO9=0,"",CO9+CP9) | CV9: =IF(CQ9="","",'Name List'!$I$4) | CZ9: =IF(CX9=0,"",CX9+CY9) | DE9: =IF(CZ9="","",'Name List'!$I$4) | DI9: =IF(DG9=0,"",DG9+DH9) | DN9: =IF(DI9="","",'Name List'!$I$4) | DR9: =IF(DP9=0,"",DP9+DQ9) | DW9: =IF(DR9="","",'Name List'!$I$4) | EA9: =IF(DY9=0,"",DY9+DZ9) | EF9: =IF(EA9="","",'Name List'!$I$4) | EJ9: =IF(EH9=0,"",EH9+EI9) | EO9: =IF(EJ9="","",'Name List'!$I$4) | EX9: =IF(ES9="","",'Name List'!$I$4) | FI9: 16 | FJ9: 13 | FK9: =IF(FI9=0,"",FI9+FJ9) -> 29 | FL9: 0 | FM9: 0 | FN9: 8 | FO9: 2 | FP9: =IF(FK9="","",'Name List'!$I$4) -> 5 | FT9: =IF(FR9=0,"",FR9+FS9) | FY9: =IF(FT9="","",'Name List'!$I$4) | GC9: =IF(GA9=0,"",GA9+GB9) | GH9: =IF(GC9="","",'Name List'!$I$4) | GL9: =IF(GJ9=0,"",GJ9+GK9) | GQ9: =IF(GL9="","",'Name List'!$I$4) | HD9: =IF(HB9=0,"",HB9+HC9) | HI9: =IF(HD9="","",'Name List'!$I$4) | HM9: =IF(HK9=0,"",HK9+HL9) | HR9: =IF(HM9="","",'Name List'!$I$4) | IJ9: =IF(IE9="","",'Name List'!$I$4) | QR9: =IF(QM9="","",'Name List'!$I$4) | QT9: =SUM(F9+O9+X9+AG9+AP9+AY9+BH9+BQ9+BZ9+CI9+CR9+DA9+DJ9+DS9+EB9+EK9+ET9+FC9+FL9+FU9+GD9+GM9+GV9+HE9+HN9+HW9+IF9+IO9+IX9+JG9+JP9+JY9+KH9+KQ9+KZ9+LI9+LR9+MA9+MJ9+MS9+NB9+NK9+NT9+OC9+OL9+OU9+PD9+PM9+PV9+QE9+QN9) -> 0 | QU9: =SUM(G9+P9+Y9+AH9+AQ9+AZ9+BI9+BR9+CA9+CJ9+CS9+DB9+DK9+DT9+EC9+EL9+EU9+FD9+FM9+FV9+GE9+GN9+GW9+HF9+HO9+HX9+IG9+IP9+IY9+JH9+JQ9+JZ9+KI9+KR9+LA9+LJ9+LS9+MB9+MK9+MT9+NC9+NL9+NU9+OD9+OM9+OV9+PE9+PN9+PW9+QF9+QO9) -> 2 | QV9: =SUM(H9+Q9+Z9+AI9+AR9+BA9+BJ9+BS9+CB9+CK9+CT9+DC9+DL9+DU9+ED9+EM9+EV9+FE9+FN9+FW9+GF9+GO9+GX9+HG9+HP9+HY9+IH9+IQ9+IZ9+JI9+JR9+KA9+KJ9+KS9+LB9+LK9+LT9+MC9+ML9+MU9+ND9+NM9+NV9+OE9+ON9+OW9+PF9+PO9+PX9+QG9+QP9) -> 17 | QW9: =SUM(I9+R9+AA9+AJ9+AS9+BB9+BK9+BT9+CC9+CL9+CU9+DD9+DM9+DV9+EE9+EN9+EW9+FF9+FO9+FX9+GG9+GP9+GY9+HH9+HQ9+HZ9+II9+IR9+JA9+JJ9+JS9+KB9+KK9+KT9+LC9+LL9+LU9+MD9+MM9+MV9+NE9+NN9+NW9+OF9+OO9+OX9+PG9+PP9+PY9+QH9+QQ9) -> 2 | QY9: =SUM(J9,S9,AB9,AK9,AT9,BC9,BL9,BU9,CD9,CM9,CV9,DE9,DN9,DW9,EF9,EO9,FP9,FY9,GH9,GQ9,HI9,HR9,IS9,JB9,JK9,JT9,KC9,KL9,KU9,LD9,LM9,LV9,ME9,MN9,MW9,NF9,NO9,NX9,OG9,OP9,OY9,PH9,PZ9)/5 -> 2 | RA9: =MAX(C9,L9,AD9,AM9,AV9,BN9,BW9,CF9,CX9,DG9,DP9,DY9,EH9,FI9,FR9,GA9,GJ9,HK9,IL9,IU9,JD9,JM9,JV9,KE9,KW9,LO9,LX9,MG9,MP9,MY9,NH9,NQ9,OI9,PA9,PS9) -> 16 | RB9: =MAX(D9,M9,AE9,AN9,AW9,BO9,BX9,CG9,CY9,DH9,DQ9,DZ9,EI9,FJ9,FS9,GB9,GK9,HL9,IM9,IV9,JE9,JN9,JW9,KF9,KX9,LP9,LY9,MH9,MQ9,MZ9,NI9,NR9,OJ9,PB9,PT9) -> 13 | RC9: =MAX(E9,N9,AF9,AO9,AX9,BP9,BY9,CH9,CZ9,DI9,DR9,EA9,EJ9,FK9,FT9,GC9,GL9,HM9,IN9,IW9,JF9,JO9,JX9,KG9,KY9,LQ9,LZ9,MI9,MR9,NA9,NJ9,NS9,OK9,PC9,PU9) -> 29 | RD9: =MIN(C9,L9,AD9,AM9,AV9,BN9,BW9,CF9,CX9,DG9,DP9,DY9,EH9,FI9,FR9,GA9,GJ9,HK9,IL9,IU9,JD9,JM9,JV9,KE9,KW9,LO9,LX9,MG9,MP9,MY9,NH9,NQ9,OI9,PA9,PS9) -> 16 | RE9: =MIN(D9,M9,AE9,AN9,AW9,BO9,BX9,CG9,CY9,DH9,DQ9,DZ9,EI9,FJ9,FS9,GB9,GK9,HL9,IM9,IV9,JE9,JN9,JW9,KF9,KX9,LP9,LY9,MH9,MQ9,MZ9,NI9,NR9,OJ9,PB9,PT9) -> 13 | RF9: =MIN(E9,N9,AF9,AO9,AX9,BP9,BY9,CH9,CZ9,DI9,DR9,EA9,EJ9,FK9,FT9,GC9,GL9,HM9,IN9,IW9,JF9,JO9,JX9,KG9,KY9,LQ9,LZ9,MI9,MR9,NA9,NJ9,NS9,OK9,PC9,PU9) -> 29 | RH9: =MAX(W9,BG9,CQ9,HD9,LH9,OB9,OT9) -> 36 | RI9: =MIN(W9,BG9,CQ9,HD9,LH9,OB9,OT9) -> 36 | RK9: =IFERROR(SUM(E9,N9,W9,AF9,AO9,AX9,BG9,BP9,BY9,CH9,CQ9,CZ9,DI9,DR9,EA9,EJ9,FK9,GC9,GL9,HD9,HM9,IN9,IW9,JF9,JO9,JX9,KG9,KY9,LH9,LQ9,LZ9,MI9,MR9,NA9,NJ9,NS9,OB9,OK9,OT9,PC9,)/QY9,0) -> 32.5 | RM9: =MAX(ES9,IE9) -> 0 | RN9: =MIN(ES9,IE9) -> 0 | RP9: =SUM(EX9,IJ9)/5 -> 0
A10: ='Name List'!B10 -> George Burton | E10: =IF(C10=0,"",C10+D10) | J10: =IF(E10="","",'Name List'!$I$4) | W10: =IF(U10=0,"",U10+V10) | AB10: =IF(W10="","",'Name List'!$I$4) | AF10: =IF(AD10=0,"",AD10+AE10) | AK10: =IF(AF10="","",'Name List'!$I$4) | AO10: =IF(AM10=0,"",AM10+AN10) | AT10: =IF(AO10="","",'Name List'!$I$4) | AX10: =IF(AV10=0,"",AV10+AW10) | BC10: =IF(AX10="","",'Name List'!$I$4) | BG10: =IF(BE10=0,"",BE10+BF10) | BL10: =IF(BG10="","",'Name List'!$I$4) | BY10: =IF(BW10=0,"",BW10+BX10) | CD10: =IF(BY10="","",'Name List'!$I$4) | CF10: 13 | CG10: 14 | CH10: =IF(CF10=0,"",CF10+CG10) -> 27 | CI10: 0 | CJ10: 2 | CK10: 6 | CL10: 1 | CM10: =IF(CH10="","",'Name List'!$I$4) -> 5 | CO10: 13 | CP10: 16 | CQ10: =IF(CO10=0,"",CO10+CP10) -> 29 | CR10: 0 | CS10: 3 | CT10: 8 | CU10: 1 | CV10: =IF(CQ10="","",'Name List'!$I$4) -> 5 | CZ10: =IF(CX10=0,"",CX10+CY10) | DE10: =IF(CZ10="","",'Name List'!$I$4) | DI10: =IF(DG10=0,"",DG10+DH10) | DN10: =IF(DI10="","",'Name List'!$I$4) | DR10: =IF(DP10=0,"",DP10+DQ10) | DW10: =IF(DR10="","",'Name List'!$I$4) | EA10: =IF(DY10=0,"",DY10+DZ10) | EF10: =IF(EA10="","",'Name List'!$I$4) | EJ10: =IF(EH10=0,"",EH10+EI10) | EO10: =IF(EJ10="","",'Name List'!$I$4) | EX10: =IF(ES10="","",'Name List'!$I$4) | FK10: =IF(FI10=0,"",FI10+FJ10) | FP10: =IF(FK10="","",'Name List'!$I$4) | FT10: =IF(FR10=0,"",FR10+FS10) | FY10: =IF(FT10="","",'Name List'!$I$4) | GC10: =IF(GA10=0,"",GA10+GB10) | GH10: =IF(GC10="","",'Name List'!$I$4) | GL10: =IF(GJ10=0,"",GJ10+GK10) | GQ10: =IF(GL10="","",'Name List'!$I$4) | HD10: =IF(HB10=0,"",HB10+HC10) | HI10: =IF(HD10="","",'Name List'!$I$4) | HM10: =IF(HK10=0,"",HK10+HL10) | HR10: =IF(HM10="","",'Name List'!$I$4) | IJ10: =IF(IE10="","",'Name List'!$I$4) | QR10: =IF(QM10="","",'Name List'!$I$4) | QT10: =SUM(F10+O10+X10+AG10+AP10+AY10+BH10+BQ10+BZ10+CI10+CR10+DA10+DJ10+DS10+EB10+EK10+ET10+FC10+FL10+FU10+GD10+GM10+GV10+HE10+HN10+HW10+IF10+IO10+IX10+JG10+JP10+JY10+KH10+KQ10+KZ10+LI10+LR10+MA10+MJ10+MS10+NB10+NK10+NT10+OC10+OL10+OU10+PD10+PM10+PV10+QE10+QN10) -> 0 | QU10: =SUM(G10+P10+Y10+AH10+AQ10+AZ10+BI10+BR10+CA10+CJ10+CS10+DB10+DK10+DT10+EC10+EL10+EU10+FD10+FM10+FV10+GE10+GN10+GW10+HF10+HO10+HX10+IG10+IP10+IY10+JH10+JQ10+JZ10+KI10+KR10+LA10+LJ10+LS10+MB10+MK10+MT10+NC10+NL10+NU10+OD10+OM10+OV10+PE10+PN10+PW10+QF10+QO10) -> 5 | QV10: =SUM(H10+Q10+Z10+AI10+AR10+BA10+BJ10+BS10+CB10+CK10+CT10+DC10+DL10+DU10+ED10+EM10+EV10+FE10+FN10+FW10+GF10+GO10+GX10+HG10+HP10+HY10+IH10+IQ10+IZ10+JI10+JR10+KA10+KJ10+KS10+LB10+LK10+LT10+MC10+ML10+MU10+ND10+NM10+NV10+OE10+ON10+OW10+PF10+PO10+PX10+QG10+QP10) -> 14 | QW10: =SUM(I10+R10+AA10+AJ10+AS10+BB10+BK10+BT10+CC10+CL10+CU10+DD10+DM10+DV10+EE10+EN10+EW10+FF10+FO10+FX10+GG10+GP10+GY10+HH10+HQ10+HZ10+II10+IR10+JA10+JJ10+JS10+KB10+KK10+KT10+LC10+LL10+LU10+MD10+MM10+MV10+NE10+NN10+NW10+OF10+OO10+OX10+PG10+PP10+PY10+QH10+QQ10) -> 2 | QY10: =SUM(J10,S10,AB10,AK10,AT10,BC10,BL10,BU10,CD10,CM10,CV10,DE10,DN10,DW10,EF10,EO10,FP10,FY10,GH10,GQ10,HI10,HR10,IS10,JB10,JK10,JT10,KC10,KL10,KU10,LD10,LM10,LV10,ME10,MN10,MW10,NF10,NO10,NX10,OG10,OP10,OY10,PH10,PZ10)/5 -> 2 | RA10: =MAX(C10,L10,AD10,AM10,AV10,BN10,BW10,CF10,CX10,DG10,DP10,DY10,EH10,FI10,FR10,GA10,GJ10,HK10,IL10,IU10,JD10,JM10,JV10,KE10,KW10,LO10,LX10,MG10,MP10,MY10,NH10,NQ10,OI10,PA10,PS10) -> 13 | RB10: =MAX(D10,M10,AE10,AN10,AW10,BO10,BX10,CG10,CY10,DH10,DQ10,DZ10,EI10,FJ10,FS10,GB10,GK10,HL10,IM10,IV10,JE10,JN10,JW10,KF10,KX10,LP10,LY10,MH10,MQ10,MZ10,NI10,NR10,OJ10,PB10,PT10) -> 14 | RC10: =MAX(E10,N10,AF10,AO10,AX10,BP10,BY10,CH10,CZ10,DI10,DR10,EA10,EJ10,FK10,FT10,GC10,GL10,HM10,IN10,IW10,JF10,JO10,JX10,KG10,KY10,LQ10,LZ10,MI10,MR10,NA10,NJ10,NS10,OK10,PC10,PU10) -> 27 | RD10: =MIN(C10,L10,AD10,AM10,AV10,BN10,BW10,CF10,CX10,DG10,DP10,DY10,EH10,FI10,FR10,GA10,GJ10,HK10,IL10,IU10,JD10,JM10,JV10,KE10,KW10,LO10,LX10,MG10,MP10,MY10,NH10,NQ10,OI10,PA10,PS10) -> 13 | RE10: =MIN(D10,M10,AE10,AN10,AW10,BO10,BX10,CG10,CY10,DH10,DQ10,DZ10,EI10,FJ10,FS10,GB10,GK10,HL10,IM10,IV10,JE10,JN10,JW10,KF10,KX10,LP10,LY10,MH10,MQ10,MZ10,NI10,NR10,OJ10,PB10,PT10) -> 14 | RF10: =MIN(E10,N10,AF10,AO10,AX10,BP10,BY10,CH10,CZ10,DI10,DR10,EA10,EJ10,FK10,FT10,GC10,GL10,HM10,IN10,IW10,JF10,JO10,JX10,KG10,KY10,LQ10,LZ10,MI10,MR10,NA10,NJ10,NS10,OK10,PC10,PU10) -> 27 | RH10: =MAX(W10,BG10,CQ10,HD10,LH10,OB10,OT10) -> 29 | RI10: =MIN(W10,BG10,CQ10,HD10,LH10,OB10,OT10) -> 29 | RK10: =IFERROR(SUM(E10,N10,W10,AF10,AO10,AX10,BG10,BP10,BY10,CH10,CQ10,CZ10,DI10,DR10,EA10,EJ10,FK10,GC10,GL10,HD10,HM10,IN10,IW10,JF10,JO10,JX10,KG10,KY10,LH10,LQ10,LZ10,MI10,MR10,NA10,NJ10,NS10,OB10,OK10,OT10,PC10,)/QY10,0) -> 28 | RM10: =MAX(ES10,IE10) -> 0 | RN10: =MIN(ES10,IE10) -> 0 | RP10: =SUM(EX10,IJ10)/5 -> 0
A11: ='Name List'!B11 -> Tom Burton | E11: =IF(C11=0,"",C11+D11) | J11: =IF(E11="","",'Name List'!$I$4) | W11: =IF(U11=0,"",U11+V11) | AB11: =IF(W11="","",'Name List'!$I$4) | AF11: =IF(AD11=0,"",AD11+AE11) | AK11: =IF(AF11="","",'Name List'!$I$4) | AO11: =IF(AM11=0,"",AM11+AN11) | AT11: =IF(AO11="","",'Name List'!$I$4) | AV11: 15 | AW11: 15 | AX11: =IF(AV11=0,"",AV11+AW11) -> 30 | AY11: 0 | AZ11: 1 | BA11: 10 | BB11: 2 | BC11: =IF(AX11="","",'Name List'!$I$4) -> 5 | BG11: =IF(BE11=0,"",BE11+BF11) | BL11: =IF(BG11="","",'Name List'!$I$4) | BY11: =IF(BW11=0,"",BW11+BX11) | CD11: =IF(BY11="","",'Name List'!$I$4) | CF11: 16 | CG11: 13 | CH11: =IF(CF11=0,"",CF11+CG11) -> 29 | CI11: 0 | CJ11: 1 | CK11: 10 | CL11: 2 | CM11: =IF(CH11="","",'Name List'!$I$4) -> 5 | CO11: 15 | CP11: 18 | CQ11: =IF(CO11=0,"",CO11+CP11) -> 33 | CR11: 0 | CS11: 2 | CT11: 11 | CU11: 2 | CV11: =IF(CQ11="","",'Name List'!$I$4) -> 5 | CZ11: =IF(CX11=0,"",CX11+CY11) | DE11: =IF(CZ11="","",'Name List'!$I$4) | DI11: =IF(DG11=0,"",DG11+DH11) | DN11: =IF(DI11="","",'Name List'!$I$4) | DP11: 17 | DQ11: 19 | DR11: =IF(DP11=0,"",DP11+DQ11) -> 36 | DS11: 0 | DT11: 4 | DU11: 9 | DV11: 1 | DW11: =IF(DR11="","",'Name List'!$I$4) -> 5 | EA11: =IF(DY11=0,"",DY11+DZ11) | EF11: =IF(EA11="","",'Name List'!$I$4) | EJ11: =IF(EH11=0,"",EH11+EI11) | EO11: =IF(EJ11="","",'Name List'!$I$4) | EX11: =IF(ES11="","",'Name List'!$I$4) | FK11: =IF(FI11=0,"",FI11+FJ11) | FP11: =IF(FK11="","",'Name List'!$I$4) | FT11: =IF(FR11=0,"",FR11+FS11) | FY11: =IF(FT11="","",'Name List'!$I$4) | GC11: =IF(GA11=0,"",GA11+GB11) | GH11: =IF(GC11="","",'Name List'!$I$4) | GL11: =IF(GJ11=0,"",GJ11+GK11) | GQ11: =IF(GL11="","",'Name List'!$I$4) | HB11: 18 | HC11: 15 | HD11: =IF(HB11=0,"",HB11+HC11) -> 33 | HE11: 0 | HF11: 2 | HG11: 10 | HH11: 2 | HI11: =IF(HD11="","",'Name List'!$I$4) -> 5 | HM11: =IF(HK11=0,"",HK11+HL11) | HR11: =IF(HM11="","",'Name List'!$I$4) | IJ11: =IF(IE11="","",'Name List'!$I$4) | QR11: =IF(QM11="","",'Name List'!$I$4) | QT11: =SUM(F11+O11+X11+AG11+AP11+AY11+BH11+BQ11+BZ11+CI11+CR11+DA11+DJ11+DS11+EB11+EK11+ET11+FC11+FL11+FU11+GD11+GM11+GV11+HE11+HN11+HW11+IF11+IO11+IX11+JG11+JP11+JY11+KH11+KQ11+KZ11+LI11+LR11+MA11+MJ11+MS11+NB11+NK11+NT11+OC11+OL11+OU11+PD11+PM11+PV11+QE11+QN11) -> 0 | QU11: =SUM(G11+P11+Y11+AH11+AQ11+AZ11+BI11+BR11+CA11+CJ11+CS11+DB11+DK11+DT11+EC11+EL11+EU11+FD11+FM11+FV11+GE11+GN11+GW11+HF11+HO11+HX11+IG11+IP11+IY11+JH11+JQ11+JZ11+KI11+KR11+LA11+LJ11+LS11+MB11+MK11+MT11+NC11+NL11+NU11+OD11+OM11+OV11+PE11+PN11+PW11+QF11+QO11) -> 10 | QV11: =SUM(H11+Q11+Z11+AI11+AR11+BA11+BJ11+BS11+CB11+CK11+CT11+DC11+DL11+DU11+ED11+EM11+EV11+FE11+FN11+FW11+GF11+GO11+GX11+HG11+HP11+HY11+IH11+IQ11+IZ11+JI11+JR11+KA11+KJ11+KS11+LB11+LK11+LT11+MC11+ML11+MU11+ND11+NM11+NV11+OE11+ON11+OW11+PF11+PO11+PX11+QG11+QP11) -> 50 | QW11: =SUM(I11+R11+AA11+AJ11+AS11+BB11+BK11+BT11+CC11+CL11+CU11+DD11+DM11+DV11+EE11+EN11+EW11+FF11+FO11+FX11+GG11+GP11+GY11+HH11+HQ11+HZ11+II11+IR11+JA11+JJ11+JS11+KB11+KK11+KT11+LC11+LL11+LU11+MD11+MM11+MV11+NE11+NN11+NW11+OF11+OO11+OX11+PG11+PP11+PY11+QH11+QQ11) -> 9 | QY11: =SUM(J11,S11,AB11,AK11,AT11,BC11,BL11,BU11,CD11,CM11,CV11,DE11,DN11,DW11,EF11,EO11,FP11,FY11,GH11,GQ11,HI11,HR11,IS11,JB11,JK11,JT11,KC11,KL11,KU11,LD11,LM11,LV11,ME11,MN11,MW11,NF11,NO11,NX11,OG11,OP11,OY11,PH11,PZ11)/5 -> 5 | RA11: =MAX(C11,L11,AD11,AM11,AV11,BN11,BW11,CF11,CX11,DG11,DP11,DY11,EH11,FI11,FR11,GA11,GJ11,HK11,IL11,IU11,JD11,JM11,JV11,KE11,KW11,LO11,LX11,MG11,MP11,MY11,NH11,NQ11,OI11,PA11,PS11) -> 17 | RB11: =MAX(D11,M11,AE11,AN11,AW11,BO11,BX11,CG11,CY11,DH11,DQ11,DZ11,EI11,FJ11,FS11,GB11,GK11,HL11,IM11,IV11,JE11,JN11,JW11,KF11,KX11,LP11,LY11,MH11,MQ11,MZ11,NI11,NR11,OJ11,PB11,PT11) -> 19 | RC11: =MAX(E11,N11,AF11,AO11,AX11,BP11,BY11,CH11,CZ11,DI11,DR11,EA11,EJ11,FK11,FT11,GC11,GL11,HM11,IN11,IW11,JF11,JO11,JX11,KG11,KY11,LQ11,LZ11,MI11,MR11,NA11,NJ11,NS11,OK11,PC11,PU11) -> 36 | RD11: =MIN(C11,L11,AD11,AM11,AV11,BN11,BW11,CF11,CX11,DG11,DP11,DY11,EH11,FI11,FR11,GA11,GJ11,HK11,IL11,IU11,JD11,JM11,JV11,KE11,KW11,LO11,LX11,MG11,MP11,MY11,NH11,NQ11,OI11,PA11,PS11) -> 15 | RE11: =MIN(D11,M11,AE11,AN11,AW11,BO11,BX11,CG11,CY11,DH11,DQ11,DZ11,EI11,FJ11,FS11,GB11,GK11,HL11,IM11,IV11,JE11,JN11,JW11,KF11,KX11,LP11,LY11,MH11,MQ11,MZ11,NI11,NR11,OJ11,PB11,PT11) -> 13 | RF11: =MIN(E11,N11,AF11,AO11,AX11,BP11,BY11,CH11,CZ11,DI11,DR11,EA11,EJ11,FK11,FT11,GC11,GL11,HM11,IN11,IW11,JF11,JO11,JX11,KG11,KY11,LQ11,LZ11,MI11,MR11,NA11,NJ11,NS11,OK11,PC11,PU11) -> 29 | RH11: =MAX(W11,BG11,CQ11,HD11,LH11,OB11,OT11) -> 33 | RI11: =MIN(W11,BG11,CQ11,HD11,LH11,OB11,OT11) -> 33 | RK11: =IFERROR(SUM(E11,N11,W11,AF11,AO11,AX11,BG11,BP11,BY11,CH11,CQ11,CZ11,DI11,DR11,EA11,EJ11,FK11,GC11,GL11,HD11,HM11,IN11,IW11,JF11,JO11,JX11,KG11,KY11,LH11,LQ11,LZ11,MI11,MR11,NA11,NJ11,NS11,OB11,OK11,OT11,PC11,)/QY11,0) -> 32.2 | RM11: =MAX(ES11,IE11) -> 0 | RN11: =MIN(ES11,IE11) -> 0 | RP11: =SUM(EX11,IJ11)/5 -> 0
A12: ='Name List'!B12 -> Mike Chubb | E12: =IF(C12=0,"",C12+D12) | J12: =IF(E12="","",'Name List'!$I$4) | W12: =IF(U12=0,"",U12+V12) | AB12: =IF(W12="","",'Name List'!$I$4) | AF12: =IF(AD12=0,"",AD12+AE12) | AK12: =IF(AF12="","",'Name List'!$I$4) | AO12: =IF(AM12=0,"",AM12+AN12) | AT12: =IF(AO12="","",'Name List'!$I$4) | AX12: =IF(AV12=0,"",AV12+AW12) | BC12: =IF(AX12="","",'Name List'!$I$4) | BG12: =IF(BE12=0,"",BE12+BF12) | BL12: =IF(BG12="","",'Name List'!$I$4) | BY12: =IF(BW12=0,"",BW12+BX12) | CD12: =IF(BY12="","",'Name List'!$I$4) | CH12: =IF(CF12=0,"",CF12+CG12) | CM12: =IF(CH12="","",'Name List'!$I$4) | CQ12: =IF(CO12=0,"",CO12+CP12) | CV12: =IF(CQ12="","",'Name List'!$I$4) | CZ12: =IF(CX12=0,"",CX12+CY12) | DE12: =IF(CZ12="","",'Name List'!$I$4) | DI12: =IF(DG12=0,"",DG12+DH12) | DN12: =IF(DI12="","",'Name List'!$I$4) | DR12: =IF(DP12=0,"",DP12+DQ12) | DW12: =IF(DR12="","",'Name List'!$I$4) | EA12: =IF(DY12=0,"",DY12+DZ12) | EF12: =IF(EA12="","",'Name List'!$I$4) | EJ12: =IF(EH12=0,"",EH12+EI12) | EO12: =IF(EJ12="","",'Name List'!$I$4) | EX12: =IF(ES12="","",'Name List'!$I$4) | FI12: 17 | FJ12: 17 | FK12: =IF(FI12=0,"",FI12+FJ12) -> 34 | FL12: 0 | FM12: 0 | FN12: 3 | FO12: 2 | FP12: =IF(FK12="","",'Name List'!$I$4) -> 5 | FT12: =IF(FR12=0,"",FR12+FS12) | FY12: =IF(FT12="","",'Name List'!$I$4) | GC12: =IF(GA12=0,"",GA12+GB12) | GH12: =IF(GC12="","",'Name List'!$I$4) | GL12: =IF(GJ12=0,"",GJ12+GK12) | GQ12: =IF(GL12="","",'Name List'!$I$4) | HD12: =IF(HB12=0,"",HB12+HC12) | HI12: =IF(HD12="","",'Name List'!$I$4) | HM12: =IF(HK12=0,"",HK12+HL12) | HR12: =IF(HM12="","",'Name List'!$I$4) | IJ12: =IF(IE12="","",'Name List'!$I$4) | QR12: =IF(QM12="","",'Name List'!$I$4) | QT12: =SUM(F12+O12+X12+AG12+AP12+AY12+BH12+BQ12+BZ12+CI12+CR12+DA12+DJ12+DS12+EB12+EK12+ET12+FC12+FL12+FU12+GD12+GM12+GV12+HE12+HN12+HW12+IF12+IO12+IX12+JG12+JP12+JY12+KH12+KQ12+KZ12+LI12+LR12+MA12+MJ12+MS12+NB12+NK12+NT12+OC12+OL12+OU12+PD12+PM12+PV12+QE12+QN12) -> 0 | QU12: =SUM(G12+P12+Y12+AH12+AQ12+AZ12+BI12+BR12+CA12+CJ12+CS12+DB12+DK12+DT12+EC12+EL12+EU12+FD12+FM12+FV12+GE12+GN12+GW12+HF12+HO12+HX12+IG12+IP12+IY12+JH12+JQ12+JZ12+KI12+KR12+LA12+LJ12+LS12+MB12+MK12+MT12+NC12+NL12+NU12+OD12+OM12+OV12+PE12+PN12+PW12+QF12+QO12) -> 0 | QV12: =SUM(H12+Q12+Z12+AI12+AR12+BA12+BJ12+BS12+CB12+CK12+CT12+DC12+DL12+DU12+ED12+EM12+EV12+FE12+FN12+FW12+GF12+GO12+GX12+HG12+HP12+HY12+IH12+IQ12+IZ12+JI12+JR12+KA12+KJ12+KS12+LB12+LK12+LT12+MC12+ML12+MU12+ND12+NM12+NV12+OE12+ON12+OW12+PF12+PO12+PX12+QG12+QP12) -> 3 | QW12: =SUM(I12+R12+AA12+AJ12+AS12+BB12+BK12+BT12+CC12+CL12+CU12+DD12+DM12+DV12+EE12+EN12+EW12+FF12+FO12+FX12+GG12+GP12+GY12+HH12+HQ12+HZ12+II12+IR12+JA12+JJ12+JS12+KB12+KK12+KT12+LC12+LL12+LU12+MD12+MM12+MV12+NE12+NN12+NW12+OF12+OO12+OX12+PG12+PP12+PY12+QH12+QQ12) -> 2 | QY12: =SUM(J12,S12,AB12,AK12,AT12,BC12,BL12,BU12,CD12,CM12,CV12,DE12,DN12,DW12,EF12,EO12,FP12,FY12,GH12,GQ12,HI12,HR12,IS12,JB12,JK12,JT12,KC12,KL12,KU12,LD12,LM12,LV12,ME12,MN12,MW12,NF12,NO12,NX12,OG12,OP12,OY12,PH12,PZ12)/5 -> 1 | RA12: =MAX(C12,L12,AD12,AM12,AV12,BN12,BW12,CF12,CX12,DG12,DP12,DY12,EH12,FI12,FR12,GA12,GJ12,HK12,IL12,IU12,JD12,JM12,JV12,KE12,KW12,LO12,LX12,MG12,MP12,MY12,NH12,NQ12,OI12,PA12,PS12) -> 17 | RB12: =MAX(D12,M12,AE12,AN12,AW12,BO12,BX12,CG12,CY12,DH12,DQ12,DZ12,EI12,FJ12,FS12,GB12,GK12,HL12,IM12,IV12,JE12,JN12,JW12,KF12,KX12,LP12,LY12,MH12,MQ12,MZ12,NI12,NR12,OJ12,PB12,PT12) -> 17 | RC12: =MAX(E12,N12,AF12,AO12,AX12,BP12,BY12,CH12,CZ12,DI12,DR12,EA12,EJ12,FK12,FT12,GC12,GL12,HM12,IN12,IW12,JF12,JO12,JX12,KG12,KY12,LQ12,LZ12,MI12,MR12,NA12,NJ12,NS12,OK12,PC12,PU12) -> 34 | RD12: =MIN(C12,L12,AD12,AM12,AV12,BN12,BW12,CF12,CX12,DG12,DP12,DY12,EH12,FI12,FR12,GA12,GJ12,HK12,IL12,IU12,JD12,JM12,JV12,KE12,KW12,LO12,LX12,MG12,MP12,MY12,NH12,NQ12,OI12,PA12,PS12) -> 17 | RE12: =MIN(D12,M12,AE12,AN12,AW12,BO12,BX12,CG12,CY12,DH12,DQ12,DZ12,EI12,FJ12,FS12,GB12,GK12,HL12,IM12,IV12,JE12,JN12,JW12,KF12,KX12,LP12,LY12,MH12,MQ12,MZ12,NI12,NR12,OJ12,PB12,PT12) -> 17 | RF12: =MIN(E12,N12,AF12,AO12,AX12,BP12,BY12,CH12,CZ12,DI12,DR12,EA12,EJ12,FK12,FT12,GC12,GL12,HM12,IN12,IW12,JF12,JO12,JX12,KG12,KY12,LQ12,LZ12,MI12,MR12,NA12,NJ12,NS12,OK12,PC12,PU12) -> 34 | RH12: =MAX(W12,BG12,CQ12,HD12,LH12,OB12,OT12) -> 0 | RI12: =MIN(W12,BG12,CQ12,HD12,LH12,OB12,OT12) -> 0 | RK12: =IFERROR(SUM(E12,N12,W12,AF12,AO12,AX12,BG12,BP12,BY12,CH12,CQ12,CZ12,DI12,DR12,EA12,EJ12,FK12,GC12,GL12,HD12,HM12,IN12,IW12,JF12,JO12,JX12,KG12,KY12,LH12,LQ12,LZ12,MI12,MR12,NA12,NJ12,NS12,OB12,OK12,OT12,PC12,)/QY12,0) -> 34 | RM12: =MAX(ES12,IE12) -> 0 | RN12: =MIN(ES12,IE12) -> 0 | RP12: =SUM(EX12,IJ12)/5 -> 0
A13: ='Name List'!B13 -> George Clarke | E13: =IF(C13=0,"",C13+D13) | J13: =IF(E13="","",'Name List'!$I$4) | W13: =IF(U13=0,"",U13+V13) | AB13: =IF(W13="","",'Name List'!$I$4) | AF13: =IF(AD13=0,"",AD13+AE13) | AK13: =IF(AF13="","",'Name List'!$I$4) | AO13: =IF(AM13=0,"",AM13+AN13) | AT13: =IF(AO13="","",'Name List'!$I$4) | AX13: =IF(AV13=0,"",AV13+AW13) | BC13: =IF(AX13="","",'Name List'!$I$4) | BG13: =IF(BE13=0,"",BE13+BF13) | BL13: =IF(BG13="","",'Name List'!$I$4) | BY13: =IF(BW13=0,"",BW13+BX13) | CD13: =IF(BY13="","",'Name List'!$I$4) | CH13: =IF(CF13=0,"",CF13+CG13) | CM13: =IF(CH13="","",'Name List'!$I$4) | CQ13: =IF(CO13=0,"",CO13+CP13) | CV13: =IF(CQ13="","",'Name List'!$I$4) | CZ13: =IF(CX13=0,"",CX13+CY13) | DE13: =IF(CZ13="","",'Name List'!$I$4) | DI13: =IF(DG13=0,"",DG13+DH13) | DN13: =IF(DI13="","",'Name List'!$I$4) | DP13: 17 | DQ13: 18 | DR13: =IF(DP13=0,"",DP13+DQ13) -> 35 | DS13: 0 | DT13: 1 | DU13: 7 | DV13: 1 | DW13: =IF(DR13="","",'Name List'!$I$4) -> 5 | EA13: =IF(DY13=0,"",DY13+DZ13) | EF13: =IF(EA13="","",'Name List'!$I$4) | EJ13: =IF(EH13=0,"",EH13+EI13) | EO13: =IF(EJ13="","",'Name List'!$I$4) | EX13: =IF(ES13="","",'Name List'!$I$4) | FK13: =IF(FI13=0,"",FI13+FJ13) | FP13: =IF(FK13="","",'Name List'!$I$4) | FT13: =IF(FR13=0,"",FR13+FS13) | FY13: =IF(FT13="","",'Name List'!$I$4) | GC13: =IF(GA13=0,"",GA13+GB13) | GH13: =IF(GC13="","",'Name List'!$I$4) | GL13: =IF(GJ13=0,"",GJ13+GK13) | GQ13: =IF(GL13="","",'Name List'!$I$4) | HD13: =IF(HB13=0,"",HB13+HC13) | HI13: =IF(HD13="","",'Name List'!$I$4) | HM13: =IF(HK13=0,"",HK13+HL13) | HR13: =IF(HM13="","",'Name List'!$I$4) | IJ13: =IF(IE13="","",'Name List'!$I$4) | QR13: =IF(QM13="","",'Name List'!$I$4) | QT13: =SUM(F13+O13+X13+AG13+AP13+AY13+BH13+BQ13+BZ13+CI13+CR13+DA13+DJ13+DS13+EB13+EK13+ET13+FC13+FL13+FU13+GD13+GM13+GV13+HE13+HN13+HW13+IF13+IO13+IX13+JG13+JP13+JY13+KH13+KQ13+KZ13+LI13+LR13+MA13+MJ13+MS13+NB13+NK13+NT13+OC13+OL13+OU13+PD13+PM13+PV13+QE13+QN13) -> 0 | QU13: =SUM(G13+P13+Y13+AH13+AQ13+AZ13+BI13+BR13+CA13+CJ13+CS13+DB13+DK13+DT13+EC13+EL13+EU13+FD13+FM13+FV13+GE13+GN13+GW13+HF13+HO13+HX13+IG13+IP13+IY13+JH13+JQ13+JZ13+KI13+KR13+LA13+LJ13+LS13+MB13+MK13+MT13+NC13+NL13+NU13+OD13+OM13+OV13+PE13+PN13+PW13+QF13+QO13) -> 1 | QV13: =SUM(H13+Q13+Z13+AI13+AR13+BA13+BJ13+BS13+CB13+CK13+CT13+DC13+DL13+DU13+ED13+EM13+EV13+FE13+FN13+FW13+GF13+GO13+GX13+HG13+HP13+HY13+IH13+IQ13+IZ13+JI13+JR13+KA13+KJ13+KS13+LB13+LK13+LT13+MC13+ML13+MU13+ND13+NM13+NV13+OE13+ON13+OW13+PF13+PO13+PX13+QG13+QP13) -> 7 | QW13: =SUM(I13+R13+AA13+AJ13+AS13+BB13+BK13+BT13+CC13+CL13+CU13+DD13+DM13+DV13+EE13+EN13+EW13+FF13+FO13+FX13+GG13+GP13+GY13+HH13+HQ13+HZ13+II13+IR13+JA13+JJ13+JS13+KB13+KK13+KT13+LC13+LL13+LU13+MD13+MM13+MV13+NE13+NN13+NW13+OF13+OO13+OX13+PG13+PP13+PY13+QH13+QQ13) -> 1 | QY13: =SUM(J13,S13,AB13,AK13,AT13,BC13,BL13,BU13,CD13,CM13,CV13,DE13,DN13,DW13,EF13,EO13,FP13,FY13,GH13,GQ13,HI13,HR13,IS13,JB13,JK13,JT13,KC13,KL13,KU13,LD13,LM13,LV13,ME13,MN13,MW13,NF13,NO13,NX13,OG13,OP13,OY13,PH13,PZ13)/5 -> 1 | RA13: =MAX(C13,L13,AD13,AM13,AV13,BN13,BW13,CF13,CX13,DG13,DP13,DY13,EH13,FI13,FR13,GA13,GJ13,HK13,IL13,IU13,JD13,JM13,JV13,KE13,KW13,LO13,LX13,MG13,MP13,MY13,NH13,NQ13,OI13,PA13,PS13) -> 17 | RB13: =MAX(D13,M13,AE13,AN13,AW13,BO13,BX13,CG13,CY13,DH13,DQ13,DZ13,EI13,FJ13,FS13,GB13,GK13,HL13,IM13,IV13,JE13,JN13,JW13,KF13,KX13,LP13,LY13,MH13,MQ13,MZ13,NI13,NR13,OJ13,PB13,PT13) -> 18 | RC13: =MAX(E13,N13,AF13,AO13,AX13,BP13,BY13,CH13,CZ13,DI13,DR13,EA13,EJ13,FK13,FT13,GC13,GL13,HM13,IN13,IW13,JF13,JO13,JX13,KG13,KY13,LQ13,LZ13,MI13,MR13,NA13,NJ13,NS13,OK13,PC13,PU13) -> 35 | RD13: =MIN(C13,L13,AD13,AM13,AV13,BN13,BW13,CF13,CX13,DG13,DP13,DY13,EH13,FI13,FR13,GA13,GJ13,HK13,IL13,IU13,JD13,JM13,JV13,KE13,KW13,LO13,LX13,MG13,MP13,MY13,NH13,NQ13,OI13,PA13,PS13) -> 17 | RE13: =MIN(D13,M13,AE13,AN13,AW13,BO13,BX13,CG13,CY13,DH13,DQ13,DZ13,EI13,FJ13,FS13,GB13,GK13,HL13,IM13,IV13,JE13,JN13,JW13,KF13,KX13,LP13,LY13,MH13,MQ13,MZ13,NI13,NR13,OJ13,PB13,PT13) -> 18 | RF13: =MIN(E13,N13,AF13,AO13,AX13,BP13,BY13,CH13,CZ13,DI13,DR13,EA13,EJ13,FK13,FT13,GC13,GL13,HM13,IN13,IW13,JF13,JO13,JX13,KG13,KY13,LQ13,LZ13,MI13,MR13,NA13,NJ13,NS13,OK13,PC13,PU13) -> 35 | RH13: =MAX(W13,BG13,CQ13,HD13,LH13,OB13,OT13) -> 0 | RI13: =MIN(W13,BG13,CQ13,HD13,LH13,OB13,OT13) -> 0 | RK13: =IFERROR(SUM(E13,N13,W13,AF13,AO13,AX13,BG13,BP13,BY13,CH13,CQ13,CZ13,DI13,DR13,EA13,EJ13,FK13,GC13,GL13,HD13,HM13,IN13,IW13,JF13,JO13,JX13,KG13,KY13,LH13,LQ13,LZ13,MI13,MR13,NA13,NJ13,NS13,OB13,OK13,OT13,PC13,)/QY13,0) -> 35 | RM13: =MAX(ES13,IE13) -> 0 | RN13: =MIN(ES13,IE13) -> 0 | RP13: =SUM(EX13,IJ13)/5 -> 0
A14: ='Name List'!B14 -> Paul Clarke | E14: =IF(C14=0,"",C14+D14) | J14: =IF(E14="","",'Name List'!$I$4) | W14: =IF(U14=0,"",U14+V14) | AB14: =IF(W14="","",'Name List'!$I$4) | AD14: 16 | AE14: 18 | AF14: =IF(AD14=0,"",AD14+AE14) -> 34 | AG14: 0 | AH14: 0 | AI14: 7 | AJ14: 1 | AK14: =IF(AF14="","",'Name List'!$I$4) -> 5 | AM14: 21 | AN14: 16 | AO14: =IF(AM14=0,"",AM14+AN14) -> 37 | AP14: 0 | AQ14: 3 | AR14: 3 | AS14: 0 | AT14: =IF(AO14="","",'Name List'!$I$4) -> 5 | AX14: =IF(AV14=0,"",AV14+AW14) | BC14: =IF(AX14="","",'Name List'!$I$4) | BE14: 17 | BF14: 14 | BG14: =IF(BE14=0,"",BE14+BF14) -> 31 | BH14: 0 | BI14: 0 | BJ14: 4 | BK14: 1 | BL14: =IF(BG14="","",'Name List'!$I$4) -> 5 | BY14: =IF(BW14=0,"",BW14+BX14) | CD14: =IF(BY14="","",'Name List'!$I$4) | CH14: =IF(CF14=0,"",CF14+CG14) | CM14: =IF(CH14="","",'Name List'!$I$4) | CQ14: =IF(CO14=0,"",CO14+CP14) | CV14: =IF(CQ14="","",'Name List'!$I$4) | CX14: 16 | CY14: 15 | CZ14: =IF(CX14=0,"",CX14+CY14) -> 31 | DA14: 0 | DB14: 1 | DC14: 6 | DD14: 1 | DE14: =IF(CZ14="","",'Name List'!$I$4) -> 5 | DG14: 12 | DH14: 10 | DI14: =IF(DG14=0,"",DG14+DH14) -> 22 | DJ14: 0 | DK14: 0 | DL14: 4 | DM14: 7 | DN14: =IF(DI14="","",'Name List'!$I$4) -> 5 | DP14: 17 | DQ14: 11 | DR14: =IF(DP14=0,"",DP14+DQ14) -> 28 | DS14: 0 | DT14: 0 | DU14: 6 | DV14: 2 | DW14: =IF(DR14="","",'Name List'!$I$4) -> 5 | EA14: =IF(DY14=0,"",DY14+DZ14) | EF14: =IF(EA14="","",'Name List'!$I$4) | EH14: 14 | EI14: 16 | EJ14: =IF(EH14=0,"",EH14+EI14) -> 30 | EK14: 0 | EL14: 1 | EM14: 3 | EN14: 0 | EO14: =IF(EJ14="","",'Name List'!$I$4) -> 5 | EX14: =IF(ES14="","",'Name List'!$I$4) | FK14: =IF(FI14=0,"",FI14+FJ14) | FP14: =IF(FK14="","",'Name List'!$I$4) | FR14: 15 | FS14: 4 | FT14: =IF(FR14=0,"",FR14+FS14) -> 19 | FU14: 0 | FV14: 0 | FW14: 3 | FX14: 6 | FY14: =IF(FT14="","",'Name List'!$I$4) -> 5 | GC14: =IF(GA14=0,"",GA14+GB14) | GH14: =IF(GC14="","",'Name List'!$I$4) | GL14: =IF(GJ14=0,"",GJ14+GK14) | GQ14: =IF(GL14="","",'Name List'!$I$4) | HD14: =IF(HB14=0,"",HB14+HC14) | HI14: =IF(HD14="","",'Name List'!$I$4) | HM14: =IF(HK14=0,"",HK14+HL14) | HR14: =IF(HM14="","",'Name List'!$I$4) | IJ14: =IF(IE14="","",'Name List'!$I$4) | QR14: =IF(QM14="","",'Name List'!$I$4) | QT14: =SUM(F14+O14+X14+AG14+AP14+AY14+BH14+BQ14+BZ14+CI14+CR14+DA14+DJ14+DS14+EB14+EK14+ET14+FC14+FL14+FU14+GD14+GM14+GV14+HE14+HN14+HW14+IF14+IO14+IX14+JG14+JP14+JY14+KH14+KQ14+KZ14+LI14+LR14+MA14+MJ14+MS14+NB14+NK14+NT14+OC14+OL14+OU14+PD14+PM14+PV14+QE14+QN14) -> 0 | QU14: =SUM(G14+P14+Y14+AH14+AQ14+AZ14+BI14+BR14+CA14+CJ14+CS14+DB14+DK14+DT14+EC14+EL14+EU14+FD14+FM14+FV14+GE14+GN14+GW14+HF14+HO14+HX14+IG14+IP14+IY14+JH14+JQ14+JZ14+KI14+KR14+LA14+LJ14+LS14+MB14+MK14+MT14+NC14+NL14+NU14+OD14+OM14+OV14+PE14+PN14+PW14+QF14+QO14) -> 5 | QV14: =SUM(H14+Q14+Z14+AI14+AR14+BA14+BJ14+BS14+CB14+CK14+CT14+DC14+DL14+DU14+ED14+EM14+EV14+FE14+FN14+FW14+GF14+GO14+GX14+HG14+HP14+HY14+IH14+IQ14+IZ14+JI14+JR14+KA14+KJ14+KS14+LB14+LK14+LT14+MC14+ML14+MU14+ND14+NM14+NV14+OE14+ON14+OW14+PF14+PO14+PX14+QG14+QP14) -> 36 | QW14: =SUM(I14+R14+AA14+AJ14+AS14+BB14+BK14+BT14+CC14+CL14+CU14+DD14+DM14+DV14+EE14+EN14+EW14+FF14+FO14+FX14+GG14+GP14+GY14+HH14+HQ14+HZ14+II14+IR14+JA14+JJ14+JS14+KB14+KK14+KT14+LC14+LL14+LU14+MD14+MM14+MV14+NE14+NN14+NW14+OF14+OO14+OX14+PG14+PP14+PY14+QH14+QQ14) -> 18 | QY14: =SUM(J14,S14,AB14,AK14,AT14,BC14,BL14,BU14,CD14,CM14,CV14,DE14,DN14,DW14,EF14,EO14,FP14,FY14,GH14,GQ14,HI14,HR14,IS14,JB14,JK14,JT14,KC14,KL14,KU14,LD14,LM14,LV14,ME14,MN14,MW14,NF14,NO14,NX14,OG14,OP14,OY14,PH14,PZ14)/5 -> 8 | RA14: =MAX(C14,L14,AD14,AM14,AV14,BN14,BW14,CF14,CX14,DG14,DP14,DY14,EH14,FI14,FR14,GA14,GJ14,HK14,IL14,IU14,JD14,JM14,JV14,KE14,KW14,LO14,LX14,MG14,MP14,MY14,NH14,NQ14,OI14,PA14,PS14) -> 21 | RB14: =MAX(D14,M14,AE14,AN14,AW14,BO14,BX14,CG14,CY14,DH14,DQ14,DZ14,EI14,FJ14,FS14,GB14,GK14,HL14,IM14,IV14,JE14,JN14,JW14,KF14,KX14,LP14,LY14,MH14,MQ14,MZ14,NI14,NR14,OJ14,PB14,PT14) -> 18 | RC14: =MAX(E14,N14,AF14,AO14,AX14,BP14,BY14,CH14,CZ14,DI14,DR14,EA14,EJ14,FK14,FT14,GC14,GL14,HM14,IN14,IW14,JF14,JO14,JX14,KG14,KY14,LQ14,LZ14,MI14,MR14,NA14,NJ14,NS14,OK14,PC14,PU14) -> 37 | RD14: =MIN(C14,L14,AD14,AM14,AV14,BN14,BW14,CF14,CX14,DG14,DP14,DY14,EH14,FI14,FR14,GA14,GJ14,HK14,IL14,IU14,JD14,JM14,JV14,KE14,KW14,LO14,LX14,MG14,MP14,MY14,NH14,NQ14,OI14,PA14,PS14) -> 12 | RE14: =MIN(D14,M14,AE14,AN14,AW14,BO14,BX14,CG14,CY14,DH14,DQ14,DZ14,EI14,FJ14,FS14,GB14,GK14,HL14,IM14,IV14,JE14,JN14,JW14,KF14,KX14,LP14,LY14,MH14,MQ14,MZ14,NI14,NR14,OJ14,PB14,PT14) -> 4 | RF14: =MIN(E14,N14,AF14,AO14,AX14,BP14,BY14,CH14,CZ14,DI14,DR14,EA14,EJ14,FK14,FT14,GC14,GL14,HM14,IN14,IW14,JF14,JO14,JX14,KG14,KY14,LQ14,LZ14,MI14,MR14,NA14,NJ14,NS14,OK14,PC14,PU14) -> 19 | RH14: =MAX(W14,BG14,CQ14,HD14,LH14,OB14,OT14) -> 31 | RI14: =MIN(W14,BG14,CQ14,HD14,LH14,OB14,OT14) -> 31 | RK14: =IFERROR(SUM(E14,N14,W14,AF14,AO14,AX14,BG14,BP14,BY14,CH14,CQ14,CZ14,DI14,DR14,EA14,EJ14,FK14,GC14,GL14,HD14,HM14,IN14,IW14,JF14,JO14,JX14,KG14,KY14,LH14,LQ14,LZ14,MI14,MR14,NA14,NJ14,NS14,OB14,OK14,OT14,PC14,)/QY14,0) -> 26.625 | RM14: =MAX(ES14,IE14) -> 0 | RN14: =MIN(ES14,IE14) -> 0 | RP14: =SUM(EX14,IJ14)/5 -> 0
A15: ='Name List'!B15 -> Martin Coomber | E15: =IF(C15=0,"",C15+D15) | J15: =IF(E15="","",'Name List'!$I$4) | U15: 12 | V15: 18 | W15: =IF(U15=0,"",U15+V15) -> 30 | X15: 0 | Y15: 0 | Z15: 9 | AA15: 2 | AB15: =IF(W15="","",'Name List'!$I$4) -> 5 | AD15: 17 | AE15: 16 | AF15: =IF(AD15=0,"",AD15+AE15) -> 33 | AG15: 0 | AH15: 0 | AI15: 3 | AJ15: 0 | AK15: =IF(AF15="","",'Name List'!$I$4) -> 5 | AM15: 20 | AN15: 14 | AO15: =IF(AM15=0,"",AM15+AN15) -> 34 | AP15: 0 | AQ15: 2 | AR15: 7 | AS15: 2 | AT15: =IF(AO15="","",'Name List'!$I$4) -> 5 | AV15: 20 | AW15: 16 | AX15: =IF(AV15=0,"",AV15+AW15) -> 36 | AY15: 0 | AZ15: 2 | BA15: 9 | BB15: 1 | BC15: =IF(AX15="","",'Name List'!$I$4) -> 5 | BE15: 15 | BF15: 18 | BG15: =IF(BE15=0,"",BE15+BF15) -> 33 | BH15: 0 | BI15: 0 | BJ15: 8 | BK15: 0 | BL15: =IF(BG15="","",'Name List'!$I$4) -> 5 | BY15: =IF(BW15=0,"",BW15+BX15) | CD15: =IF(BY15="","",'Name List'!$I$4) | CF15: 16 | CG15: 19 | CH15: =IF(CF15=0,"",CF15+CG15) -> 35 | CI15: 0 | CJ15: 0 | CK15: 12 | CL15: 1 | CM15: =IF(CH15="","",'Name List'!$I$4) -> 5 | CO15: 20 | CP15: 18 | CQ15: =IF(CO15=0,"",CO15+CP15) -> 38 | CR15: 0 | CS15: 3 | CT15: 7 | CU15: 2 | CV15: =IF(CQ15="","",'Name List'!$I$4) -> 5 | CZ15: =IF(CX15=0,"",CX15+CY15) | DE15: =IF(CZ15="","",'Name List'!$I$4) | DI15: =IF(DG15=0,"",DG15+DH15) | DN15: =IF(DI15="","",'Name List'!$I$4) | DP15: 17 | DQ15: 16 | DR15: =IF(DP15=0,"",DP15+DQ15) -> 33 | DS15: 0 | DT15: 1 | DU15: 10 | DV15: 2 | DW15: =IF(DR15="","",'Name List'!$I$4) -> 5 | DY15: 13 | DZ15: 16 | EA15: =IF(DY15=0,"",DY15+DZ15) -> 29 | EB15: 0 | EC15: 1 | ED15: 8 | EE15: 4 | EF15: =IF(EA15="","",'Name List'!$I$4) -> 5 | EJ15: =IF(EH15=0,"",EH15+EI15) | EO15: =IF(EJ15="","",'Name List'!$I$4) | EX15: =IF(ES15="","",'Name List'!$I$4) | FI15: 16 | FJ15: 20 | FK15: =IF(FI15=0,"",FI15+FJ15) -> 36 | FL15: 0 | FM15: 4 | FN15: 6 | FO15: 2 | FP15: =IF(FK15="","",'Name List'!$I$4) -> 5 | FT15: =IF(FR15=0,"",FR15+FS15) | FY15: =IF(FT15="","",'Name List'!$I$4) | GA15: 18 | GB15: 17 | GC15: =IF(GA15=0,"",GA15+GB15) -> 35 | GD15: 0 | GE15: 1 | GF15: 10 | GG15: 1 | GH15: =IF(GC15="","",'Name List'!$I$4) -> 5 | GJ15: 17 | GK15: 18 | GL15: =IF(GJ15=0,"",GJ15+GK15) -> 35 | GM15: 0 | GN15: 2 | GO15: 9 | GP15: 1 | GQ15: =IF(GL15="","",'Name List'!$I$4) -> 5 | HB15: 14 | HC15: 20 | HD15: =IF(HB15=0,"",HB15+HC15) -> 34 | HE15: 0 | HF15: 2 | HG15: 4 | HH15: 2 | HI15: =IF(HD15="","",'Name List'!$I$4) -> 5 | HM15: =IF(HK15=0,"",HK15+HL15) | HR15: =IF(HM15="","",'Name List'!$I$4) | IJ15: =IF(IE15="","",'Name List'!$I$4) | QR15: =IF(QM15="","",'Name List'!$I$4) | QT15: =SUM(F15+O15+X15+AG15+AP15+AY15+BH15+BQ15+BZ15+CI15+CR15+DA15+DJ15+DS15+EB15+EK15+ET15+FC15+FL15+FU15+GD15+GM15+GV15+HE15+HN15+HW15+IF15+IO15+IX15+JG15+JP15+JY15+KH15+KQ15+KZ15+LI15+LR15+MA15+MJ15+MS15+NB15+NK15+NT15+OC15+OL15+OU15+PD15+PM15+PV15+QE15+QN15) -> 0 | QU15: =SUM(G15+P15+Y15+AH15+AQ15+AZ15+BI15+BR15+CA15+CJ15+CS15+DB15+DK15+DT15+EC15+EL15+EU15+FD15+FM15+FV15+GE15+GN15+GW15+HF15+HO15+HX15+IG15+IP15+IY15+JH15+JQ15+JZ15+KI15+KR15+LA15+LJ15+LS15+MB15+MK15+MT15+NC15+NL15+NU15+OD15+OM15+OV15+PE15+PN15+PW15+QF15+QO15) -> 18 | QV15: =SUM(H15+Q15+Z15+AI15+AR15+BA15+BJ15+BS15+CB15+CK15+CT15+DC15+DL15+DU15+ED15+EM15+EV15+FE15+FN15+FW15+GF15+GO15+GX15+HG15+HP15+HY15+IH15+IQ15+IZ15+JI15+JR15+KA15+KJ15+KS15+LB15+LK15+LT15+MC15+ML15+MU15+ND15+NM15+NV15+OE15+ON15+OW15+PF15+PO15+PX15+QG15+QP15) -> 102 | QW15: =SUM(I15+R15+AA15+AJ15+AS15+BB15+BK15+BT15+CC15+CL15+CU15+DD15+DM15+DV15+EE15+EN15+EW15+FF15+FO15+FX15+GG15+GP15+GY15+HH15+HQ15+HZ15+II15+IR15+JA15+JJ15+JS15+KB15+KK15+KT15+LC15+LL15+LU15+MD15+MM15+MV15+NE15+NN15+NW15+OF15+OO15+OX15+PG15+PP15+PY15+QH15+QQ15) -> 20 | QY15: =SUM(J15,S15,AB15,AK15,AT15,BC15,BL15,BU15,CD15,CM15,CV15,DE15,DN15,DW15,EF15,EO15,FP15,FY15,GH15,GQ15,HI15,HR15,IS15,JB15,JK15,JT15,KC15,KL15,KU15,LD15,LM15,LV15,ME15,MN15,MW15,NF15,NO15,NX15,OG15,OP15,OY15,PH15,PZ15)/5 -> 13 | RA15: =MAX(C15,L15,AD15,AM15,AV15,BN15,BW15,CF15,CX15,DG15,DP15,DY15,EH15,FI15,FR15,GA15,GJ15,HK15,IL15,IU15,JD15,JM15,JV15,KE15,KW15,LO15,LX15,MG15,MP15,MY15,NH15,NQ15,OI15,PA15,PS15) -> 20 | RB15: =MAX(D15,M15,AE15,AN15,AW15,BO15,BX15,CG15,CY15,DH15,DQ15,DZ15,EI15,FJ15,FS15,GB15,GK15,HL15,IM15,IV15,JE15,JN15,JW15,KF15,KX15,LP15,LY15,MH15,MQ15,MZ15,NI15,NR15,OJ15,PB15,PT15) -> 20 | RC15: =MAX(E15,N15,AF15,AO15,AX15,BP15,BY15,CH15,CZ15,DI15,DR15,EA15,EJ15,FK15,FT15,GC15,GL15,HM15,IN15,IW15,JF15,JO15,JX15,KG15,KY15,LQ15,LZ15,MI15,MR15,NA15,NJ15,NS15,OK15,PC15,PU15) -> 36 | RD15: =MIN(C15,L15,AD15,AM15,AV15,BN15,BW15,CF15,CX15,DG15,DP15,DY15,EH15,FI15,FR15,GA15,GJ15,HK15,IL15,IU15,JD15,JM15,JV15,KE15,KW15,LO15,LX15,MG15,MP15,MY15,NH15,NQ15,OI15,PA15,PS15) -> 13 | RE15: =MIN(D15,M15,AE15,AN15,AW15,BO15,BX15,CG15,CY15,DH15,DQ15,DZ15,EI15,FJ15,FS15,GB15,GK15,HL15,IM15,IV15,JE15,JN15,JW15,KF15,KX15,LP15,LY15,MH15,MQ15,MZ15,NI15,NR15,OJ15,PB15,PT15) -> 14 | RF15: =MIN(E15,N15,AF15,AO15,AX15,BP15,BY15,CH15,CZ15,DI15,DR15,EA15,EJ15,FK15,FT15,GC15,GL15,HM15,IN15,IW15,JF15,JO15,JX15,KG15,KY15,LQ15,LZ15,MI15,MR15,NA15,NJ15,NS15,OK15,PC15,PU15) -> 29 | RH15: =MAX(W15,BG15,CQ15,HD15,LH15,OB15,OT15) -> 38 | RI15: =MIN(W15,BG15,CQ15,HD15,LH15,OB15,OT15) -> 30 | RK15: =IFERROR(SUM(E15,N15,W15,AF15,AO15,AX15,BG15,BP15,BY15,CH15,CQ15,CZ15,DI15,DR15,EA15,EJ15,FK15,GC15,GL15,HD15,HM15,IN15,IW15,JF15,JO15,JX15,KG15,KY15,LH15,LQ15,LZ15,MI15,MR15,NA15,NJ15,NS15,OB15,OK15,OT15,PC15,)/QY15,0) -> 33.923077 | RM15: =MAX(ES15,IE15) -> 0 | RN15: =MIN(ES15,IE15) -> 0 | RP15: =SUM(EX15,IJ15)/5 -> 0
A16: ='Name List'!B16 -> Dominic Coughlin | E16: =IF(C16=0,"",C16+D16) | J16: =IF(E16="","",'Name List'!$I$4) | W16: =IF(U16=0,"",U16+V16) | AB16: =IF(W16="","",'Name List'!$I$4) | AF16: =IF(AD16=0,"",AD16+AE16) | AK16: =IF(AF16="","",'Name List'!$I$4) | AM16: 3 | AN16: 16 | AO16: =IF(AM16=0,"",AM16+AN16) -> 19 | AP16: 0 | AQ16: 0 | AR16: 2 | AS16: 8 | AT16: =IF(AO16="","",'Name List'!$I$4) -> 5 | AX16: =IF(AV16=0,"",AV16+AW16) | BC16: =IF(AX16="","",'Name List'!$I$4) | BG16: =IF(BE16=0,"",BE16+BF16) | BL16: =IF(BG16="","",'Name List'!$I$4) | BY16: =IF(BW16=0,"",BW16+BX16) | CD16: =IF(BY16="","",'Name List'!$I$4) | CH16: =IF(CF16=0,"",CF16+CG16) | CM16: =IF(CH16="","",'Name List'!$I$4) | CQ16: =IF(CO16=0,"",CO16+CP16) | CV16: =IF(CQ16="","",'Name List'!$I$4) | CZ16: =IF(CX16=0,"",CX16+CY16) | DE16: =IF(CZ16="","",'Name List'!$I$4) | DI16: =IF(DG16=0,"",DG16+DH16) | DN16: =IF(DI16="","",'Name List'!$I$4) | DR16: =IF(DP16=0,"",DP16+DQ16) | DW16: =IF(DR16="","",'Name List'!$I$4) | EA16: =IF(DY16=0,"",DY16+DZ16) | EF16: =IF(EA16="","",'Name List'!$I$4) | EJ16: =IF(EH16=0,"",EH16+EI16) | EO16: =IF(EJ16="","",'Name List'!$I$4) | EX16: =IF(ES16="","",'Name List'!$I$4) | FK16: =IF(FI16=0,"",FI16+FJ16) | FP16: =IF(FK16="","",'Name List'!$I$4) | FT16: =IF(FR16=0,"",FR16+FS16) | FY16: =IF(FT16="","",'Name List'!$I$4) | GC16: =IF(GA16=0,"",GA16+GB16) | GH16: =IF(GC16="","",'Name List'!$I$4) | GL16: =IF(GJ16=0,"",GJ16+GK16) | GQ16: =IF(GL16="","",'Name List'!$I$4) | HD16: =IF(HB16=0,"",HB16+HC16) | HI16: =IF(HD16="","",'Name List'!$I$4) | HM16: =IF(HK16=0,"",HK16+HL16) | HR16: =IF(HM16="","",'Name List'!$I$4) | IJ16: =IF(IE16="","",'Name List'!$I$4) | QR16: =IF(QM16="","",'Name List'!$I$4) | QT16: =SUM(F16+O16+X16+AG16+AP16+AY16+BH16+BQ16+BZ16+CI16+CR16+DA16+DJ16+DS16+EB16+EK16+ET16+FC16+FL16+FU16+GD16+GM16+GV16+HE16+HN16+HW16+IF16+IO16+IX16+JG16+JP16+JY16+KH16+KQ16+KZ16+LI16+LR16+MA16+MJ16+MS16+NB16+NK16+NT16+OC16+OL16+OU16+PD16+PM16+PV16+QE16+QN16) -> 0 | QU16: =SUM(G16+P16+Y16+AH16+AQ16+AZ16+BI16+BR16+CA16+CJ16+CS16+DB16+DK16+DT16+EC16+EL16+EU16+FD16+FM16+FV16+GE16+GN16+GW16+HF16+HO16+HX16+IG16+IP16+IY16+JH16+JQ16+JZ16+KI16+KR16+LA16+LJ16+LS16+MB16+MK16+MT16+NC16+NL16+NU16+OD16+OM16+OV16+PE16+PN16+PW16+QF16+QO16) -> 0 | QV16: =SUM(H16+Q16+Z16+AI16+AR16+BA16+BJ16+BS16+CB16+CK16+CT16+DC16+DL16+DU16+ED16+EM16+EV16+FE16+FN16+FW16+GF16+GO16+GX16+HG16+HP16+HY16+IH16+IQ16+IZ16+JI16+JR16+KA16+KJ16+KS16+LB16+LK16+LT16+MC16+ML16+MU16+ND16+NM16+NV16+OE16+ON16+OW16+PF16+PO16+PX16+QG16+QP16) -> 2 | QW16: =SUM(I16+R16+AA16+AJ16+AS16+BB16+BK16+BT16+CC16+CL16+CU16+DD16+DM16+DV16+EE16+EN16+EW16+FF16+FO16+FX16+GG16+GP16+GY16+HH16+HQ16+HZ16+II16+IR16+JA16+JJ16+JS16+KB16+KK16+KT16+LC16+LL16+LU16+MD16+MM16+MV16+NE16+NN16+NW16+OF16+OO16+OX16+PG16+PP16+PY16+QH16+QQ16) -> 8 | QY16: =SUM(J16,S16,AB16,AK16,AT16,BC16,BL16,BU16,CD16,CM16,CV16,DE16,DN16,DW16,EF16,EO16,FP16,FY16,GH16,GQ16,HI16,HR16,IS16,JB16,JK16,JT16,KC16,KL16,KU16,LD16,LM16,LV16,ME16,MN16,MW16,NF16,NO16,NX16,OG16,OP16,OY16,PH16,PZ16)/5 -> 1 | RA16: =MAX(C16,L16,AD16,AM16,AV16,BN16,BW16,CF16,CX16,DG16,DP16,DY16,EH16,FI16,FR16,GA16,GJ16,HK16,IL16,IU16,JD16,JM16,JV16,KE16,KW16,LO16,LX16,MG16,MP16,MY16,NH16,NQ16,OI16,PA16,PS16) -> 3 | RB16: =MAX(D16,M16,AE16,AN16,AW16,BO16,BX16,CG16,CY16,DH16,DQ16,DZ16,EI16,FJ16,FS16,GB16,GK16,HL16,IM16,IV16,JE16,JN16,JW16,KF16,KX16,LP16,LY16,MH16,MQ16,MZ16,NI16,NR16,OJ16,PB16,PT16) -> 16 | RC16: =MAX(E16,N16,AF16,AO16,AX16,BP16,BY16,CH16,CZ16,DI16,DR16,EA16,EJ16,FK16,FT16,GC16,GL16,HM16,IN16,IW16,JF16,JO16,JX16,KG16,KY16,LQ16,LZ16,MI16,MR16,NA16,NJ16,NS16,OK16,PC16,PU16) -> 19 | RD16: =MIN(C16,L16,AD16,AM16,AV16,BN16,BW16,CF16,CX16,DG16,DP16,DY16,EH16,FI16,FR16,GA16,GJ16,HK16,IL16,IU16,JD16,JM16,JV16,KE16,KW16,LO16,LX16,MG16,MP16,MY16,NH16,NQ16,OI16,PA16,PS16) -> 3 | RE16: =MIN(D16,M16,AE16,AN16,AW16,BO16,BX16,CG16,CY16,DH16,DQ16,DZ16,EI16,FJ16,FS16,GB16,GK16,HL16,IM16,IV16,JE16,JN16,JW16,KF16,KX16,LP16,LY16,MH16,MQ16,MZ16,NI16,NR16,OJ16,PB16,PT16) -> 16 | RF16: =MIN(E16,N16,AF16,AO16,AX16,BP16,BY16,CH16,CZ16,DI16,DR16,EA16,EJ16,FK16,FT16,GC16,GL16,HM16,IN16,IW16,JF16,JO16,JX16,KG16,KY16,LQ16,LZ16,MI16,MR16,NA16,NJ16,NS16,OK16,PC16,PU16) -> 19 | RH16: =MAX(W16,BG16,CQ16,HD16,LH16,OB16,OT16) -> 0 | RI16: =MIN(W16,BG16,CQ16,HD16,LH16,OB16,OT16) -> 0 | RK16: =IFERROR(SUM(E16,N16,W16,AF16,AO16,AX16,BG16,BP16,BY16,CH16,CQ16,CZ16,DI16,DR16,EA16,EJ16,FK16,GC16,GL16,HD16,HM16,IN16,IW16,JF16,JO16,JX16,KG16,KY16,LH16,LQ16,LZ16,MI16,MR16,NA16,NJ16,NS16,OB16,OK16,OT16,PC16,)/QY16,0) -> 19 | RM16: =MAX(ES16,IE16) -> 0 | RN16: =MIN(ES16,IE16) -> 0 | RP16: =SUM(EX16,IJ16)/5 -> 0
A17: ='Name List'!B17 -> Gareth Davies | E17: =IF(C17=0,"",C17+D17) | J17: =IF(E17="","",'Name List'!$I$4) | U17: 13 | V17: 13 | W17: =IF(U17=0,"",U17+V17) -> 26 | X17: 0 | Y17: 1 | Z17: 4 | AA17: 3 | AB17: =IF(W17="","",'Name List'!$I$4) -> 5 | AF17: =IF(AD17=0,"",AD17+AE17) | AK17: =IF(AF17="","",'Name List'!$I$4) | AO17: =IF(AM17=0,"",AM17+AN17) | AT17: =IF(AO17="","",'Name List'!$I$4) | AX17: =IF(AV17=0,"",AV17+AW17) | BC17: =IF(AX17="","",'Name List'!$I$4) | BG17: =IF(BE17=0,"",BE17+BF17) | BL17: =IF(BG17="","",'Name List'!$I$4) | BY17: =IF(BW17=0,"",BW17+BX17) | CD17: =IF(BY17="","",'Name List'!$I$4) | CH17: =IF(CF17=0,"",CF17+CG17) | CM17: =IF(CH17="","",'Name List'!$I$4) | CQ17: =IF(CO17=0,"",CO17+CP17) | CV17: =IF(CQ17="","",'Name List'!$I$4) | CZ17: =IF(CX17=0,"",CX17+CY17) | DE17: =IF(CZ17="","",'Name List'!$I$4) | DI17: =IF(DG17=0,"",DG17+DH17) | DN17: =IF(DI17="","",'Name List'!$I$4) | DR17: =IF(DP17=0,"",DP17+DQ17) | DW17: =IF(DR17="","",'Name List'!$I$4) | DY17: 16 | DZ17: 13 | EA17: =IF(DY17=0,"",DY17+DZ17) -> 29 | EB17: 0 | EC17: 0 | ED17: 6 | EE17: 3 | EF17: =IF(EA17="","",'Name List'!$I$4) -> 5 | EH17: 18 | EI17: 12 | EJ17: =IF(EH17=0,"",EH17+EI17) -> 30 | EK17: 0 | EL17: 1 | EM17: 6 | EN17: 4 | EO17: =IF(EJ17="","",'Name List'!$I$4) -> 5 | ES17: 82 | ET17: 0 | EU17: 0 | EV17: 9 | EX17: =IF(ES17="","",'Name List'!$I$4) -> 5 | FK17: =IF(FI17=0,"",FI17+FJ17) | FP17: =IF(FK17="","",'Name List'!$I$4) | FT17: =IF(FR17=0,"",FR17+FS17) | FY17: =IF(FT17="","",'Name List'!$I$4) | GC17: =IF(GA17=0,"",GA17+GB17) | GH17: =IF(GC17="","",'Name List'!$I$4) | GJ17: 11 | GK17: 15 | GL17: =IF(GJ17=0,"",GJ17+GK17) -> 26 | GM17: 0 | GN17: 1 | GO17: 6 | GP17: 2 | GQ17: =IF(GL17="","",'Name List'!$I$4) -> 5 | HD17: =IF(HB17=0,"",HB17+HC17) | HI17: =IF(HD17="","",'Name List'!$I$4) | HM17: =IF(HK17=0,"",HK17+HL17) | HR17: =IF(HM17="","",'Name List'!$I$4) | IJ17: =IF(IE17="","",'Name List'!$I$4) | QR17: =IF(QM17="","",'Name List'!$I$4) | QT17: =SUM(F17+O17+X17+AG17+AP17+AY17+BH17+BQ17+BZ17+CI17+CR17+DA17+DJ17+DS17+EB17+EK17+ET17+FC17+FL17+FU17+GD17+GM17+GV17+HE17+HN17+HW17+IF17+IO17+IX17+JG17+JP17+JY17+KH17+KQ17+KZ17+LI17+LR17+MA17+MJ17+MS17+NB17+NK17+NT17+OC17+OL17+OU17+PD17+PM17+PV17+QE17+QN17) -> 0 | QU17: =SUM(G17+P17+Y17+AH17+AQ17+AZ17+BI17+BR17+CA17+CJ17+CS17+DB17+DK17+DT17+EC17+EL17+EU17+FD17+FM17+FV17+GE17+GN17+GW17+HF17+HO17+HX17+IG17+IP17+IY17+JH17+JQ17+JZ17+KI17+KR17+LA17+LJ17+LS17+MB17+MK17+MT17+NC17+NL17+NU17+OD17+OM17+OV17+PE17+PN17+PW17+QF17+QO17) -> 3 | QV17: =SUM(H17+Q17+Z17+AI17+AR17+BA17+BJ17+BS17+CB17+CK17+CT17+DC17+DL17+DU17+ED17+EM17+EV17+FE17+FN17+FW17+GF17+GO17+GX17+HG17+HP17+HY17+IH17+IQ17+IZ17+JI17+JR17+KA17+KJ17+KS17+LB17+LK17+LT17+MC17+ML17+MU17+ND17+NM17+NV17+OE17+ON17+OW17+PF17+PO17+PX17+QG17+QP17) -> 31 | QW17: =SUM(I17+R17+AA17+AJ17+AS17+BB17+BK17+BT17+CC17+CL17+CU17+DD17+DM17+DV17+EE17+EN17+EW17+FF17+FO17+FX17+GG17+GP17+GY17+HH17+HQ17+HZ17+II17+IR17+JA17+JJ17+JS17+KB17+KK17+KT17+LC17+LL17+LU17+MD17+MM17+MV17+NE17+NN17+NW17+OF17+OO17+OX17+PG17+PP17+PY17+QH17+QQ17) -> 12 | QY17: =SUM(J17,S17,AB17,AK17,AT17,BC17,BL17,BU17,CD17,CM17,CV17,DE17,DN17,DW17,EF17,EO17,FP17,FY17,GH17,GQ17,HI17,HR17,IS17,JB17,JK17,JT17,KC17,KL17,KU17,LD17,LM17,LV17,ME17,MN17,MW17,NF17,NO17,NX17,OG17,OP17,OY17,PH17,PZ17)/5 -> 4 | RA17: =MAX(C17,L17,AD17,AM17,AV17,BN17,BW17,CF17,CX17,DG17,DP17,DY17,EH17,FI17,FR17,GA17,GJ17,HK17,IL17,IU17,JD17,JM17,JV17,KE17,KW17,LO17,LX17,MG17,MP17,MY17,NH17,NQ17,OI17,PA17,PS17) -> 18 | RB17: =MAX(D17,M17,AE17,AN17,AW17,BO17,BX17,CG17,CY17,DH17,DQ17,DZ17,EI17,FJ17,FS17,GB17,GK17,HL17,IM17,IV17,JE17,JN17,JW17,KF17,KX17,LP17,LY17,MH17,MQ17,MZ17,NI17,NR17,OJ17,PB17,PT17) -> 15 | RC17: =MAX(E17,N17,AF17,AO17,AX17,BP17,BY17,CH17,CZ17,DI17,DR17,EA17,EJ17,FK17,FT17,GC17,GL17,HM17,IN17,IW17,JF17,JO17,JX17,KG17,KY17,LQ17,LZ17,MI17,MR17,NA17,NJ17,NS17,OK17,PC17,PU17) -> 30 | RD17: =MIN(C17,L17,AD17,AM17,AV17,BN17,BW17,CF17,CX17,DG17,DP17,DY17,EH17,FI17,FR17,GA17,GJ17,HK17,IL17,IU17,JD17,JM17,JV17,KE17,KW17,LO17,LX17,MG17,MP17,MY17,NH17,NQ17,OI17,PA17,PS17) -> 11 | RE17: =MIN(D17,M17,AE17,AN17,AW17,BO17,BX17,CG17,CY17,DH17,DQ17,DZ17,EI17,FJ17,FS17,GB17,GK17,HL17,IM17,IV17,JE17,JN17,JW17,KF17,KX17,LP17,LY17,MH17,MQ17,MZ17,NI17,NR17,OJ17,PB17,PT17) -> 12 | RF17: =MIN(E17,N17,AF17,AO17,AX17,BP17,BY17,CH17,CZ17,DI17,DR17,EA17,EJ17,FK17,FT17,GC17,GL17,HM17,IN17,IW17,JF17,JO17,JX17,KG17,KY17,LQ17,LZ17,MI17,MR17,NA17,NJ17,NS17,OK17,PC17,PU17) -> 26 | RH17: =MAX(W17,BG17,CQ17,HD17,LH17,OB17,OT17) -> 26 | RI17: =MIN(W17,BG17,CQ17,HD17,LH17,OB17,OT17) -> 26 | RK17: =IFERROR(SUM(E17,N17,W17,AF17,AO17,AX17,BG17,BP17,BY17,CH17,CQ17,CZ17,DI17,DR17,EA17,EJ17,FK17,GC17,GL17,HD17,HM17,IN17,IW17,JF17,JO17,JX17,KG17,KY17,LH17,LQ17,LZ17,MI17,MR17,NA17,NJ17,NS17,OB17,OK17,OT17,PC17,)/QY17,0) -> 27.75 | RM17: =MAX(ES17,IE17) -> 82 | RN17: =MIN(ES17,IE17) -> 82 | RP17: =SUM(EX17,IJ17)/5 -> 1
A18: ='Name List'!B18 -> Peter Donovan | E18: =IF(C18=0,"",C18+D18) | J18: =IF(E18="","",'Name List'!$I$4) | W18: =IF(U18=0,"",U18+V18) | AB18: =IF(W18="","",'Name List'!$I$4) | AF18: =IF(AD18=0,"",AD18+AE18) | AK18: =IF(AF18="","",'Name List'!$I$4) | AO18: =IF(AM18=0,"",AM18+AN18) | AT18: =IF(AO18="","",'Name List'!$I$4) | AX18: =IF(AV18=0,"",AV18+AW18) | BC18: =IF(AX18="","",'Name List'!$I$4) | BG18: =IF(BE18=0,"",BE18+BF18) | BL18: =IF(BG18="","",'Name List'!$I$4) | BY18: =IF(BW18=0,"",BW18+BX18) | CD18: =IF(BY18="","",'Name List'!$I$4) | CH18: =IF(CF18=0,"",CF18+CG18) | CM18: =IF(CH18="","",'Name List'!$I$4) | CQ18: =IF(CO18=0,"",CO18+CP18) | CV18: =IF(CQ18="","",'Name List'!$I$4) | CZ18: =IF(CX18=0,"",CX18+CY18) | DE18: =IF(CZ18="","",'Name List'!$I$4) | DI18: =IF(DG18=0,"",DG18+DH18) | DN18: =IF(DI18="","",'Name List'!$I$4) | DR18: =IF(DP18=0,"",DP18+DQ18) | DW18: =IF(DR18="","",'Name List'!$I$4) | EA18: =IF(DY18=0,"",DY18+DZ18) | EF18: =IF(EA18="","",'Name List'!$I$4) | EJ18: =IF(EH18=0,"",EH18+EI18) | EO18: =IF(EJ18="","",'Name List'!$I$4) | EX18: =IF(ES18="","",'Name List'!$I$4) | FK18: =IF(FI18=0,"",FI18+FJ18) | FP18: =IF(FK18="","",'Name List'!$I$4) | FT18: =IF(FR18=0,"",FR18+FS18) | FY18: =IF(FT18="","",'Name List'!$I$4) | GC18: =IF(GA18=0,"",GA18+GB18) | GH18: =IF(GC18="","",'Name List'!$I$4) | GL18: =IF(GJ18=0,"",GJ18+GK18) | GQ18: =IF(GL18="","",'Name List'!$I$4) | HD18: =IF(HB18=0,"",HB18+HC18) | HI18: =IF(HD18="","",'Name List'!$I$4) | HM18: =IF(HK18=0,"",HK18+HL18) | HR18: =IF(HM18="","",'Name List'!$I$4) | IJ18: =IF(IE18="","",'Name List'!$I$4) | QR18: =IF(QM18="","",'Name List'!$I$4) | QT18: =SUM(F18+O18+X18+AG18+AP18+AY18+BH18+BQ18+BZ18+CI18+CR18+DA18+DJ18+DS18+EB18+EK18+ET18+FC18+FL18+FU18+GD18+GM18+GV18+HE18+HN18+HW18+IF18+IO18+IX18+JG18+JP18+JY18+KH18+KQ18+KZ18+LI18+LR18+MA18+MJ18+MS18+NB18+NK18+NT18+OC18+OL18+OU18+PD18+PM18+PV18+QE18+QN18) -> 0 | QU18: =SUM(G18+P18+Y18+AH18+AQ18+AZ18+BI18+BR18+CA18+CJ18+CS18+DB18+DK18+DT18+EC18+EL18+EU18+FD18+FM18+FV18+GE18+GN18+GW18+HF18+HO18+HX18+IG18+IP18+IY18+JH18+JQ18+JZ18+KI18+KR18+LA18+LJ18+LS18+MB18+MK18+MT18+NC18+NL18+NU18+OD18+OM18+OV18+PE18+PN18+PW18+QF18+QO18) -> 0 | QV18: =SUM(H18+Q18+Z18+AI18+AR18+BA18+BJ18+BS18+CB18+CK18+CT18+DC18+DL18+DU18+ED18+EM18+EV18+FE18+FN18+FW18+GF18+GO18+GX18+HG18+HP18+HY18+IH18+IQ18+IZ18+JI18+JR18+KA18+KJ18+KS18+LB18+LK18+LT18+MC18+ML18+MU18+ND18+NM18+NV18+OE18+ON18+OW18+PF18+PO18+PX18+QG18+QP18) -> 0 | QW18: =SUM(I18+R18+AA18+AJ18+AS18+BB18+BK18+BT18+CC18+CL18+CU18+DD18+DM18+DV18+EE18+EN18+EW18+FF18+FO18+FX18+GG18+GP18+GY18+HH18+HQ18+HZ18+II18+IR18+JA18+JJ18+JS18+KB18+KK18+KT18+LC18+LL18+LU18+MD18+MM18+MV18+NE18+NN18+NW18+OF18+OO18+OX18+PG18+PP18+PY18+QH18+QQ18) -> 0 | QY18: =SUM(J18,S18,AB18,AK18,AT18,BC18,BL18,BU18,CD18,CM18,CV18,DE18,DN18,DW18,EF18,EO18,FP18,FY18,GH18,GQ18,HI18,HR18,IS18,JB18,JK18,JT18,KC18,KL18,KU18,LD18,LM18,LV18,ME18,MN18,MW18,NF18,NO18,NX18,OG18,OP18,OY18,PH18,PZ18)/5 -> 0 | RA18: =MAX(C18,L18,AD18,AM18,AV18,BN18,BW18,CF18,CX18,DG18,DP18,DY18,EH18,FI18,FR18,GA18,GJ18,HK18,IL18,IU18,JD18,JM18,JV18,KE18,KW18,LO18,LX18,MG18,MP18,MY18,NH18,NQ18,OI18,PA18,PS18) -> 0 | RB18: =MAX(D18,M18,AE18,AN18,AW18,BO18,BX18,CG18,CY18,DH18,DQ18,DZ18,EI18,FJ18,FS18,GB18,GK18,HL18,IM18,IV18,JE18,JN18,JW18,KF18,KX18,LP18,LY18,MH18,MQ18,MZ18,NI18,NR18,OJ18,PB18,PT18) -> 0 | RC18: =MAX(E18,N18,AF18,AO18,AX18,BP18,BY18,CH18,CZ18,DI18,DR18,EA18,EJ18,FK18,FT18,GC18,GL18,HM18,IN18,IW18,JF18,JO18,JX18,KG18,KY18,LQ18,LZ18,MI18,MR18,NA18,NJ18,NS18,OK18,PC18,PU18) -> 0 | RD18: =MIN(C18,L18,AD18,AM18,AV18,BN18,BW18,CF18,CX18,DG18,DP18,DY18,EH18,FI18,FR18,GA18,GJ18,HK18,IL18,IU18,JD18,JM18,JV18,KE18,KW18,LO18,LX18,MG18,MP18,MY18,NH18,NQ18,OI18,PA18,PS18) -> 0 | RE18: =MIN(D18,M18,AE18,AN18,AW18,BO18,BX18,CG18,CY18,DH18,DQ18,DZ18,EI18,FJ18,FS18,GB18,GK18,HL18,IM18,IV18,JE18,JN18,JW18,KF18,KX18,LP18,LY18,MH18,MQ18,MZ18,NI18,NR18,OJ18,PB18,PT18) -> 0 | RF18: =MIN(E18,N18,AF18,AO18,AX18,BP18,BY18,CH18,CZ18,DI18,DR18,EA18,EJ18,FK18,FT18,GC18,GL18,HM18,IN18,IW18,JF18,JO18,JX18,KG18,KY18,LQ18,LZ18,MI18,MR18,NA18,NJ18,NS18,OK18,PC18,PU18) -> 0 | RH18: =MAX(W18,BG18,CQ18,HD18,LH18,OB18,OT18) -> 0 | RI18: =MIN(W18,BG18,CQ18,HD18,LH18,OB18,OT18) -> 0 | RK18: =IFERROR(SUM(E18,N18,W18,AF18,AO18,AX18,BG18,BP18,BY18,CH18,CQ18,CZ18,DI18,DR18,EA18,EJ18,FK18,GC18,GL18,HD18,HM18,IN18,IW18,JF18,JO18,JX18,KG18,KY18,LH18,LQ18,LZ18,MI18,MR18,NA18,NJ18,NS18,OB18,OK18,OT18,PC18,)/QY18,0) -> 0 | RM18: =MAX(ES18,IE18) -> 0 | RN18: =MIN(ES18,IE18) -> 0 | RP18: =SUM(EX18,IJ18)/5 -> 0
A19: ='Name List'!B19 -> James Dunn | E19: =IF(C19=0,"",C19+D19) | J19: =IF(E19="","",'Name List'!$I$4) | W19: =IF(U19=0,"",U19+V19) | AB19: =IF(W19="","",'Name List'!$I$4) | AF19: =IF(AD19=0,"",AD19+AE19) | AK19: =IF(AF19="","",'Name List'!$I$4) | AO19: =IF(AM19=0,"",AM19+AN19) | AT19: =IF(AO19="","",'Name List'!$I$4) | AX19: =IF(AV19=0,"",AV19+AW19) | BC19: =IF(AX19="","",'Name List'!$I$4) | BG19: =IF(BE19=0,"",BE19+BF19) | BL19: =IF(BG19="","",'Name List'!$I$4) | BY19: =IF(BW19=0,"",BW19+BX19) | CD19: =IF(BY19="","",'Name List'!$I$4) | CF19: 19 | CG19: 18 | CH19: =IF(CF19=0,"",CF19+CG19) -> 37 | CI19: 1 | CJ19: 2 | CK19: 15 | CL19: 0 | CM19: =IF(CH19="","",'Name List'!$I$4) -> 5 | CQ19: =IF(CO19=0,"",CO19+CP19) | CV19: =IF(CQ19="","",'Name List'!$I$4) | CZ19: =IF(CX19=0,"",CX19+CY19) | DE19: =IF(CZ19="","",'Name List'!$I$4) | DI19: =IF(DG19=0,"",DG19+DH19) | DN19: =IF(DI19="","",'Name List'!$I$4) | DR19: =IF(DP19=0,"",DP19+DQ19) | DW19: =IF(DR19="","",'Name List'!$I$4) | EA19: =IF(DY19=0,"",DY19+DZ19) | EF19: =IF(EA19="","",'Name List'!$I$4) | EJ19: =IF(EH19=0,"",EH19+EI19) | EO19: =IF(EJ19="","",'Name List'!$I$4) | EX19: =IF(ES19="","",'Name List'!$I$4) | FK19: =IF(FI19=0,"",FI19+FJ19) | FP19: =IF(FK19="","",'Name List'!$I$4) | FT19: =IF(FR19=0,"",FR19+FS19) | FY19: =IF(FT19="","",'Name List'!$I$4) | GC19: =IF(GA19=0,"",GA19+GB19) | GH19: =IF(GC19="","",'Name List'!$I$4) | GL19: =IF(GJ19=0,"",GJ19+GK19) | GQ19: =IF(GL19="","",'Name List'!$I$4) | HD19: =IF(HB19=0,"",HB19+HC19) | HI19: =IF(HD19="","",'Name List'!$I$4) | HM19: =IF(HK19=0,"",HK19+HL19) | HR19: =IF(HM19="","",'Name List'!$I$4) | IJ19: =IF(IE19="","",'Name List'!$I$4) | QR19: =IF(QM19="","",'Name List'!$I$4) | QT19: =SUM(F19+O19+X19+AG19+AP19+AY19+BH19+BQ19+BZ19+CI19+CR19+DA19+DJ19+DS19+EB19+EK19+ET19+FC19+FL19+FU19+GD19+GM19+GV19+HE19+HN19+HW19+IF19+IO19+IX19+JG19+JP19+JY19+KH19+KQ19+KZ19+LI19+LR19+MA19+MJ19+MS19+NB19+NK19+NT19+OC19+OL19+OU19+PD19+PM19+PV19+QE19+QN19) -> 1 | QU19: =SUM(G19+P19+Y19+AH19+AQ19+AZ19+BI19+BR19+CA19+CJ19+CS19+DB19+DK19+DT19+EC19+EL19+EU19+FD19+FM19+FV19+GE19+GN19+GW19+HF19+HO19+HX19+IG19+IP19+IY19+JH19+JQ19+JZ19+KI19+KR19+LA19+LJ19+LS19+MB19+MK19+MT19+NC19+NL19+NU19+OD19+OM19+OV19+PE19+PN19+PW19+QF19+QO19) -> 2 | QV19: =SUM(H19+Q19+Z19+AI19+AR19+BA19+BJ19+BS19+CB19+CK19+CT19+DC19+DL19+DU19+ED19+EM19+EV19+FE19+FN19+FW19+GF19+GO19+GX19+HG19+HP19+HY19+IH19+IQ19+IZ19+JI19+JR19+KA19+KJ19+KS19+LB19+LK19+LT19+MC19+ML19+MU19+ND19+NM19+NV19+OE19+ON19+OW19+PF19+PO19+PX19+QG19+QP19) -> 15 | QW19: =SUM(I19+R19+AA19+AJ19+AS19+BB19+BK19+BT19+CC19+CL19+CU19+DD19+DM19+DV19+EE19+EN19+EW19+FF19+FO19+FX19+GG19+GP19+GY19+HH19+HQ19+HZ19+II19+IR19+JA19+JJ19+JS19+KB19+KK19+KT19+LC19+LL19+LU19+MD19+MM19+MV19+NE19+NN19+NW19+OF19+OO19+OX19+PG19+PP19+PY19+QH19+QQ19) -> 0 | QY19: =SUM(J19,S19,AB19,AK19,AT19,BC19,BL19,BU19,CD19,CM19,CV19,DE19,DN19,DW19,EF19,EO19,FP19,FY19,GH19,GQ19,HI19,HR19,IS19,JB19,JK19,JT19,KC19,KL19,KU19,LD19,LM19,LV19,ME19,MN19,MW19,NF19,NO19,NX19,OG19,OP19,OY19,PH19,PZ19)/5 -> 1 | RA19: =MAX(C19,L19,AD19,AM19,AV19,BN19,BW19,CF19,CX19,DG19,DP19,DY19,EH19,FI19,FR19,GA19,GJ19,HK19,IL19,IU19,JD19,JM19,JV19,KE19,KW19,LO19,LX19,MG19,MP19,MY19,NH19,NQ19,OI19,PA19,PS19) -> 19 | RB19: =MAX(D19,M19,AE19,AN19,AW19,BO19,BX19,CG19,CY19,DH19,DQ19,DZ19,EI19,FJ19,FS19,GB19,GK19,HL19,IM19,IV19,JE19,JN19,JW19,KF19,KX19,LP19,LY19,MH19,MQ19,MZ19,NI19,NR19,OJ19,PB19,PT19) -> 18 | RC19: =MAX(E19,N19,AF19,AO19,AX19,BP19,BY19,CH19,CZ19,DI19,DR19,EA19,EJ19,FK19,FT19,GC19,GL19,HM19,IN19,IW19,JF19,JO19,JX19,KG19,KY19,LQ19,LZ19,MI19,MR19,NA19,NJ19,NS19,OK19,PC19,PU19) -> 37 | RD19: =MIN(C19,L19,AD19,AM19,AV19,BN19,BW19,CF19,CX19,DG19,DP19,DY19,EH19,FI19,FR19,GA19,GJ19,HK19,IL19,IU19,JD19,JM19,JV19,KE19,KW19,LO19,LX19,MG19,MP19,MY19,NH19,NQ19,OI19,PA19,PS19) -> 19 | RE19: =MIN(D19,M19,AE19,AN19,AW19,BO19,BX19,CG19,CY19,DH19,DQ19,DZ19,EI19,FJ19,FS19,GB19,GK19,HL19,IM19,IV19,JE19,JN19,JW19,KF19,KX19,LP19,LY19,MH19,MQ19,MZ19,NI19,NR19,OJ19,PB19,PT19) -> 18 | RF19: =MIN(E19,N19,AF19,AO19,AX19,BP19,BY19,CH19,CZ19,DI19,DR19,EA19,EJ19,FK19,FT19,GC19,GL19,HM19,IN19,IW19,JF19,JO19,JX19,KG19,KY19,LQ19,LZ19,MI19,MR19,NA19,NJ19,NS19,OK19,PC19,PU19) -> 37 | RH19: =MAX(W19,BG19,CQ19,HD19,LH19,OB19,OT19) -> 0 | RI19: =MIN(W19,BG19,CQ19,HD19,LH19,OB19,OT19) -> 0 | RK19: =IFERROR(SUM(E19,N19,W19,AF19,AO19,AX19,BG19,BP19,BY19,CH19,CQ19,CZ19,DI19,DR19,EA19,EJ19,FK19,GC19,GL19,HD19,HM19,IN19,IW19,JF19,JO19,JX19,KG19,KY19,LH19,LQ19,LZ19,MI19,MR19,NA19,NJ19,NS19,OB19,OK19,OT19,PC19,)/QY19,0) -> 37 | RM19: =MAX(ES19,IE19) -> 0 | RN19: =MIN(ES19,IE19) -> 0 | RP19: =SUM(EX19,IJ19)/5 -> 0
A20: ='Name List'!B20 -> Gordon Fielding | E20: =IF(C20=0,"",C20+D20) | J20: =IF(E20="","",'Name List'!$I$4) | W20: =IF(U20=0,"",U20+V20) | AB20: =IF(W20="","",'Name List'!$I$4) | AF20: =IF(AD20=0,"",AD20+AE20) | AK20: =IF(AF20="","",'Name List'!$I$4) | AO20: =IF(AM20=0,"",AM20+AN20) | AT20: =IF(AO20="","",'Name List'!$I$4) | AX20: =IF(AV20=0,"",AV20+AW20) | BC20: =IF(AX20="","",'Name List'!$I$4) | BG20: =IF(BE20=0,"",BE20+BF20) | BL20: =IF(BG20="","",'Name List'!$I$4) | BY20: =IF(BW20=0,"",BW20+BX20) | CD20: =IF(BY20="","",'Name List'!$I$4) | CH20: =IF(CF20=0,"",CF20+CG20) | CM20: =IF(CH20="","",'Name List'!$I$4) | CQ20: =IF(CO20=0,"",CO20+CP20) | CV20: =IF(CQ20="","",'Name List'!$I$4) | CZ20: =IF(CX20=0,"",CX20+CY20) | DE20: =IF(CZ20="","",'Name List'!$I$4) | DI20: =IF(DG20=0,"",DG20+DH20) | DN20: =IF(DI20="","",'Name List'!$I$4) | DR20: =IF(DP20=0,"",DP20+DQ20) | DW20: =IF(DR20="","",'Name List'!$I$4) | EA20: =IF(DY20=0,"",DY20+DZ20) | EF20: =IF(EA20="","",'Name List'!$I$4) | EJ20: =IF(EH20=0,"",EH20+EI20) | EO20: =IF(EJ20="","",'Name List'!$I$4) | EX20: =IF(ES20="","",'Name List'!$I$4) | FK20: =IF(FI20=0,"",FI20+FJ20) | FP20: =IF(FK20="","",'Name List'!$I$4) | FT20: =IF(FR20=0,"",FR20+FS20) | FY20: =IF(FT20="","",'Name List'!$I$4) | GC20: =IF(GA20=0,"",GA20+GB20) | GH20: =IF(GC20="","",'Name List'!$I$4) | GL20: =IF(GJ20=0,"",GJ20+GK20) | GQ20: =IF(GL20="","",'Name List'!$I$4) | HD20: =IF(HB20=0,"",HB20+HC20) | HI20: =IF(HD20="","",'Name List'!$I$4) | HM20: =IF(HK20=0,"",HK20+HL20) | HR20: =IF(HM20="","",'Name List'!$I$4) | IJ20: =IF(IE20="","",'Name List'!$I$4) | QR20: =IF(QM20="","",'Name List'!$I$4) | QT20: =SUM(F20+O20+X20+AG20+AP20+AY20+BH20+BQ20+BZ20+CI20+CR20+DA20+DJ20+DS20+EB20+EK20+ET20+FC20+FL20+FU20+GD20+GM20+GV20+HE20+HN20+HW20+IF20+IO20+IX20+JG20+JP20+JY20+KH20+KQ20+KZ20+LI20+LR20+MA20+MJ20+MS20+NB20+NK20+NT20+OC20+OL20+OU20+PD20+PM20+PV20+QE20+QN20) -> 0 | QU20: =SUM(G20+P20+Y20+AH20+AQ20+AZ20+BI20+BR20+CA20+CJ20+CS20+DB20+DK20+DT20+EC20+EL20+EU20+FD20+FM20+FV20+GE20+GN20+GW20+HF20+HO20+HX20+IG20+IP20+IY20+JH20+JQ20+JZ20+KI20+KR20+LA20+LJ20+LS20+MB20+MK20+MT20+NC20+NL20+NU20+OD20+OM20+OV20+PE20+PN20+PW20+QF20+QO20) -> 0 | QV20: =SUM(H20+Q20+Z20+AI20+AR20+BA20+BJ20+BS20+CB20+CK20+CT20+DC20+DL20+DU20+ED20+EM20+EV20+FE20+FN20+FW20+GF20+GO20+GX20+HG20+HP20+HY20+IH20+IQ20+IZ20+JI20+JR20+KA20+KJ20+KS20+LB20+LK20+LT20+MC20+ML20+MU20+ND20+NM20+NV20+OE20+ON20+OW20+PF20+PO20+PX20+QG20+QP20) -> 0 | QW20: =SUM(I20+R20+AA20+AJ20+AS20+BB20+BK20+BT20+CC20+CL20+CU20+DD20+DM20+DV20+EE20+EN20+EW20+FF20+FO20+FX20+GG20+GP20+GY20+HH20+HQ20+HZ20+II20+IR20+JA20+JJ20+JS20+KB20+KK20+KT20+LC20+LL20+LU20+MD20+MM20+MV20+NE20+NN20+NW20+OF20+OO20+OX20+PG20+PP20+PY20+QH20+QQ20) -> 0 | QY20: =SUM(J20,S20,AB20,AK20,AT20,BC20,BL20,BU20,CD20,CM20,CV20,DE20,DN20,DW20,EF20,EO20,FP20,FY20,GH20,GQ20,HI20,HR20,IS20,JB20,JK20,JT20,KC20,KL20,KU20,LD20,LM20,LV20,ME20,MN20,MW20,NF20,NO20,NX20,OG20,OP20,OY20,PH20,PZ20)/5 -> 0 | RA20: =MAX(C20,L20,AD20,AM20,AV20,BN20,BW20,CF20,CX20,DG20,DP20,DY20,EH20,FI20,FR20,GA20,GJ20,HK20,IL20,IU20,JD20,JM20,JV20,KE20,KW20,LO20,LX20,MG20,MP20,MY20,NH20,NQ20,OI20,PA20,PS20) -> 0 | RB20: =MAX(D20,M20,AE20,AN20,AW20,BO20,BX20,CG20,CY20,DH20,DQ20,DZ20,EI20,FJ20,FS20,GB20,GK20,HL20,IM20,IV20,JE20,JN20,JW20,KF20,KX20,LP20,LY20,MH20,MQ20,MZ20,NI20,NR20,OJ20,PB20,PT20) -> 0 | RC20: =MAX(E20,N20,AF20,AO20,AX20,BP20,BY20,CH20,CZ20,DI20,DR20,EA20,EJ20,FK20,FT20,GC20,GL20,HM20,IN20,IW20,JF20,JO20,JX20,KG20,KY20,LQ20,LZ20,MI20,MR20,NA20,NJ20,NS20,OK20,PC20,PU20) -> 0 | RD20: =MIN(C20,L20,AD20,AM20,AV20,BN20,BW20,CF20,CX20,DG20,DP20,DY20,EH20,FI20,FR20,GA20,GJ20,HK20,IL20,IU20,JD20,JM20,JV20,KE20,KW20,LO20,LX20,MG20,MP20,MY20,NH20,NQ20,OI20,PA20,PS20) -> 0 | RE20: =MIN(D20,M20,AE20,AN20,AW20,BO20,BX20,CG20,CY20,DH20,DQ20,DZ20,EI20,FJ20,FS20,GB20,GK20,HL20,IM20,IV20,JE20,JN20,JW20,KF20,KX20,LP20,LY20,MH20,MQ20,MZ20,NI20,NR20,OJ20,PB20,PT20) -> 0 | RF20: =MIN(E20,N20,AF20,AO20,AX20,BP20,BY20,CH20,CZ20,DI20,DR20,EA20,EJ20,FK20,FT20,GC20,GL20,HM20,IN20,IW20,JF20,JO20,JX20,KG20,KY20,LQ20,LZ20,MI20,MR20,NA20,NJ20,NS20,OK20,PC20,PU20) -> 0 | RH20: =MAX(W20,BG20,CQ20,HD20,LH20,OB20,OT20) -> 0 | RI20: =MIN(W20,BG20,CQ20,HD20,LH20,OB20,OT20) -> 0 | RK20: =IFERROR(SUM(E20,N20,W20,AF20,AO20,AX20,BG20,BP20,BY20,CH20,CQ20,CZ20,DI20,DR20,EA20,EJ20,FK20,GC20,GL20,HD20,HM20,IN20,IW20,JF20,JO20,JX20,KG20,KY20,LH20,LQ20,LZ20,MI20,MR20,NA20,NJ20,NS20,OB20,OK20,OT20,PC20,)/QY20,0) -> 0 | RM20: =MAX(ES20,IE20) -> 0 | RN20: =MIN(ES20,IE20) -> 0 | RP20: =SUM(EX20,IJ20)/5 -> 0
A21: ='Name List'!B21 -> Paul Fitzgerald | E21: =IF(C21=0,"",C21+D21) | J21: =IF(E21="","",'Name List'!$I$4) | W21: =IF(U21=0,"",U21+V21) | AB21: =IF(W21="","",'Name List'!$I$4) | AF21: =IF(AD21=0,"",AD21+AE21) | AK21: =IF(AF21="","",'Name List'!$I$4) | AM21: 16 | AN21: 20 | AO21: =IF(AM21=0,"",AM21+AN21) -> 36 | AP21: 0 | AQ21: 1 | AR21: 6 | AS21: 0 | AT21: =IF(AO21="","",'Name List'!$I$4) -> 5 | AX21: =IF(AV21=0,"",AV21+AW21) | BC21: =IF(AX21="","",'Name List'!$I$4) | BG21: =IF(BE21=0,"",BE21+BF21) | BL21: =IF(BG21="","",'Name List'!$I$4) | BW21: 21 | BX21: 18 | BY21: =IF(BW21=0,"",BW21+BX21) -> 39 | BZ21: 0 | CA21: 2 | CB21: 5 | CC21: 0 | CD21: =IF(BY21="","",'Name List'!$I$4) -> 5 | CH21: =IF(CF21=0,"",CF21+CG21) | CM21: =IF(CH21="","",'Name List'!$I$4) | CQ21: =IF(CO21=0,"",CO21+CP21) | CV21: =IF(CQ21="","",'Name List'!$I$4) | CZ21: =IF(CX21=0,"",CX21+CY21) | DE21: =IF(CZ21="","",'Name List'!$I$4) | DI21: =IF(DG21=0,"",DG21+DH21) | DN21: =IF(DI21="","",'Name List'!$I$4) | DR21: =IF(DP21=0,"",DP21+DQ21) | DW21: =IF(DR21="","",'Name List'!$I$4) | DY21: 17 | DZ21: 12 | EA21: =IF(DY21=0,"",DY21+DZ21) -> 29 | EB21: 0 | EC21: 0 | ED21: 5 | EE21: 4 | EF21: =IF(EA21="","",'Name List'!$I$4) -> 5 | EJ21: =IF(EH21=0,"",EH21+EI21) | EO21: =IF(EJ21="","",'Name List'!$I$4) | EX21: =IF(ES21="","",'Name List'!$I$4) | FK21: =IF(FI21=0,"",FI21+FJ21) | FP21: =IF(FK21="","",'Name List'!$I$4) | FT21: =IF(FR21=0,"",FR21+FS21) | FY21: =IF(FT21="","",'Name List'!$I$4) | GC21: =IF(GA21=0,"",GA21+GB21) | GH21: =IF(GC21="","",'Name List'!$I$4) | GJ21: 15 | GK21: 12 | GL21: =IF(GJ21=0,"",GJ21+GK21) -> 27 | GM21: 0 | GN21: 0 | GO21: 5 | GP21: 3 | GQ21: =IF(GL21="","",'Name List'!$I$4) -> 5 | HD21: =IF(HB21=0,"",HB21+HC21) | HI21: =IF(HD21="","",'Name List'!$I$4) | HM21: =IF(HK21=0,"",HK21+HL21) | HR21: =IF(HM21="","",'Name List'!$I$4) | IJ21: =IF(IE21="","",'Name List'!$I$4) | QR21: =IF(QM21="","",'Name List'!$I$4) | QT21: =SUM(F21+O21+X21+AG21+AP21+AY21+BH21+BQ21+BZ21+CI21+CR21+DA21+DJ21+DS21+EB21+EK21+ET21+FC21+FL21+FU21+GD21+GM21+GV21+HE21+HN21+HW21+IF21+IO21+IX21+JG21+JP21+JY21+KH21+KQ21+KZ21+LI21+LR21+MA21+MJ21+MS21+NB21+NK21+NT21+OC21+OL21+OU21+PD21+PM21+PV21+QE21+QN21) -> 0 | QU21: =SUM(G21+P21+Y21+AH21+AQ21+AZ21+BI21+BR21+CA21+CJ21+CS21+DB21+DK21+DT21+EC21+EL21+EU21+FD21+FM21+FV21+GE21+GN21+GW21+HF21+HO21+HX21+IG21+IP21+IY21+JH21+JQ21+JZ21+KI21+KR21+LA21+LJ21+LS21+MB21+MK21+MT21+NC21+NL21+NU21+OD21+OM21+OV21+PE21+PN21+PW21+QF21+QO21) -> 3 | QV21: =SUM(H21+Q21+Z21+AI21+AR21+BA21+BJ21+BS21+CB21+CK21+CT21+DC21+DL21+DU21+ED21+EM21+EV21+FE21+FN21+FW21+GF21+GO21+GX21+HG21+HP21+HY21+IH21+IQ21+IZ21+JI21+JR21+KA21+KJ21+KS21+LB21+LK21+LT21+MC21+ML21+MU21+ND21+NM21+NV21+OE21+ON21+OW21+PF21+PO21+PX21+QG21+QP21) -> 21 | QW21: =SUM(I21+R21+AA21+AJ21+AS21+BB21+BK21+BT21+CC21+CL21+CU21+DD21+DM21+DV21+EE21+EN21+EW21+FF21+FO21+FX21+GG21+GP21+GY21+HH21+HQ21+HZ21+II21+IR21+JA21+JJ21+JS21+KB21+KK21+KT21+LC21+LL21+LU21+MD21+MM21+MV21+NE21+NN21+NW21+OF21+OO21+OX21+PG21+PP21+PY21+QH21+QQ21) -> 7 | QY21: =SUM(J21,S21,AB21,AK21,AT21,BC21,BL21,BU21,CD21,CM21,CV21,DE21,DN21,DW21,EF21,EO21,FP21,FY21,GH21,GQ21,HI21,HR21,IS21,JB21,JK21,JT21,KC21,KL21,KU21,LD21,LM21,LV21,ME21,MN21,MW21,NF21,NO21,NX21,OG21,OP21,OY21,PH21,PZ21)/5 -> 4 | RA21: =MAX(C21,L21,AD21,AM21,AV21,BN21,BW21,CF21,CX21,DG21,DP21,DY21,EH21,FI21,FR21,GA21,GJ21,HK21,IL21,IU21,JD21,JM21,JV21,KE21,KW21,LO21,LX21,MG21,MP21,MY21,NH21,NQ21,OI21,PA21,PS21) -> 21 | RB21: =MAX(D21,M21,AE21,AN21,AW21,BO21,BX21,CG21,CY21,DH21,DQ21,DZ21,EI21,FJ21,FS21,GB21,GK21,HL21,IM21,IV21,JE21,JN21,JW21,KF21,KX21,LP21,LY21,MH21,MQ21,MZ21,NI21,NR21,OJ21,PB21,PT21) -> 20 | RC21: =MAX(E21,N21,AF21,AO21,AX21,BP21,BY21,CH21,CZ21,DI21,DR21,EA21,EJ21,FK21,FT21,GC21,GL21,HM21,IN21,IW21,JF21,JO21,JX21,KG21,KY21,LQ21,LZ21,MI21,MR21,NA21,NJ21,NS21,OK21,PC21,PU21) -> 39 | RD21: =MIN(C21,L21,AD21,AM21,AV21,BN21,BW21,CF21,CX21,DG21,DP21,DY21,EH21,FI21,FR21,GA21,GJ21,HK21,IL21,IU21,JD21,JM21,JV21,KE21,KW21,LO21,LX21,MG21,MP21,MY21,NH21,NQ21,OI21,PA21,PS21) -> 15 | RE21: =MIN(D21,M21,AE21,AN21,AW21,BO21,BX21,CG21,CY21,DH21,DQ21,DZ21,EI21,FJ21,FS21,GB21,GK21,HL21,IM21,IV21,JE21,JN21,JW21,KF21,KX21,LP21,LY21,MH21,MQ21,MZ21,NI21,NR21,OJ21,PB21,PT21) -> 12 | RF21: =MIN(E21,N21,AF21,AO21,AX21,BP21,BY21,CH21,CZ21,DI21,DR21,EA21,EJ21,FK21,FT21,GC21,GL21,HM21,IN21,IW21,JF21,JO21,JX21,KG21,KY21,LQ21,LZ21,MI21,MR21,NA21,NJ21,NS21,OK21,PC21,PU21) -> 27 | RH21: =MAX(W21,BG21,CQ21,HD21,LH21,OB21,OT21) -> 0 | RI21: =MIN(W21,BG21,CQ21,HD21,LH21,OB21,OT21) -> 0 | RK21: =IFERROR(SUM(E21,N21,W21,AF21,AO21,AX21,BG21,BP21,BY21,CH21,CQ21,CZ21,DI21,DR21,EA21,EJ21,FK21,GC21,GL21,HD21,HM21,IN21,IW21,JF21,JO21,JX21,KG21,KY21,LH21,LQ21,LZ21,MI21,MR21,NA21,NJ21,NS21,OB21,OK21,OT21,PC21,)/QY21,0) -> 32.75 | RM21: =MAX(ES21,IE21) -> 0 | RN21: =MIN(ES21,IE21) -> 0 | RP21: =SUM(EX21,IJ21)/5 -> 0
A22: ='Name List'!B22 -> Ben Fleet | E22: =IF(C22=0,"",C22+D22) | J22: =IF(E22="","",'Name List'!$I$4) | U22: 12 | V22: 13 | W22: =IF(U22=0,"",U22+V22) -> 25 | X22: 0 | Y22: 0 | Z22: 1 | AA22: 2 | AB22: =IF(W22="","",'Name List'!$I$4) -> 5 | AF22: =IF(AD22=0,"",AD22+AE22) | AK22: =IF(AF22="","",'Name List'!$I$4) | AM22: 17 | AN22: 18 | AO22: =IF(AM22=0,"",AM22+AN22) -> 35 | AP22: 0 | AQ22: 0 | AR22: 8 | AS22: 1 | AT22: =IF(AO22="","",'Name List'!$I$4) -> 5 | AV22: 14 | AW22: 17 | AX22: =IF(AV22=0,"",AV22+AW22) -> 31 | AY22: 0 | AZ22: 0 | BA22: 6 | BB22: 1 | BC22: =IF(AX22="","",'Name List'!$I$4) -> 5 | BE22: 9 | BF22: 13 | BG22: =IF(BE22=0,"",BE22+BF22) -> 22 | BH22: 0 | BI22: 1 | BJ22: 2 | BK22: 5 | BL22: =IF(BG22="","",'Name List'!$I$4) -> 5 | BW22: 12 | BX22: 12 | BY22: =IF(BW22=0,"",BW22+BX22) -> 24 | BZ22: 0 | CA22: 1 | CB22: 3 | CC22: 5 | CD22: =IF(BY22="","",'Name List'!$I$4) -> 5 | CH22: =IF(CF22=0,"",CF22+CG22) | CM22: =IF(CH22="","",'Name List'!$I$4) | CO22: 19 | CP22: 16 | CQ22: =IF(CO22=0,"",CO22+CP22) -> 35 | CR22: 0 | CS22: 1 | CT22: 6 | CU22: 2 | CV22: =IF(CQ22="","",'Name List'!$I$4) -> 5 | CX22: 14 | CY22: 15 | CZ22: =IF(CX22=0,"",CX22+CY22) -> 29 | DA22: 0 | DB22: 0 | DC22: 8 | DD22: 3 | DE22: =IF(CZ22="","",'Name List'!$I$4) -> 5 | DG22: 18 | DH22: 16 | DI22: =IF(DG22=0,"",DG22+DH22) -> 34 | DJ22: 0 | DK22: 1 | DL22: 6 | DM22: 1 | DN22: =IF(DI22="","",'Name List'!$I$4) -> 5 | DR22: =IF(DP22=0,"",DP22+DQ22) | DW22: =IF(DR22="","",'Name List'!$I$4) | EA22: =IF(DY22=0,"",DY22+DZ22) | EF22: =IF(EA22="","",'Name List'!$I$4) | EH22: 17 | EI22: 11 | EJ22: =IF(EH22=0,"",EH22+EI22) -> 28 | EK22: 0 | EL22: 2 | EM22: 1 | EN22: 1 | EO22: =IF(EJ22="","",'Name List'!$I$4) -> 5 | ES22: 89 | ET22: 0 | EU22: 1 | EV22: 6 | EX22: =IF(ES22="","",'Name List'!$I$4) -> 5 | FK22: =IF(FI22=0,"",FI22+FJ22) | FP22: =IF(FK22="","",'Name List'!$I$4) | FR22: 18 | FS22: 15 | FT22: =IF(FR22=0,"",FR22+FS22) -> 33 | FU22: 0 | FV22: 0 | FW22: 7 | FX22: 1 | FY22: =IF(FT22="","",'Name List'!$I$4) -> 5 | GA22: 10 | GB22: 15 | GC22: =IF(GA22=0,"",GA22+GB22) -> 25 | GD22: 0 | GE22: 0 | GF22: 4 | GG22: 4 | GH22: =IF(GC22="","",'Name List'!$I$4) -> 5 | GJ22: 21 | GK22: 14 | GL22: =IF(GJ22=0,"",GJ22+GK22) -> 35 | GM22: 0 | GN22: 1 | GO22: 8 | GP22: 1 | GQ22: =IF(GL22="","",'Name List'!$I$4) -> 5 | HB22: 21 | HC22: 20 | HD22: =IF(HB22=0,"",HB22+HC22) -> 41 | HE22: 0 | HF22: 0 | HG22: 11 | HH22: 0 | HI22: =IF(HD22="","",'Name List'!$I$4) -> 5 | HM22: =IF(HK22=0,"",HK22+HL22) | HR22: =IF(HM22="","",'Name List'!$I$4) | IJ22: =IF(IE22="","",'Name List'!$I$4) | QR22: =IF(QM22="","",'Name List'!$I$4) | QT22: =SUM(F22+O22+X22+AG22+AP22+AY22+BH22+BQ22+BZ22+CI22+CR22+DA22+DJ22+DS22+EB22+EK22+ET22+FC22+FL22+FU22+GD22+GM22+GV22+HE22+HN22+HW22+IF22+IO22+IX22+JG22+JP22+JY22+KH22+KQ22+KZ22+LI22+LR22+MA22+MJ22+MS22+NB22+NK22+NT22+OC22+OL22+OU22+PD22+PM22+PV22+QE22+QN22) -> 0 | QU22: =SUM(G22+P22+Y22+AH22+AQ22+AZ22+BI22+BR22+CA22+CJ22+CS22+DB22+DK22+DT22+EC22+EL22+EU22+FD22+FM22+FV22+GE22+GN22+GW22+HF22+HO22+HX22+IG22+IP22+IY22+JH22+JQ22+JZ22+KI22+KR22+LA22+LJ22+LS22+MB22+MK22+MT22+NC22+NL22+NU22+OD22+OM22+OV22+PE22+PN22+PW22+QF22+QO22) -> 8 | QV22: =SUM(H22+Q22+Z22+AI22+AR22+BA22+BJ22+BS22+CB22+CK22+CT22+DC22+DL22+DU22+ED22+EM22+EV22+FE22+FN22+FW22+GF22+GO22+GX22+HG22+HP22+HY22+IH22+IQ22+IZ22+JI22+JR22+KA22+KJ22+KS22+LB22+LK22+LT22+MC22+ML22+MU22+ND22+NM22+NV22+OE22+ON22+OW22+PF22+PO22+PX22+QG22+QP22) -> 77 | QW22: =SUM(I22+R22+AA22+AJ22+AS22+BB22+BK22+BT22+CC22+CL22+CU22+DD22+DM22+DV22+EE22+EN22+EW22+FF22+FO22+FX22+GG22+GP22+GY22+HH22+HQ22+HZ22+II22+IR22+JA22+JJ22+JS22+KB22+KK22+KT22+LC22+LL22+LU22+MD22+MM22+MV22+NE22+NN22+NW22+OF22+OO22+OX22+PG22+PP22+PY22+QH22+QQ22) -> 27 | QY22: =SUM(J22,S22,AB22,AK22,AT22,BC22,BL22,BU22,CD22,CM22,CV22,DE22,DN22,DW22,EF22,EO22,FP22,FY22,GH22,GQ22,HI22,HR22,IS22,JB22,JK22,JT22,KC22,KL22,KU22,LD22,LM22,LV22,ME22,MN22,MW22,NF22,NO22,NX22,OG22,OP22,OY22,PH22,PZ22)/5 -> 13 | RA22: =MAX(C22,L22,AD22,AM22,AV22,BN22,BW22,CF22,CX22,DG22,DP22,DY22,EH22,FI22,FR22,GA22,GJ22,HK22,IL22,IU22,JD22,JM22,JV22,KE22,KW22,LO22,LX22,MG22,MP22,MY22,NH22,NQ22,OI22,PA22,PS22) -> 21 | RB22: =MAX(D22,M22,AE22,AN22,AW22,BO22,BX22,CG22,CY22,DH22,DQ22,DZ22,EI22,FJ22,FS22,GB22,GK22,HL22,IM22,IV22,JE22,JN22,JW22,KF22,KX22,LP22,LY22,MH22,MQ22,MZ22,NI22,NR22,OJ22,PB22,PT22) -> 18 | RC22: =MAX(E22,N22,AF22,AO22,AX22,BP22,BY22,CH22,CZ22,DI22,DR22,EA22,EJ22,FK22,FT22,GC22,GL22,HM22,IN22,IW22,JF22,JO22,JX22,KG22,KY22,LQ22,LZ22,MI22,MR22,NA22,NJ22,NS22,OK22,PC22,PU22) -> 35 | RD22: =MIN(C22,L22,AD22,AM22,AV22,BN22,BW22,CF22,CX22,DG22,DP22,DY22,EH22,FI22,FR22,GA22,GJ22,HK22,IL22,IU22,JD22,JM22,JV22,KE22,KW22,LO22,LX22,MG22,MP22,MY22,NH22,NQ22,OI22,PA22,PS22) -> 10 | RE22: =MIN(D22,M22,AE22,AN22,AW22,BO22,BX22,CG22,CY22,DH22,DQ22,DZ22,EI22,FJ22,FS22,GB22,GK22,HL22,IM22,IV22,JE22,JN22,JW22,KF22,KX22,LP22,LY22,MH22,MQ22,MZ22,NI22,NR22,OJ22,PB22,PT22) -> 11 | RF22: =MIN(E22,N22,AF22,AO22,AX22,BP22,BY22,CH22,CZ22,DI22,DR22,EA22,EJ22,FK22,FT22,GC22,GL22,HM22,IN22,IW22,JF22,JO22,JX22,KG22,KY22,LQ22,LZ22,MI22,MR22,NA22,NJ22,NS22,OK22,PC22,PU22) -> 24 | RH22: =MAX(W22,BG22,CQ22,HD22,LH22,OB22,OT22) -> 41 | RI22: =MIN(W22,BG22,CQ22,HD22,LH22,OB22,OT22) -> 22 | RK22: =IFERROR(SUM(E22,N22,W22,AF22,AO22,AX22,BG22,BP22,BY22,CH22,CQ22,CZ22,DI22,DR22,EA22,EJ22,FK22,GC22,GL22,HD22,HM22,IN22,IW22,JF22,JO22,JX22,KG22,KY22,LH22,LQ22,LZ22,MI22,MR22,NA22,NJ22,NS22,OB22,OK22,OT22,PC22,)/QY22,0) -> 28 | RM22: =MAX(ES22,IE22) -> 89 | RN22: =MIN(ES22,IE22) -> 89 | RP22: =SUM(EX22,IJ22)/5 -> 1
A23: ='Name List'!B23 -> Mike Forrest | E23: =IF(C23=0,"",C23+D23) | J23: =IF(E23="","",'Name List'!$I$4) | W23: =IF(U23=0,"",U23+V23) | AB23: =IF(W23="","",'Name List'!$I$4) | AD23: 18 | AE23: 15 | AF23: =IF(AD23=0,"",AD23+AE23) -> 33 | AG23: 0 | AH23: 0 | AI23: 1 | AJ23: 0 | AK23: =IF(AF23="","",'Name List'!$I$4) -> 5 | AM23: 12 | AN23: 20 | AO23: =IF(AM23=0,"",AM23+AN23) -> 32 | AP23: 0 | AQ23: 0 | AR23: 4 | AS23: 3 | AT23: =IF(AO23="","",'Name List'!$I$4) -> 5 | AX23: =IF(AV23=0,"",AV23+AW23) | BC23: =IF(AX23="","",'Name List'!$I$4) | BG23: =IF(BE23=0,"",BE23+BF23) | BL23: =IF(BG23="","",'Name List'!$I$4) | BW23: 11 | BX23: 12 | BY23: =IF(BW23=0,"",BW23+BX23) -> 23 | BZ23: 0 | CA23: 0 | CB23: 1 | CC23: 4 | CD23: =IF(BY23="","",'Name List'!$I$4) -> 5 | CF23: 15 | CG23: 14 | CH23: =IF(CF23=0,"",CF23+CG23) -> 29 | CI23: 0 | CJ23: 0 | CK23: 3 | CL23: 3 | CM23: =IF(CH23="","",'Name List'!$I$4) -> 5 | CQ23: =IF(CO23=0,"",CO23+CP23) | CV23: =IF(CQ23="","",'Name List'!$I$4) | CX23: 12 | CY23: 19 | CZ23: =IF(CX23=0,"",CX23+CY23) -> 31 | DA23: 0 | DB23: 0 | DC23: 4 | DD23: 2 | DE23: =IF(CZ23="","",'Name List'!$I$4) -> 5 | DG23: 12 | DH23: 14 | DI23: =IF(DG23=0,"",DG23+DH23) -> 26 | DJ23: 0 | DK23: 0 | DL23: 1 | DM23: 3 | DN23: =IF(DI23="","",'Name List'!$I$4) -> 5 | DP23: 13 | DQ23: 12 | DR23: =IF(DP23=0,"",DP23+DQ23) -> 25 | DS23: 0 | DT23: 0 | DU23: 1 | DV23: 3 | DW23: =IF(DR23="","",'Name List'!$I$4) -> 5 | EA23: =IF(DY23=0,"",DY23+DZ23) | EF23: =IF(EA23="","",'Name List'!$I$4) | EH23: 13 | EI23: 12 | EJ23: =IF(EH23=0,"",EH23+EI23) -> 25 | EK23: 0 | EL23: 0 | EM23: 2 | EN23: 4 | EO23: =IF(EJ23="","",'Name List'!$I$4) -> 5 | EX23: =IF(ES23="","",'Name List'!$I$4) | FK23: =IF(FI23=0,"",FI23+FJ23) | FP23: =IF(FK23="","",'Name List'!$I$4) | FT23: =IF(FR23=0,"",FR23+FS23) | FY23: =IF(FT23="","",'Name List'!$I$4) | GC23: =IF(GA23=0,"",GA23+GB23) | GH23: =IF(GC23="","",'Name List'!$I$4) | GL23: =IF(GJ23=0,"",GJ23+GK23) | GQ23: =IF(GL23="","",'Name List'!$I$4) | HB23: 15 | HC23: 15 | HD23: =IF(HB23=0,"",HB23+HC23) -> 30 | HE23: 0 | HF23: 0 | HG23: 5 | HH23: 3 | HI23: =IF(HD23="","",'Name List'!$I$4) -> 5 | HK23: 15 | HL23: 19 | HM23: =IF(HK23=0,"",HK23+HL23) -> 34 | HN23: 0 | HO23: 0 | HP23: 4 | HQ23: 2 | HR23: =IF(HM23="","",'Name List'!$I$4) -> 5 | IJ23: =IF(IE23="","",'Name List'!$I$4) | QR23: =IF(QM23="","",'Name List'!$I$4) | QT23: =SUM(F23+O23+X23+AG23+AP23+AY23+BH23+BQ23+BZ23+CI23+CR23+DA23+DJ23+DS23+EB23+EK23+ET23+FC23+FL23+FU23+GD23+GM23+GV23+HE23+HN23+HW23+IF23+IO23+IX23+JG23+JP23+JY23+KH23+KQ23+KZ23+LI23+LR23+MA23+MJ23+MS23+NB23+NK23+NT23+OC23+OL23+OU23+PD23+PM23+PV23+QE23+QN23) -> 0 | QU23: =SUM(G23+P23+Y23+AH23+AQ23+AZ23+BI23+BR23+CA23+CJ23+CS23+DB23+DK23+DT23+EC23+EL23+EU23+FD23+FM23+FV23+GE23+GN23+GW23+HF23+HO23+HX23+IG23+IP23+IY23+JH23+JQ23+JZ23+KI23+KR23+LA23+LJ23+LS23+MB23+MK23+MT23+NC23+NL23+NU23+OD23+OM23+OV23+PE23+PN23+PW23+QF23+QO23) -> 0 | QV23: =SUM(H23+Q23+Z23+AI23+AR23+BA23+BJ23+BS23+CB23+CK23+CT23+DC23+DL23+DU23+ED23+EM23+EV23+FE23+FN23+FW23+GF23+GO23+GX23+HG23+HP23+HY23+IH23+IQ23+IZ23+JI23+JR23+KA23+KJ23+KS23+LB23+LK23+LT23+MC23+ML23+MU23+ND23+NM23+NV23+OE23+ON23+OW23+PF23+PO23+PX23+QG23+QP23) -> 26 | QW23: =SUM(I23+R23+AA23+AJ23+AS23+BB23+BK23+BT23+CC23+CL23+CU23+DD23+DM23+DV23+EE23+EN23+EW23+FF23+FO23+FX23+GG23+GP23+GY23+HH23+HQ23+HZ23+II23+IR23+JA23+JJ23+JS23+KB23+KK23+KT23+LC23+LL23+LU23+MD23+MM23+MV23+NE23+NN23+NW23+OF23+OO23+OX23+PG23+PP23+PY23+QH23+QQ23) -> 27 | QY23: =SUM(J23,S23,AB23,AK23,AT23,BC23,BL23,BU23,CD23,CM23,CV23,DE23,DN23,DW23,EF23,EO23,FP23,FY23,GH23,GQ23,HI23,HR23,IS23,JB23,JK23,JT23,KC23,KL23,KU23,LD23,LM23,LV23,ME23,MN23,MW23,NF23,NO23,NX23,OG23,OP23,OY23,PH23,PZ23)/5 -> 10 | RA23: =MAX(C23,L23,AD23,AM23,AV23,BN23,BW23,CF23,CX23,DG23,DP23,DY23,EH23,FI23,FR23,GA23,GJ23,HK23,IL23,IU23,JD23,JM23,JV23,KE23,KW23,LO23,LX23,MG23,MP23,MY23,NH23,NQ23,OI23,PA23,PS23) -> 18 | RB23: =MAX(D23,M23,AE23,AN23,AW23,BO23,BX23,CG23,CY23,DH23,DQ23,DZ23,EI23,FJ23,FS23,GB23,GK23,HL23,IM23,IV23,JE23,JN23,JW23,KF23,KX23,LP23,LY23,MH23,MQ23,MZ23,NI23,NR23,OJ23,PB23,PT23) -> 20 | RC23: =MAX(E23,N23,AF23,AO23,AX23,BP23,BY23,CH23,CZ23,DI23,DR23,EA23,EJ23,FK23,FT23,GC23,GL23,HM23,IN23,IW23,JF23,JO23,JX23,KG23,KY23,LQ23,LZ23,MI23,MR23,NA23,NJ23,NS23,OK23,PC23,PU23) -> 34 | RD23: =MIN(C23,L23,AD23,AM23,AV23,BN23,BW23,CF23,CX23,DG23,DP23,DY23,EH23,FI23,FR23,GA23,GJ23,HK23,IL23,IU23,JD23,JM23,JV23,KE23,KW23,LO23,LX23,MG23,MP23,MY23,NH23,NQ23,OI23,PA23,PS23) -> 11 | RE23: =MIN(D23,M23,AE23,AN23,AW23,BO23,BX23,CG23,CY23,DH23,DQ23,DZ23,EI23,FJ23,FS23,GB23,GK23,HL23,IM23,IV23,JE23,JN23,JW23,KF23,KX23,LP23,LY23,MH23,MQ23,MZ23,NI23,NR23,OJ23,PB23,PT23) -> 12 | RF23: =MIN(E23,N23,AF23,AO23,AX23,BP23,BY23,CH23,CZ23,DI23,DR23,EA23,EJ23,FK23,FT23,GC23,GL23,HM23,IN23,IW23,JF23,JO23,JX23,KG23,KY23,LQ23,LZ23,MI23,MR23,NA23,NJ23,NS23,OK23,PC23,PU23) -> 23 | RH23: =MAX(W23,BG23,CQ23,HD23,LH23,OB23,OT23) -> 30 | RI23: =MIN(W23,BG23,CQ23,HD23,LH23,OB23,OT23) -> 30 | RK23: =IFERROR(SUM(E23,N23,W23,AF23,AO23,AX23,BG23,BP23,BY23,CH23,CQ23,CZ23,DI23,DR23,EA23,EJ23,FK23,GC23,GL23,HD23,HM23,IN23,IW23,JF23,JO23,JX23,KG23,KY23,LH23,LQ23,LZ23,MI23,MR23,NA23,NJ23,NS23,OB23,OK23,OT23,PC23,)/QY23,0) -> 28.8 | RM23: =MAX(ES23,IE23) -> 0 | RN23: =MIN(ES23,IE23) -> 0 | RP23: =SUM(EX23,IJ23)/5 -> 0
A24: ='Name List'!B24 -> Tony Forsyth-James | E24: =IF(C24=0,"",C24+D24) | J24: =IF(E24="","",'Name List'!$I$4) | U24: 10 | V24: 14 | W24: =IF(U24=0,"",U24+V24) -> 24 | X24: 0 | Y24: 0 | Z24: 2 | AA24: 3 | AB24: =IF(W24="","",'Name List'!$I$4) -> 5 | AD24: 14 | AE24: 23 | AF24: =IF(AD24=0,"",AD24+AE24) -> 37 | AG24: 0 | AH24: 1 | AI24: 10 | AJ24: 2 | AK24: =IF(AF24="","",'Name List'!$I$4) -> 5 | AM24: 15 | AN24: 17 | AO24: =IF(AM24=0,"",AM24+AN24) -> 32 | AP24: 0 | AQ24: 0 | AR24: 4 | AS24: 3 | AT24: =IF(AO24="","",'Name List'!$I$4) -> 5 | AX24: =IF(AV24=0,"",AV24+AW24) | BC24: =IF(AX24="","",'Name List'!$I$4) | BE24: 16 | BF24: 20 | BG24: =IF(BE24=0,"",BE24+BF24) -> 36 | BH24: 0 | BI24: 0 | BJ24: 5 | BK24: 2 | BL24: =IF(BG24="","",'Name List'!$I$4) -> 5 | BY24: =IF(BW24=0,"",BW24+BX24) | CD24: =IF(BY24="","",'Name List'!$I$4) | CH24: =IF(CF24=0,"",CF24+CG24) | CM24: =IF(CH24="","",'Name List'!$I$4) | CO24: 14 | CP24: 15 | CQ24: =IF(CO24=0,"",CO24+CP24) -> 29 | CR24: 0 | CS24: 0 | CT24: 4 | CU24: 3 | CV24: =IF(CQ24="","",'Name List'!$I$4) -> 5 | CX24: 11 | CY24: 15 | CZ24: =IF(CX24=0,"",CX24+CY24) -> 26 | DA24: 0 | DB24: 0 | DC24: 2 | DD24: 3 | DE24: =IF(CZ24="","",'Name List'!$I$4) -> 5 | DG24: 10 | DH24: 16 | DI24: =IF(DG24=0,"",DG24+DH24) -> 26 | DJ24: 0 | DK24: 0 | DL24: 2 | DM24: 2 | DN24: =IF(DI24="","",'Name List'!$I$4) -> 5 | DP24: 13 | DQ24: 10 | DR24: =IF(DP24=0,"",DP24+DQ24) -> 23 | DS24: 0 | DT24: 0 | DU24: 5 | DV24: 6 | DW24: =IF(DR24="","",'Name List'!$I$4) -> 5 | DY24: 17 | DZ24: 12 | EA24: =IF(DY24=0,"",DY24+DZ24) -> 29 | EB24: 0 | EC24: 0 | ED24: 4 | EE24: 2 | EF24: =IF(EA24="","",'Name List'!$I$4) -> 5 | EH24: 13 | EI24: 15 | EJ24: =IF(EH24=0,"",EH24+EI24) -> 28 | EK24: 0 | EL24: 1 | EM24: 3 | EN24: 4 | EO24: =IF(EJ24="","",'Name List'!$I$4) -> 5 | ES24: 102 | ET24: 0 | EU24: 0 | EV24: 4 | EX24: =IF(ES24="","",'Name List'!$I$4) -> 5 | FI24: 19 | FJ24: 17 | FK24: =IF(FI24=0,"",FI24+FJ24) -> 36 | FL24: 0 | FM24: 1 | FN24: 4 | FO24: 1 | FP24: =IF(FK24="","",'Name List'!$I$4) -> 5 | FR24: 19 | FS24: 17 | FT24: =IF(FR24=0,"",FR24+FS24) -> 36 | FU24: 0 | FV24: 0 | FW24: 5 | FX24: 1 | FY24: =IF(FT24="","",'Name List'!$I$4) -> 5 | GA24: 17 | GB24: 16 | GC24: =IF(GA24=0,"",GA24+GB24) -> 33 | GD24: 0 | GE24: 0 | GF24: 6 | GG24: 2 | GH24: =IF(GC24="","",'Name List'!$I$4) -> 5 | GJ24: 19 | GK24: 21 | GL24: =IF(GJ24=0,"",GJ24+GK24) -> 40 | GM24: 0 | GN24: 1 | GO24: 9 | GP24: 1 | GQ24: =IF(GL24="","",'Name List'!$I$4) -> 5 | HB24: 20 | HC24: 18 | HD24: =IF(HB24=0,"",HB24+HC24) -> 38 | HE24: 0 | HF24: 1 | HG24: 5 | HH24: 1 | HI24: =IF(HD24="","",'Name List'!$I$4) -> 5 | HK24: 17 | HL24: 23 | HM24: =IF(HK24=0,"",HK24+HL24) -> 40 | HN24: 0 | HO24: 1 | HP24: 8 | HQ24: 2 | HR24: =IF(HM24="","",'Name List'!$I$4) -> 5 | IJ24: =IF(IE24="","",'Name List'!$I$4) | QR24: =IF(QM24="","",'Name List'!$I$4) | QT24: =SUM(F24+O24+X24+AG24+AP24+AY24+BH24+BQ24+BZ24+CI24+CR24+DA24+DJ24+DS24+EB24+EK24+ET24+FC24+FL24+FU24+GD24+GM24+GV24+HE24+HN24+HW24+IF24+IO24+IX24+JG24+JP24+JY24+KH24+KQ24+KZ24+LI24+LR24+MA24+MJ24+MS24+NB24+NK24+NT24+OC24+OL24+OU24+PD24+PM24+PV24+QE24+QN24) -> 0 | QU24: =SUM(G24+P24+Y24+AH24+AQ24+AZ24+BI24+BR24+CA24+CJ24+CS24+DB24+DK24+DT24+EC24+EL24+EU24+FD24+FM24+FV24+GE24+GN24+GW24+HF24+HO24+HX24+IG24+IP24+IY24+JH24+JQ24+JZ24+KI24+KR24+LA24+LJ24+LS24+MB24+MK24+MT24+NC24+NL24+NU24+OD24+OM24+OV24+PE24+PN24+PW24+QF24+QO24) -> 6 | QV24: =SUM(H24+Q24+Z24+AI24+AR24+BA24+BJ24+BS24+CB24+CK24+CT24+DC24+DL24+DU24+ED24+EM24+EV24+FE24+FN24+FW24+GF24+GO24+GX24+HG24+HP24+HY24+IH24+IQ24+IZ24+JI24+JR24+KA24+KJ24+KS24+LB24+LK24+LT24+MC24+ML24+MU24+ND24+NM24+NV24+OE24+ON24+OW24+PF24+PO24+PX24+QG24+QP24) -> 82 | QW24: =SUM(I24+R24+AA24+AJ24+AS24+BB24+BK24+BT24+CC24+CL24+CU24+DD24+DM24+DV24+EE24+EN24+EW24+FF24+FO24+FX24+GG24+GP24+GY24+HH24+HQ24+HZ24+II24+IR24+JA24+JJ24+JS24+KB24+KK24+KT24+LC24+LL24+LU24+MD24+MM24+MV24+NE24+NN24+NW24+OF24+OO24+OX24+PG24+PP24+PY24+QH24+QQ24) -> 38 | QY24: =SUM(J24,S24,AB24,AK24,AT24,BC24,BL24,BU24,CD24,CM24,CV24,DE24,DN24,DW24,EF24,EO24,FP24,FY24,GH24,GQ24,HI24,HR24,IS24,JB24,JK24,JT24,KC24,KL24,KU24,LD24,LM24,LV24,ME24,MN24,MW24,NF24,NO24,NX24,OG24,OP24,OY24,PH24,PZ24)/5 -> 16 | RA24: =MAX(C24,L24,AD24,AM24,AV24,BN24,BW24,CF24,CX24,DG24,DP24,DY24,EH24,FI24,FR24,GA24,GJ24,HK24,IL24,IU24,JD24,JM24,JV24,KE24,KW24,LO24,LX24,MG24,MP24,MY24,NH24,NQ24,OI24,PA24,PS24) -> 19 | RB24: =MAX(D24,M24,AE24,AN24,AW24,BO24,BX24,CG24,CY24,DH24,DQ24,DZ24,EI24,FJ24,FS24,GB24,GK24,HL24,IM24,IV24,JE24,JN24,JW24,KF24,KX24,LP24,LY24,MH24,MQ24,MZ24,NI24,NR24,OJ24,PB24,PT24) -> 23 | RC24: =MAX(E24,N24,AF24,AO24,AX24,BP24,BY24,CH24,CZ24,DI24,DR24,EA24,EJ24,FK24,FT24,GC24,GL24,HM24,IN24,IW24,JF24,JO24,JX24,KG24,KY24,LQ24,LZ24,MI24,MR24,NA24,NJ24,NS24,OK24,PC24,PU24) -> 40 | RD24: =MIN(C24,L24,AD24,AM24,AV24,BN24,BW24,CF24,CX24,DG24,DP24,DY24,EH24,FI24,FR24,GA24,GJ24,HK24,IL24,IU24,JD24,JM24,JV24,KE24,KW24,LO24,LX24,MG24,MP24,MY24,NH24,NQ24,OI24,PA24,PS24) -> 10 | RE24: =MIN(D24,M24,AE24,AN24,AW24,BO24,BX24,CG24,CY24,DH24,DQ24,DZ24,EI24,FJ24,FS24,GB24,GK24,HL24,IM24,IV24,JE24,JN24,JW24,KF24,KX24,LP24,LY24,MH24,MQ24,MZ24,NI24,NR24,OJ24,PB24,PT24) -> 10 | RF24: =MIN(E24,N24,AF24,AO24,AX24,BP24,BY24,CH24,CZ24,DI24,DR24,EA24,EJ24,FK24,FT24,GC24,GL24,HM24,IN24,IW24,JF24,JO24,JX24,KG24,KY24,LQ24,LZ24,MI24,MR24,NA24,NJ24,NS24,OK24,PC24,PU24) -> 23 | RH24: =MAX(W24,BG24,CQ24,HD24,LH24,OB24,OT24) -> 38 | RI24: =MIN(W24,BG24,CQ24,HD24,LH24,OB24,OT24) -> 24 | RK24: =IFERROR(SUM(E24,N24,W24,AF24,AO24,AX24,BG24,BP24,BY24,CH24,CQ24,CZ24,DI24,DR24,EA24,EJ24,FK24,GC24,GL24,HD24,HM24,IN24,IW24,JF24,JO24,JX24,KG24,KY24,LH24,LQ24,LZ24,MI24,MR24,NA24,NJ24,NS24,OB24,OK24,OT24,PC24,)/QY24,0) -> 29.8125 | RM24: =MAX(ES24,IE24) -> 102 | RN24: =MIN(ES24,IE24) -> 102 | RP24: =SUM(EX24,IJ24)/5 -> 1
A25: ='Name List'!B25 -> Archie Fraser | E25: =IF(C25=0,"",C25+D25) | J25: =IF(E25="","",'Name List'!$I$4) | W25: =IF(U25=0,"",U25+V25) | AB25: =IF(W25="","",'Name List'!$I$4) | AF25: =IF(AD25=0,"",AD25+AE25) | AK25: =IF(AF25="","",'Name List'!$I$4) | AM25: 15 | AN25: 21 | AO25: =IF(AM25=0,"",AM25+AN25) -> 36 | AP25: 0 | AQ25: 2 | AR25: 6 | AS25: 2 | AT25: =IF(AO25="","",'Name List'!$I$4) -> 5 | AX25: =IF(AV25=0,"",AV25+AW25) | BC25: =IF(AX25="","",'Name List'!$I$4) | BG25: =IF(BE25=0,"",BE25+BF25) | BL25: =IF(BG25="","",'Name List'!$I$4) | BW25: 19 | BX25: 18 | BY25: =IF(BW25=0,"",BW25+BX25) -> 37 | BZ25: 0 | CA25: 1 | CB25: 7 | CC25: 1 | CD25: =IF(BY25="","",'Name List'!$I$4) -> 5 | CH25: =IF(CF25=0,"",CF25+CG25) | CM25: =IF(CH25="","",'Name List'!$I$4) | CQ25: =IF(CO25=0,"",CO25+CP25) | CV25: =IF(CQ25="","",'Name List'!$I$4) | CZ25: =IF(CX25=0,"",CX25+CY25) | DE25: =IF(CZ25="","",'Name List'!$I$4) | DI25: =IF(DG25=0,"",DG25+DH25) | DN25: =IF(DI25="","",'Name List'!$I$4) | DR25: =IF(DP25=0,"",DP25+DQ25) | DW25: =IF(DR25="","",'Name List'!$I$4) | EA25: =IF(DY25=0,"",DY25+DZ25) | EF25: =IF(EA25="","",'Name List'!$I$4) | EJ25: =IF(EH25=0,"",EH25+EI25) | EO25: =IF(EJ25="","",'Name List'!$I$4) | EX25: =IF(ES25="","",'Name List'!$I$4) | FK25: =IF(FI25=0,"",FI25+FJ25) | FP25: =IF(FK25="","",'Name List'!$I$4) | FT25: =IF(FR25=0,"",FR25+FS25) | FY25: =IF(FT25="","",'Name List'!$I$4) | GC25: =IF(GA25=0,"",GA25+GB25) | GH25: =IF(GC25="","",'Name List'!$I$4) | GL25: =IF(GJ25=0,"",GJ25+GK25) | GQ25: =IF(GL25="","",'Name List'!$I$4) | HD25: =IF(HB25=0,"",HB25+HC25) | HI25: =IF(HD25="","",'Name List'!$I$4) | HM25: =IF(HK25=0,"",HK25+HL25) | HR25: =IF(HM25="","",'Name List'!$I$4) | IJ25: =IF(IE25="","",'Name List'!$I$4) | QR25: =IF(QM25="","",'Name List'!$I$4) | QT25: =SUM(F25+O25+X25+AG25+AP25+AY25+BH25+BQ25+BZ25+CI25+CR25+DA25+DJ25+DS25+EB25+EK25+ET25+FC25+FL25+FU25+GD25+GM25+GV25+HE25+HN25+HW25+IF25+IO25+IX25+JG25+JP25+JY25+KH25+KQ25+KZ25+LI25+LR25+MA25+MJ25+MS25+NB25+NK25+NT25+OC25+OL25+OU25+PD25+PM25+PV25+QE25+QN25) -> 0 | QU25: =SUM(G25+P25+Y25+AH25+AQ25+AZ25+BI25+BR25+CA25+CJ25+CS25+DB25+DK25+DT25+EC25+EL25+EU25+FD25+FM25+FV25+GE25+GN25+GW25+HF25+HO25+HX25+IG25+IP25+IY25+JH25+JQ25+JZ25+KI25+KR25+LA25+LJ25+LS25+MB25+MK25+MT25+NC25+NL25+NU25+OD25+OM25+OV25+PE25+PN25+PW25+QF25+QO25) -> 3 | QV25: =SUM(H25+Q25+Z25+AI25+AR25+BA25+BJ25+BS25+CB25+CK25+CT25+DC25+DL25+DU25+ED25+EM25+EV25+FE25+FN25+FW25+GF25+GO25+GX25+HG25+HP25+HY25+IH25+IQ25+IZ25+JI25+JR25+KA25+KJ25+KS25+LB25+LK25+LT25+MC25+ML25+MU25+ND25+NM25+NV25+OE25+ON25+OW25+PF25+PO25+PX25+QG25+QP25) -> 13 | QW25: =SUM(I25+R25+AA25+AJ25+AS25+BB25+BK25+BT25+CC25+CL25+CU25+DD25+DM25+DV25+EE25+EN25+EW25+FF25+FO25+FX25+GG25+GP25+GY25+HH25+HQ25+HZ25+II25+IR25+JA25+JJ25+JS25+KB25+KK25+KT25+LC25+LL25+LU25+MD25+MM25+MV25+NE25+NN25+NW25+OF25+OO25+OX25+PG25+PP25+PY25+QH25+QQ25) -> 3 | QY25: =SUM(J25,S25,AB25,AK25,AT25,BC25,BL25,BU25,CD25,CM25,CV25,DE25,DN25,DW25,EF25,EO25,FP25,FY25,GH25,GQ25,HI25,HR25,IS25,JB25,JK25,JT25,KC25,KL25,KU25,LD25,LM25,LV25,ME25,MN25,MW25,NF25,NO25,NX25,OG25,OP25,OY25,PH25,PZ25)/5 -> 2 | RA25: =MAX(C25,L25,AD25,AM25,AV25,BN25,BW25,CF25,CX25,DG25,DP25,DY25,EH25,FI25,FR25,GA25,GJ25,HK25,IL25,IU25,JD25,JM25,JV25,KE25,KW25,LO25,LX25,MG25,MP25,MY25,NH25,NQ25,OI25,PA25,PS25) -> 19 | RB25: =MAX(D25,M25,AE25,AN25,AW25,BO25,BX25,CG25,CY25,DH25,DQ25,DZ25,EI25,FJ25,FS25,GB25,GK25,HL25,IM25,IV25,JE25,JN25,JW25,KF25,KX25,LP25,LY25,MH25,MQ25,MZ25,NI25,NR25,OJ25,PB25,PT25) -> 21 | RC25: =MAX(E25,N25,AF25,AO25,AX25,BP25,BY25,CH25,CZ25,DI25,DR25,EA25,EJ25,FK25,FT25,GC25,GL25,HM25,IN25,IW25,JF25,JO25,JX25,KG25,KY25,LQ25,LZ25,MI25,MR25,NA25,NJ25,NS25,OK25,PC25,PU25) -> 37 | RD25: =MIN(C25,L25,AD25,AM25,AV25,BN25,BW25,CF25,CX25,DG25,DP25,DY25,EH25,FI25,FR25,GA25,GJ25,HK25,IL25,IU25,JD25,JM25,JV25,KE25,KW25,LO25,LX25,MG25,MP25,MY25,NH25,NQ25,OI25,PA25,PS25) -> 15 | RE25: =MIN(D25,M25,AE25,AN25,AW25,BO25,BX25,CG25,CY25,DH25,DQ25,DZ25,EI25,FJ25,FS25,GB25,GK25,HL25,IM25,IV25,JE25,JN25,JW25,KF25,KX25,LP25,LY25,MH25,MQ25,MZ25,NI25,NR25,OJ25,PB25,PT25) -> 18 | RF25: =MIN(E25,N25,AF25,AO25,AX25,BP25,BY25,CH25,CZ25,DI25,DR25,EA25,EJ25,FK25,FT25,GC25,GL25,HM25,IN25,IW25,JF25,JO25,JX25,KG25,KY25,LQ25,LZ25,MI25,MR25,NA25,NJ25,NS25,OK25,PC25,PU25) -> 36 | RH25: =MAX(W25,BG25,CQ25,HD25,LH25,OB25,OT25) -> 0 | RI25: =MIN(W25,BG25,CQ25,HD25,LH25,OB25,OT25) -> 0 | RK25: =IFERROR(SUM(E25,N25,W25,AF25,AO25,AX25,BG25,BP25,BY25,CH25,CQ25,CZ25,DI25,DR25,EA25,EJ25,FK25,GC25,GL25,HD25,HM25,IN25,IW25,JF25,JO25,JX25,KG25,KY25,LH25,LQ25,LZ25,MI25,MR25,NA25,NJ25,NS25,OB25,OK25,OT25,PC25,)/QY25,0) -> 36.5 | RM25: =MAX(ES25,IE25) -> 0 | RN25: =MIN(ES25,IE25) -> 0 | RP25: =SUM(EX25,IJ25)/5 -> 0
A26: ='Name List'!B26 -> Ross Fraser | E26: =IF(C26=0,"",C26+D26) | J26: =IF(E26="","",'Name List'!$I$4) | W26: =IF(U26=0,"",U26+V26) | AB26: =IF(W26="","",'Name List'!$I$4) | AF26: =IF(AD26=0,"",AD26+AE26) | AK26: =IF(AF26="","",'Name List'!$I$4) | AM26: 14 | AN26: 15 | AO26: =IF(AM26=0,"",AM26+AN26) -> 29 | AP26: 0 | AQ26: 0 | AR26: 5 | AS26: 2 | AT26: =IF(AO26="","",'Name List'!$I$4) -> 5 | AX26: =IF(AV26=0,"",AV26+AW26) | BC26: =IF(AX26="","",'Name List'!$I$4) | BG26: =IF(BE26=0,"",BE26+BF26) | BL26: =IF(BG26="","",'Name List'!$I$4) | BW26: 17 | BX26: 14 | BY26: =IF(BW26=0,"",BW26+BX26) -> 31 | BZ26: 0 | CA26: 1 | CB26: 5 | CC26: 2 | CD26: =IF(BY26="","",'Name List'!$I$4) -> 5 | CH26: =IF(CF26=0,"",CF26+CG26) | CM26: =IF(CH26="","",'Name List'!$I$4) | CO26: 17 | CP26: 16 | CQ26: =IF(CO26=0,"",CO26+CP26) -> 33 | CR26: 0 | CS26: 1 | CT26: 5 | CU26: 2 | CV26: =IF(CQ26="","",'Name List'!$I$4) -> 5 | CZ26: =IF(CX26=0,"",CX26+CY26) | DE26: =IF(CZ26="","",'Name List'!$I$4) | DI26: =IF(DG26=0,"",DG26+DH26) | DN26: =IF(DI26="","",'Name List'!$I$4) | DR26: =IF(DP26=0,"",DP26+DQ26) | DW26: =IF(DR26="","",'Name List'!$I$4) | EA26: =IF(DY26=0,"",DY26+DZ26) | EF26: =IF(EA26="","",'Name List'!$I$4) | EJ26: =IF(EH26=0,"",EH26+EI26) | EO26: =IF(EJ26="","",'Name List'!$I$4) | EX26: =IF(ES26="","",'Name List'!$I$4) | FK26: =IF(FI26=0,"",FI26+FJ26) | FP26: =IF(FK26="","",'Name List'!$I$4) | FT26: =IF(FR26=0,"",FR26+FS26) | FY26: =IF(FT26="","",'Name List'!$I$4) | GC26: =IF(GA26=0,"",GA26+GB26) | GH26: =IF(GC26="","",'Name List'!$I$4) | GL26: =IF(GJ26=0,"",GJ26+GK26) | GQ26: =IF(GL26="","",'Name List'!$I$4) | HD26: =IF(HB26=0,"",HB26+HC26) | HI26: =IF(HD26="","",'Name List'!$I$4) | HM26: =IF(HK26=0,"",HK26+HL26) | HR26: =IF(HM26="","",'Name List'!$I$4) | IJ26: =IF(IE26="","",'Name List'!$I$4) | QR26: =IF(QM26="","",'Name List'!$I$4) | QT26: =SUM(F26+O26+X26+AG26+AP26+AY26+BH26+BQ26+BZ26+CI26+CR26+DA26+DJ26+DS26+EB26+EK26+ET26+FC26+FL26+FU26+GD26+GM26+GV26+HE26+HN26+HW26+IF26+IO26+IX26+JG26+JP26+JY26+KH26+KQ26+KZ26+LI26+LR26+MA26+MJ26+MS26+NB26+NK26+NT26+OC26+OL26+OU26+PD26+PM26+PV26+QE26+QN26) -> 0 | QU26: =SUM(G26+P26+Y26+AH26+AQ26+AZ26+BI26+BR26+CA26+CJ26+CS26+DB26+DK26+DT26+EC26+EL26+EU26+FD26+FM26+FV26+GE26+GN26+GW26+HF26+HO26+HX26+IG26+IP26+IY26+JH26+JQ26+JZ26+KI26+KR26+LA26+LJ26+LS26+MB26+MK26+MT26+NC26+NL26+NU26+OD26+OM26+OV26+PE26+PN26+PW26+QF26+QO26) -> 2 | QV26: =SUM(H26+Q26+Z26+AI26+AR26+BA26+BJ26+BS26+CB26+CK26+CT26+DC26+DL26+DU26+ED26+EM26+EV26+FE26+FN26+FW26+GF26+GO26+GX26+HG26+HP26+HY26+IH26+IQ26+IZ26+JI26+JR26+KA26+KJ26+KS26+LB26+LK26+LT26+MC26+ML26+MU26+ND26+NM26+NV26+OE26+ON26+OW26+PF26+PO26+PX26+QG26+QP26) -> 15 | QW26: =SUM(I26+R26+AA26+AJ26+AS26+BB26+BK26+BT26+CC26+CL26+CU26+DD26+DM26+DV26+EE26+EN26+EW26+FF26+FO26+FX26+GG26+GP26+GY26+HH26+HQ26+HZ26+II26+IR26+JA26+JJ26+JS26+KB26+KK26+KT26+LC26+LL26+LU26+MD26+MM26+MV26+NE26+NN26+NW26+OF26+OO26+OX26+PG26+PP26+PY26+QH26+QQ26) -> 6 | QY26: =SUM(J26,S26,AB26,AK26,AT26,BC26,BL26,BU26,CD26,CM26,CV26,DE26,DN26,DW26,EF26,EO26,FP26,FY26,GH26,GQ26,HI26,HR26,IS26,JB26,JK26,JT26,KC26,KL26,KU26,LD26,LM26,LV26,ME26,MN26,MW26,NF26,NO26,NX26,OG26,OP26,OY26,PH26,PZ26)/5 -> 3 | RA26: =MAX(C26,L26,AD26,AM26,AV26,BN26,BW26,CF26,CX26,DG26,DP26,DY26,EH26,FI26,FR26,GA26,GJ26,HK26,IL26,IU26,JD26,JM26,JV26,KE26,KW26,LO26,LX26,MG26,MP26,MY26,NH26,NQ26,OI26,PA26,PS26) -> 17 | RB26: =MAX(D26,M26,AE26,AN26,AW26,BO26,BX26,CG26,CY26,DH26,DQ26,DZ26,EI26,FJ26,FS26,GB26,GK26,HL26,IM26,IV26,JE26,JN26,JW26,KF26,KX26,LP26,LY26,MH26,MQ26,MZ26,NI26,NR26,OJ26,PB26,PT26) -> 15 | RC26: =MAX(E26,N26,AF26,AO26,AX26,BP26,BY26,CH26,CZ26,DI26,DR26,EA26,EJ26,FK26,FT26,GC26,GL26,HM26,IN26,IW26,JF26,JO26,JX26,KG26,KY26,LQ26,LZ26,MI26,MR26,NA26,NJ26,NS26,OK26,PC26,PU26) -> 31 | RD26: =MIN(C26,L26,AD26,AM26,AV26,BN26,BW26,CF26,CX26,DG26,DP26,DY26,EH26,FI26,FR26,GA26,GJ26,HK26,IL26,IU26,JD26,JM26,JV26,KE26,KW26,LO26,LX26,MG26,MP26,MY26,NH26,NQ26,OI26,PA26,PS26) -> 14 | RE26: =MIN(D26,M26,AE26,AN26,AW26,BO26,BX26,CG26,CY26,DH26,DQ26,DZ26,EI26,FJ26,FS26,GB26,GK26,HL26,IM26,IV26,JE26,JN26,JW26,KF26,KX26,LP26,LY26,MH26,MQ26,MZ26,NI26,NR26,OJ26,PB26,PT26) -> 14 | RF26: =MIN(E26,N26,AF26,AO26,AX26,BP26,BY26,CH26,CZ26,DI26,DR26,EA26,EJ26,FK26,FT26,GC26,GL26,HM26,IN26,IW26,JF26,JO26,JX26,KG26,KY26,LQ26,LZ26,MI26,MR26,NA26,NJ26,NS26,OK26,PC26,PU26) -> 29 | RH26: =MAX(W26,BG26,CQ26,HD26,LH26,OB26,OT26) -> 33 | RI26: =MIN(W26,BG26,CQ26,HD26,LH26,OB26,OT26) -> 33 | RK26: =IFERROR(SUM(E26,N26,W26,AF26,AO26,AX26,BG26,BP26,BY26,CH26,CQ26,CZ26,DI26,DR26,EA26,EJ26,FK26,GC26,GL26,HD26,HM26,IN26,IW26,JF26,JO26,JX26,KG26,KY26,LH26,LQ26,LZ26,MI26,MR26,NA26,NJ26,NS26,OB26,OK26,OT26,PC26,)/QY26,0) -> 31 | RM26: =MAX(ES26,IE26) -> 0 | RN26: =MIN(ES26,IE26) -> 0 | RP26: =SUM(EX26,IJ26)/5 -> 0
A27: ='Name List'!B27 -> Nick Garner | E27: =IF(C27=0,"",C27+D27) | J27: =IF(E27="","",'Name List'!$I$4) | U27: 17 | V27: 11 | W27: =IF(U27=0,"",U27+V27) -> 28 | X27: 0 | Y27: 0 | Z27: 4 | AA27: 3 | AB27: =IF(W27="","",'Name List'!$I$4) -> 5 | AD27: 18 | AE27: 16 | AF27: =IF(AD27=0,"",AD27+AE27) -> 34 | AG27: 0 | AH27: 3 | AI27: 5 | AJ27: 4 | AK27: =IF(AF27="","",'Name List'!$I$4) -> 5 | AO27: =IF(AM27=0,"",AM27+AN27) | AT27: =IF(AO27="","",'Name List'!$I$4) | AX27: =IF(AV27=0,"",AV27+AW27) | BC27: =IF(AX27="","",'Name List'!$I$4) | BE27: 12 | BF27: 15 | BG27: =IF(BE27=0,"",BE27+BF27) -> 27 | BH27: 0 | BI27: 0 | BJ27: 4 | BK27: 3 | BL27: =IF(BG27="","",'Name List'!$I$4) -> 5 | BY27: =IF(BW27=0,"",BW27+BX27) | CD27: =IF(BY27="","",'Name List'!$I$4) | CH27: =IF(CF27=0,"",CF27+CG27) | CM27: =IF(CH27="","",'Name List'!$I$4) | CO27: 13 | CP27: 18 | CQ27: =IF(CO27=0,"",CO27+CP27) -> 31 | CR27: 0 | CS27: 0 | CT27: 4 | CU27: 0 | CV27: =IF(CQ27="","",'Name List'!$I$4) -> 5 | CX27: 20 | CY27: 14 | CZ27: =IF(CX27=0,"",CX27+CY27) -> 34 | DA27: 0 | DB27: 1 | DC27: 5 | DD27: 1 | DE27: =IF(CZ27="","",'Name List'!$I$4) -> 5 | DI27: =IF(DG27=0,"",DG27+DH27) | DN27: =IF(DI27="","",'Name List'!$I$4) | DP27: 14 | DQ27: 16 | DR27: =IF(DP27=0,"",DP27+DQ27) -> 30 | DS27: 0 | DT27: 0 | DU27: 4 | DV27: 1 | DW27: =IF(DR27="","",'Name List'!$I$4) -> 5 | DY27: 11 | DZ27: 14 | EA27: =IF(DY27=0,"",DY27+DZ27) -> 25 | EB27: 0 | EC27: 0 | ED27: 5 | EE27: 5 | EF27: =IF(EA27="","",'Name List'!$I$4) -> 5 | EJ27: =IF(EH27=0,"",EH27+EI27) | EO27: =IF(EJ27="","",'Name List'!$I$4) | EX27: =IF(ES27="","",'Name List'!$I$4) | FK27: =IF(FI27=0,"",FI27+FJ27) | FP27: =IF(FK27="","",'Name List'!$I$4) | FT27: =IF(FR27=0,"",FR27+FS27) | FY27: =IF(FT27="","",'Name List'!$I$4) | GC27: =IF(GA27=0,"",GA27+GB27) | GH27: =IF(GC27="","",'Name List'!$I$4) | GL27: =IF(GJ27=0,"",GJ27+GK27) | GQ27: =IF(GL27="","",'Name List'!$I$4) | HD27: =IF(HB27=0,"",HB27+HC27) | HI27: =IF(HD27="","",'Name List'!$I$4) | HM27: =IF(HK27=0,"",HK27+HL27) | HR27: =IF(HM27="","",'Name List'!$I$4) | IJ27: =IF(IE27="","",'Name List'!$I$4) | QR27: =IF(QM27="","",'Name List'!$I$4) | QT27: =SUM(F27+O27+X27+AG27+AP27+AY27+BH27+BQ27+BZ27+CI27+CR27+DA27+DJ27+DS27+EB27+EK27+ET27+FC27+FL27+FU27+GD27+GM27+GV27+HE27+HN27+HW27+IF27+IO27+IX27+JG27+JP27+JY27+KH27+KQ27+KZ27+LI27+LR27+MA27+MJ27+MS27+NB27+NK27+NT27+OC27+OL27+OU27+PD27+PM27+PV27+QE27+QN27) -> 0 | QU27: =SUM(G27+P27+Y27+AH27+AQ27+AZ27+BI27+BR27+CA27+CJ27+CS27+DB27+DK27+DT27+EC27+EL27+EU27+FD27+FM27+FV27+GE27+GN27+GW27+HF27+HO27+HX27+IG27+IP27+IY27+JH27+JQ27+JZ27+KI27+KR27+LA27+LJ27+LS27+MB27+MK27+MT27+NC27+NL27+NU27+OD27+OM27+OV27+PE27+PN27+PW27+QF27+QO27) -> 4 | QV27: =SUM(H27+Q27+Z27+AI27+AR27+BA27+BJ27+BS27+CB27+CK27+CT27+DC27+DL27+DU27+ED27+EM27+EV27+FE27+FN27+FW27+GF27+GO27+GX27+HG27+HP27+HY27+IH27+IQ27+IZ27+JI27+JR27+KA27+KJ27+KS27+LB27+LK27+LT27+MC27+ML27+MU27+ND27+NM27+NV27+OE27+ON27+OW27+PF27+PO27+PX27+QG27+QP27) -> 31 | QW27: =SUM(I27+R27+AA27+AJ27+AS27+BB27+BK27+BT27+CC27+CL27+CU27+DD27+DM27+DV27+EE27+EN27+EW27+FF27+FO27+FX27+GG27+GP27+GY27+HH27+HQ27+HZ27+II27+IR27+JA27+JJ27+JS27+KB27+KK27+KT27+LC27+LL27+LU27+MD27+MM27+MV27+NE27+NN27+NW27+OF27+OO27+OX27+PG27+PP27+PY27+QH27+QQ27) -> 17 | QY27: =SUM(J27,S27,AB27,AK27,AT27,BC27,BL27,BU27,CD27,CM27,CV27,DE27,DN27,DW27,EF27,EO27,FP27,FY27,GH27,GQ27,HI27,HR27,IS27,JB27,JK27,JT27,KC27,KL27,KU27,LD27,LM27,LV27,ME27,MN27,MW27,NF27,NO27,NX27,OG27,OP27,OY27,PH27,PZ27)/5 -> 7 | RA27: =MAX(C27,L27,AD27,AM27,AV27,BN27,BW27,CF27,CX27,DG27,DP27,DY27,EH27,FI27,FR27,GA27,GJ27,HK27,IL27,IU27,JD27,JM27,JV27,KE27,KW27,LO27,LX27,MG27,MP27,MY27,NH27,NQ27,OI27,PA27,PS27) -> 20 | RB27: =MAX(D27,M27,AE27,AN27,AW27,BO27,BX27,CG27,CY27,DH27,DQ27,DZ27,EI27,FJ27,FS27,GB27,GK27,HL27,IM27,IV27,JE27,JN27,JW27,KF27,KX27,LP27,LY27,MH27,MQ27,MZ27,NI27,NR27,OJ27,PB27,PT27) -> 16 | RC27: =MAX(E27,N27,AF27,AO27,AX27,BP27,BY27,CH27,CZ27,DI27,DR27,EA27,EJ27,FK27,FT27,GC27,GL27,HM27,IN27,IW27,JF27,JO27,JX27,KG27,KY27,LQ27,LZ27,MI27,MR27,NA27,NJ27,NS27,OK27,PC27,PU27) -> 34 | RD27: =MIN(C27,L27,AD27,AM27,AV27,BN27,BW27,CF27,CX27,DG27,DP27,DY27,EH27,FI27,FR27,GA27,GJ27,HK27,IL27,IU27,JD27,JM27,JV27,KE27,KW27,LO27,LX27,MG27,MP27,MY27,NH27,NQ27,OI27,PA27,PS27) -> 11 | RE27: =MIN(D27,M27,AE27,AN27,AW27,BO27,BX27,CG27,CY27,DH27,DQ27,DZ27,EI27,FJ27,FS27,GB27,GK27,HL27,IM27,IV27,JE27,JN27,JW27,KF27,KX27,LP27,LY27,MH27,MQ27,MZ27,NI27,NR27,OJ27,PB27,PT27) -> 14 | RF27: =MIN(E27,N27,AF27,AO27,AX27,BP27,BY27,CH27,CZ27,DI27,DR27,EA27,EJ27,FK27,FT27,GC27,GL27,HM27,IN27,IW27,JF27,JO27,JX27,KG27,KY27,LQ27,LZ27,MI27,MR27,NA27,NJ27,NS27,OK27,PC27,PU27) -> 25 | RH27: =MAX(W27,BG27,CQ27,HD27,LH27,OB27,OT27) -> 31 | RI27: =MIN(W27,BG27,CQ27,HD27,LH27,OB27,OT27) -> 27 | RK27: =IFERROR(SUM(E27,N27,W27,AF27,AO27,AX27,BG27,BP27,BY27,CH27,CQ27,CZ27,DI27,DR27,EA27,EJ27,FK27,GC27,GL27,HD27,HM27,IN27,IW27,JF27,JO27,JX27,KG27,KY27,LH27,LQ27,LZ27,MI27,MR27,NA27,NJ27,NS27,OB27,OK27,OT27,PC27,)/QY27,0) -> 29.857143 | RM27: =MAX(ES27,IE27) -> 0 | RN27: =MIN(ES27,IE27) -> 0 | RP27: =SUM(EX27,IJ27)/5 -> 0
A28: ='Name List'!B28 -> Stuart Gay | E28: =IF(C28=0,"",C28+D28) | J28: =IF(E28="","",'Name List'!$I$4) | W28: =IF(U28=0,"",U28+V28) | AB28: =IF(W28="","",'Name List'!$I$4) | AF28: =IF(AD28=0,"",AD28+AE28) | AK28: =IF(AF28="","",'Name List'!$I$4) | AO28: =IF(AM28=0,"",AM28+AN28) | AT28: =IF(AO28="","",'Name List'!$I$4) | AX28: =IF(AV28=0,"",AV28+AW28) | BC28: =IF(AX28="","",'Name List'!$I$4) | BG28: =IF(BE28=0,"",BE28+BF28) | BL28: =IF(BG28="","",'Name List'!$I$4) | BY28: =IF(BW28=0,"",BW28+BX28) | CD28: =IF(BY28="","",'Name List'!$I$4) | CH28: =IF(CF28=0,"",CF28+CG28) | CM28: =IF(CH28="","",'Name List'!$I$4) | CO28: 21 | CP28: 18 | CQ28: =IF(CO28=0,"",CO28+CP28) -> 39 | CR28: 0 | CS28: 0 | CT28: 5 | CU28: 1 | CV28: =IF(CQ28="","",'Name List'!$I$4) -> 5 | CZ28: =IF(CX28=0,"",CX28+CY28) | DE28: =IF(CZ28="","",'Name List'!$I$4) | DI28: =IF(DG28=0,"",DG28+DH28) | DN28: =IF(DI28="","",'Name List'!$I$4) | DR28: =IF(DP28=0,"",DP28+DQ28) | DW28: =IF(DR28="","",'Name List'!$I$4) | EA28: =IF(DY28=0,"",DY28+DZ28) | EF28: =IF(EA28="","",'Name List'!$I$4) | EJ28: =IF(EH28=0,"",EH28+EI28) | EO28: =IF(EJ28="","",'Name List'!$I$4) | EX28: =IF(ES28="","",'Name List'!$I$4) | FK28: =IF(FI28=0,"",FI28+FJ28) | FP28: =IF(FK28="","",'Name List'!$I$4) | FT28: =IF(FR28=0,"",FR28+FS28) | FY28: =IF(FT28="","",'Name List'!$I$4) | GC28: =IF(GA28=0,"",GA28+GB28) | GH28: =IF(GC28="","",'Name List'!$I$4) | GL28: =IF(GJ28=0,"",GJ28+GK28) | GQ28: =IF(GL28="","",'Name List'!$I$4) | HD28: =IF(HB28=0,"",HB28+HC28) | HI28: =IF(HD28="","",'Name List'!$I$4) | HM28: =IF(HK28=0,"",HK28+HL28) | HR28: =IF(HM28="","",'Name List'!$I$4) | IJ28: =IF(IE28="","",'Name List'!$I$4) | QR28: =IF(QM28="","",'Name List'!$I$4) | QT28: =SUM(F28+O28+X28+AG28+AP28+AY28+BH28+BQ28+BZ28+CI28+CR28+DA28+DJ28+DS28+EB28+EK28+ET28+FC28+FL28+FU28+GD28+GM28+GV28+HE28+HN28+HW28+IF28+IO28+IX28+JG28+JP28+JY28+KH28+KQ28+KZ28+LI28+LR28+MA28+MJ28+MS28+NB28+NK28+NT28+OC28+OL28+OU28+PD28+PM28+PV28+QE28+QN28) -> 0 | QU28: =SUM(G28+P28+Y28+AH28+AQ28+AZ28+BI28+BR28+CA28+CJ28+CS28+DB28+DK28+DT28+EC28+EL28+EU28+FD28+FM28+FV28+GE28+GN28+GW28+HF28+HO28+HX28+IG28+IP28+IY28+JH28+JQ28+JZ28+KI28+KR28+LA28+LJ28+LS28+MB28+MK28+MT28+NC28+NL28+NU28+OD28+OM28+OV28+PE28+PN28+PW28+QF28+QO28) -> 0 | QV28: =SUM(H28+Q28+Z28+AI28+AR28+BA28+BJ28+BS28+CB28+CK28+CT28+DC28+DL28+DU28+ED28+EM28+EV28+FE28+FN28+FW28+GF28+GO28+GX28+HG28+HP28+HY28+IH28+IQ28+IZ28+JI28+JR28+KA28+KJ28+KS28+LB28+LK28+LT28+MC28+ML28+MU28+ND28+NM28+NV28+OE28+ON28+OW28+PF28+PO28+PX28+QG28+QP28) -> 5 | QW28: =SUM(I28+R28+AA28+AJ28+AS28+BB28+BK28+BT28+CC28+CL28+CU28+DD28+DM28+DV28+EE28+EN28+EW28+FF28+FO28+FX28+GG28+GP28+GY28+HH28+HQ28+HZ28+II28+IR28+JA28+JJ28+JS28+KB28+KK28+KT28+LC28+LL28+LU28+MD28+MM28+MV28+NE28+NN28+NW28+OF28+OO28+OX28+PG28+PP28+PY28+QH28+QQ28) -> 1 | QY28: =SUM(J28,S28,AB28,AK28,AT28,BC28,BL28,BU28,CD28,CM28,CV28,DE28,DN28,DW28,EF28,EO28,FP28,FY28,GH28,GQ28,HI28,HR28,IS28,JB28,JK28,JT28,KC28,KL28,KU28,LD28,LM28,LV28,ME28,MN28,MW28,NF28,NO28,NX28,OG28,OP28,OY28,PH28,PZ28)/5 -> 1 | RA28: =MAX(C28,L28,AD28,AM28,AV28,BN28,BW28,CF28,CX28,DG28,DP28,DY28,EH28,FI28,FR28,GA28,GJ28,HK28,IL28,IU28,JD28,JM28,JV28,KE28,KW28,LO28,LX28,MG28,MP28,MY28,NH28,NQ28,OI28,PA28,PS28) -> 0 | RB28: =MAX(D28,M28,AE28,AN28,AW28,BO28,BX28,CG28,CY28,DH28,DQ28,DZ28,EI28,FJ28,FS28,GB28,GK28,HL28,IM28,IV28,JE28,JN28,JW28,KF28,KX28,LP28,LY28,MH28,MQ28,MZ28,NI28,NR28,OJ28,PB28,PT28) -> 0 | RC28: =MAX(E28,N28,AF28,AO28,AX28,BP28,BY28,CH28,CZ28,DI28,DR28,EA28,EJ28,FK28,FT28,GC28,GL28,HM28,IN28,IW28,JF28,JO28,JX28,KG28,KY28,LQ28,LZ28,MI28,MR28,NA28,NJ28,NS28,OK28,PC28,PU28) -> 0 | RD28: =MIN(C28,L28,AD28,AM28,AV28,BN28,BW28,CF28,CX28,DG28,DP28,DY28,EH28,FI28,FR28,GA28,GJ28,HK28,IL28,IU28,JD28,JM28,JV28,KE28,KW28,LO28,LX28,MG28,MP28,MY28,NH28,NQ28,OI28,PA28,PS28) -> 0 | RE28: =MIN(D28,M28,AE28,AN28,AW28,BO28,BX28,CG28,CY28,DH28,DQ28,DZ28,EI28,FJ28,FS28,GB28,GK28,HL28,IM28,IV28,JE28,JN28,JW28,KF28,KX28,LP28,LY28,MH28,MQ28,MZ28,NI28,NR28,OJ28,PB28,PT28) -> 0 | RF28: =MIN(E28,N28,AF28,AO28,AX28,BP28,BY28,CH28,CZ28,DI28,DR28,EA28,EJ28,FK28,FT28,GC28,GL28,HM28,IN28,IW28,JF28,JO28,JX28,KG28,KY28,LQ28,LZ28,MI28,MR28,NA28,NJ28,NS28,OK28,PC28,PU28) -> 0 | RH28: =MAX(W28,BG28,CQ28,HD28,LH28,OB28,OT28) -> 39 | RI28: =MIN(W28,BG28,CQ28,HD28,LH28,OB28,OT28) -> 39 | RK28: =IFERROR(SUM(E28,N28,W28,AF28,AO28,AX28,BG28,BP28,BY28,CH28,CQ28,CZ28,DI28,DR28,EA28,EJ28,FK28,GC28,GL28,HD28,HM28,IN28,IW28,JF28,JO28,JX28,KG28,KY28,LH28,LQ28,LZ28,MI28,MR28,NA28,NJ28,NS28,OB28,OK28,OT28,PC28,)/QY28,0) -> 39 | RM28: =MAX(ES28,IE28) -> 0 | RN28: =MIN(ES28,IE28) -> 0 | RP28: =SUM(EX28,IJ28)/5 -> 0
A29: ='Name List'!B29 -> Jordan Hall | E29: =IF(C29=0,"",C29+D29) | J29: =IF(E29="","",'Name List'!$I$4) | W29: =IF(U29=0,"",U29+V29) | AB29: =IF(W29="","",'Name List'!$I$4) | AF29: =IF(AD29=0,"",AD29+AE29) | AK29: =IF(AF29="","",'Name List'!$I$4) | AO29: =IF(AM29=0,"",AM29+AN29) | AT29: =IF(AO29="","",'Name List'!$I$4) | AX29: =IF(AV29=0,"",AV29+AW29) | BC29: =IF(AX29="","",'Name List'!$I$4) | BG29: =IF(BE29=0,"",BE29+BF29) | BL29: =IF(BG29="","",'Name List'!$I$4) | BY29: =IF(BW29=0,"",BW29+BX29) | CD29: =IF(BY29="","",'Name List'!$I$4) | CF29: 19 | CG29: 19 | CH29: =IF(CF29=0,"",CF29+CG29) -> 38 | CI29: 1 | CJ29: 2 | CK29: 13 | CL29: 0 | CM29: =IF(CH29="","",'Name List'!$I$4) -> 5 | CQ29: =IF(CO29=0,"",CO29+CP29) | CV29: =IF(CQ29="","",'Name List'!$I$4) | CZ29: =IF(CX29=0,"",CX29+CY29) | DE29: =IF(CZ29="","",'Name List'!$I$4) | DI29: =IF(DG29=0,"",DG29+DH29) | DN29: =IF(DI29="","",'Name List'!$I$4) | DR29: =IF(DP29=0,"",DP29+DQ29) | DW29: =IF(DR29="","",'Name List'!$I$4) | EA29: =IF(DY29=0,"",DY29+DZ29) | EF29: =IF(EA29="","",'Name List'!$I$4) | EJ29: =IF(EH29=0,"",EH29+EI29) | EO29: =IF(EJ29="","",'Name List'!$I$4) | EX29: =IF(ES29="","",'Name List'!$I$4) | FK29: =IF(FI29=0,"",FI29+FJ29) | FP29: =IF(FK29="","",'Name List'!$I$4) | FT29: =IF(FR29=0,"",FR29+FS29) | FY29: =IF(FT29="","",'Name List'!$I$4) | GC29: =IF(GA29=0,"",GA29+GB29) | GH29: =IF(GC29="","",'Name List'!$I$4) | GL29: =IF(GJ29=0,"",GJ29+GK29) | GQ29: =IF(GL29="","",'Name List'!$I$4) | HD29: =IF(HB29=0,"",HB29+HC29) | HI29: =IF(HD29="","",'Name List'!$I$4) | HM29: =IF(HK29=0,"",HK29+HL29) | HR29: =IF(HM29="","",'Name List'!$I$4) | IJ29: =IF(IE29="","",'Name List'!$I$4) | QR29: =IF(QM29="","",'Name List'!$I$4) | QT29: =SUM(F29+O29+X29+AG29+AP29+AY29+BH29+BQ29+BZ29+CI29+CR29+DA29+DJ29+DS29+EB29+EK29+ET29+FC29+FL29+FU29+GD29+GM29+GV29+HE29+HN29+HW29+IF29+IO29+IX29+JG29+JP29+JY29+KH29+KQ29+KZ29+LI29+LR29+MA29+MJ29+MS29+NB29+NK29+NT29+OC29+OL29+OU29+PD29+PM29+PV29+QE29+QN29) -> 1 | QU29: =SUM(G29+P29+Y29+AH29+AQ29+AZ29+BI29+BR29+CA29+CJ29+CS29+DB29+DK29+DT29+EC29+EL29+EU29+FD29+FM29+FV29+GE29+GN29+GW29+HF29+HO29+HX29+IG29+IP29+IY29+JH29+JQ29+JZ29+KI29+KR29+LA29+LJ29+LS29+MB29+MK29+MT29+NC29+NL29+NU29+OD29+OM29+OV29+PE29+PN29+PW29+QF29+QO29) -> 2 | QV29: =SUM(H29+Q29+Z29+AI29+AR29+BA29+BJ29+BS29+CB29+CK29+CT29+DC29+DL29+DU29+ED29+EM29+EV29+FE29+FN29+FW29+GF29+GO29+GX29+HG29+HP29+HY29+IH29+IQ29+IZ29+JI29+JR29+KA29+KJ29+KS29+LB29+LK29+LT29+MC29+ML29+MU29+ND29+NM29+NV29+OE29+ON29+OW29+PF29+PO29+PX29+QG29+QP29) -> 13 | QW29: =SUM(I29+R29+AA29+AJ29+AS29+BB29+BK29+BT29+CC29+CL29+CU29+DD29+DM29+DV29+EE29+EN29+EW29+FF29+FO29+FX29+GG29+GP29+GY29+HH29+HQ29+HZ29+II29+IR29+JA29+JJ29+JS29+KB29+KK29+KT29+LC29+LL29+LU29+MD29+MM29+MV29+NE29+NN29+NW29+OF29+OO29+OX29+PG29+PP29+PY29+QH29+QQ29) -> 0 | QY29: =SUM(J29,S29,AB29,AK29,AT29,BC29,BL29,BU29,CD29,CM29,CV29,DE29,DN29,DW29,EF29,EO29,FP29,FY29,GH29,GQ29,HI29,HR29,IS29,JB29,JK29,JT29,KC29,KL29,KU29,LD29,LM29,LV29,ME29,MN29,MW29,NF29,NO29,NX29,OG29,OP29,OY29,PH29,PZ29)/5 -> 1 | RA29: =MAX(C29,L29,AD29,AM29,AV29,BN29,BW29,CF29,CX29,DG29,DP29,DY29,EH29,FI29,FR29,GA29,GJ29,HK29,IL29,IU29,JD29,JM29,JV29,KE29,KW29,LO29,LX29,MG29,MP29,MY29,NH29,NQ29,OI29,PA29,PS29) -> 19 | RB29: =MAX(D29,M29,AE29,AN29,AW29,BO29,BX29,CG29,CY29,DH29,DQ29,DZ29,EI29,FJ29,FS29,GB29,GK29,HL29,IM29,IV29,JE29,JN29,JW29,KF29,KX29,LP29,LY29,MH29,MQ29,MZ29,NI29,NR29,OJ29,PB29,PT29) -> 19 | RC29: =MAX(E29,N29,AF29,AO29,AX29,BP29,BY29,CH29,CZ29,DI29,DR29,EA29,EJ29,FK29,FT29,GC29,GL29,HM29,IN29,IW29,JF29,JO29,JX29,KG29,KY29,LQ29,LZ29,MI29,MR29,NA29,NJ29,NS29,OK29,PC29,PU29) -> 38 | RD29: =MIN(C29,L29,AD29,AM29,AV29,BN29,BW29,CF29,CX29,DG29,DP29,DY29,EH29,FI29,FR29,GA29,GJ29,HK29,IL29,IU29,JD29,JM29,JV29,KE29,KW29,LO29,LX29,MG29,MP29,MY29,NH29,NQ29,OI29,PA29,PS29) -> 19 | RE29: =MIN(D29,M29,AE29,AN29,AW29,BO29,BX29,CG29,CY29,DH29,DQ29,DZ29,EI29,FJ29,FS29,GB29,GK29,HL29,IM29,IV29,JE29,JN29,JW29,KF29,KX29,LP29,LY29,MH29,MQ29,MZ29,NI29,NR29,OJ29,PB29,PT29) -> 19 | RF29: =MIN(E29,N29,AF29,AO29,AX29,BP29,BY29,CH29,CZ29,DI29,DR29,EA29,EJ29,FK29,FT29,GC29,GL29,HM29,IN29,IW29,JF29,JO29,JX29,KG29,KY29,LQ29,LZ29,MI29,MR29,NA29,NJ29,NS29,OK29,PC29,PU29) -> 38 | RH29: =MAX(W29,BG29,CQ29,HD29,LH29,OB29,OT29) -> 0 | RI29: =MIN(W29,BG29,CQ29,HD29,LH29,OB29,OT29) -> 0 | RK29: =IFERROR(SUM(E29,N29,W29,AF29,AO29,AX29,BG29,BP29,BY29,CH29,CQ29,CZ29,DI29,DR29,EA29,EJ29,FK29,GC29,GL29,HD29,HM29,IN29,IW29,JF29,JO29,JX29,KG29,KY29,LH29,LQ29,LZ29,MI29,MR29,NA29,NJ29,NS29,OB29,OK29,OT29,PC29,)/QY29,0) -> 38 | RM29: =MAX(ES29,IE29) -> 0 | RN29: =MIN(ES29,IE29) -> 0 | RP29: =SUM(EX29,IJ29)/5 -> 0
A30: ='Name List'!B30 -> Gary Hall | E30: =IF(C30=0,"",C30+D30) | J30: =IF(E30="","",'Name List'!$I$4) | W30: =IF(U30=0,"",U30+V30) | AB30: =IF(W30="","",'Name List'!$I$4) | AF30: =IF(AD30=0,"",AD30+AE30) | AK30: =IF(AF30="","",'Name List'!$I$4) | AO30: =IF(AM30=0,"",AM30+AN30) | AT30: =IF(AO30="","",'Name List'!$I$4) | AX30: =IF(AV30=0,"",AV30+AW30) | BC30: =IF(AX30="","",'Name List'!$I$4) | BG30: =IF(BE30=0,"",BE30+BF30) | BL30: =IF(BG30="","",'Name List'!$I$4) | BY30: =IF(BW30=0,"",BW30+BX30) | CD30: =IF(BY30="","",'Name List'!$I$4) | CF30: 9 | CG30: 0 | CH30: =IF(CF30=0,"",CF30+CG30) -> 9 | CI30: 0 | CJ30: 0 | CK30: 4 | CL30: 13 | CM30: =IF(CH30="","",'Name List'!$I$4) -> 5 | CQ30: =IF(CO30=0,"",CO30+CP30) | CV30: =IF(CQ30="","",'Name List'!$I$4) | CZ30: =IF(CX30=0,"",CX30+CY30) | DE30: =IF(CZ30="","",'Name List'!$I$4) | DI30: =IF(DG30=0,"",DG30+DH30) | DN30: =IF(DI30="","",'Name List'!$I$4) | DR30: =IF(DP30=0,"",DP30+DQ30) | DW30: =IF(DR30="","",'Name List'!$I$4) | EA30: =IF(DY30=0,"",DY30+DZ30) | EF30: =IF(EA30="","",'Name List'!$I$4) | EJ30: =IF(EH30=0,"",EH30+EI30) | EO30: =IF(EJ30="","",'Name List'!$I$4) | EX30: =IF(ES30="","",'Name List'!$I$4) | FK30: =IF(FI30=0,"",FI30+FJ30) | FP30: =IF(FK30="","",'Name List'!$I$4) | FT30: =IF(FR30=0,"",FR30+FS30) | FY30: =IF(FT30="","",'Name List'!$I$4) | GC30: =IF(GA30=0,"",GA30+GB30) | GH30: =IF(GC30="","",'Name List'!$I$4) | GL30: =IF(GJ30=0,"",GJ30+GK30) | GQ30: =IF(GL30="","",'Name List'!$I$4) | HD30: =IF(HB30=0,"",HB30+HC30) | HI30: =IF(HD30="","",'Name List'!$I$4) | HM30: =IF(HK30=0,"",HK30+HL30) | HR30: =IF(HM30="","",'Name List'!$I$4) | IJ30: =IF(IE30="","",'Name List'!$I$4) | QR30: =IF(QM30="","",'Name List'!$I$4) | QT30: =SUM(F30+O30+X30+AG30+AP30+AY30+BH30+BQ30+BZ30+CI30+CR30+DA30+DJ30+DS30+EB30+EK30+ET30+FC30+FL30+FU30+GD30+GM30+GV30+HE30+HN30+HW30+IF30+IO30+IX30+JG30+JP30+JY30+KH30+KQ30+KZ30+LI30+LR30+MA30+MJ30+MS30+NB30+NK30+NT30+OC30+OL30+OU30+PD30+PM30+PV30+QE30+QN30) -> 0 | QU30: =SUM(G30+P30+Y30+AH30+AQ30+AZ30+BI30+BR30+CA30+CJ30+CS30+DB30+DK30+DT30+EC30+EL30+EU30+FD30+FM30+FV30+GE30+GN30+GW30+HF30+HO30+HX30+IG30+IP30+IY30+JH30+JQ30+JZ30+KI30+KR30+LA30+LJ30+LS30+MB30+MK30+MT30+NC30+NL30+NU30+OD30+OM30+OV30+PE30+PN30+PW30+QF30+QO30) -> 0 | QV30: =SUM(H30+Q30+Z30+AI30+AR30+BA30+BJ30+BS30+CB30+CK30+CT30+DC30+DL30+DU30+ED30+EM30+EV30+FE30+FN30+FW30+GF30+GO30+GX30+HG30+HP30+HY30+IH30+IQ30+IZ30+JI30+JR30+KA30+KJ30+KS30+LB30+LK30+LT30+MC30+ML30+MU30+ND30+NM30+NV30+OE30+ON30+OW30+PF30+PO30+PX30+QG30+QP30) -> 4 | QW30: =SUM(I30+R30+AA30+AJ30+AS30+BB30+BK30+BT30+CC30+CL30+CU30+DD30+DM30+DV30+EE30+EN30+EW30+FF30+FO30+FX30+GG30+GP30+GY30+HH30+HQ30+HZ30+II30+IR30+JA30+JJ30+JS30+KB30+KK30+KT30+LC30+LL30+LU30+MD30+MM30+MV30+NE30+NN30+NW30+OF30+OO30+OX30+PG30+PP30+PY30+QH30+QQ30) -> 13 | QY30: =SUM(J30,S30,AB30,AK30,AT30,BC30,BL30,BU30,CD30,CM30,CV30,DE30,DN30,DW30,EF30,EO30,FP30,FY30,GH30,GQ30,HI30,HR30,IS30,JB30,JK30,JT30,KC30,KL30,KU30,LD30,LM30,LV30,ME30,MN30,MW30,NF30,NO30,NX30,OG30,OP30,OY30,PH30,PZ30)/5 -> 1 | RA30: =MAX(C30,L30,AD30,AM30,AV30,BN30,BW30,CF30,CX30,DG30,DP30,DY30,EH30,FI30,FR30,GA30,GJ30,HK30,IL30,IU30,JD30,JM30,JV30,KE30,KW30,LO30,LX30,MG30,MP30,MY30,NH30,NQ30,OI30,PA30,PS30) -> 9 | RB30: =MAX(D30,M30,AE30,AN30,AW30,BO30,BX30,CG30,CY30,DH30,DQ30,DZ30,EI30,FJ30,FS30,GB30,GK30,HL30,IM30,IV30,JE30,JN30,JW30,KF30,KX30,LP30,LY30,MH30,MQ30,MZ30,NI30,NR30,OJ30,PB30,PT30) -> 0 | RC30: =MAX(E30,N30,AF30,AO30,AX30,BP30,BY30,CH30,CZ30,DI30,DR30,EA30,EJ30,FK30,FT30,GC30,GL30,HM30,IN30,IW30,JF30,JO30,JX30,KG30,KY30,LQ30,LZ30,MI30,MR30,NA30,NJ30,NS30,OK30,PC30,PU30) -> 9 | RD30: =MIN(C30,L30,AD30,AM30,AV30,BN30,BW30,CF30,CX30,DG30,DP30,DY30,EH30,FI30,FR30,GA30,GJ30,HK30,IL30,IU30,JD30,JM30,JV30,KE30,KW30,LO30,LX30,MG30,MP30,MY30,NH30,NQ30,OI30,PA30,PS30) -> 9 | RE30: =MIN(D30,M30,AE30,AN30,AW30,BO30,BX30,CG30,CY30,DH30,DQ30,DZ30,EI30,FJ30,FS30,GB30,GK30,HL30,IM30,IV30,JE30,JN30,JW30,KF30,KX30,LP30,LY30,MH30,MQ30,MZ30,NI30,NR30,OJ30,PB30,PT30) -> 0 | RF30: =MIN(E30,N30,AF30,AO30,AX30,BP30,BY30,CH30,CZ30,DI30,DR30,EA30,EJ30,FK30,FT30,GC30,GL30,HM30,IN30,IW30,JF30,JO30,JX30,KG30,KY30,LQ30,LZ30,MI30,MR30,NA30,NJ30,NS30,OK30,PC30,PU30) -> 9 | RH30: =MAX(W30,BG30,CQ30,HD30,LH30,OB30,OT30) -> 0 | RI30: =MIN(W30,BG30,CQ30,HD30,LH30,OB30,OT30) -> 0 | RK30: =IFERROR(SUM(E30,N30,W30,AF30,AO30,AX30,BG30,BP30,BY30,CH30,CQ30,CZ30,DI30,DR30,EA30,EJ30,FK30,GC30,GL30,HD30,HM30,IN30,IW30,JF30,JO30,JX30,KG30,KY30,LH30,LQ30,LZ30,MI30,MR30,NA30,NJ30,NS30,OB30,OK30,OT30,PC30,)/QY30,0) -> 9 | RM30: =MAX(ES30,IE30) -> 0 | RN30: =MIN(ES30,IE30) -> 0 | RP30: =SUM(EX30,IJ30)/5 -> 0
A31: ='Name List'!B31 -> Anthony Harris | E31: =IF(C31=0,"",C31+D31) | J31: =IF(E31="","",'Name List'!$I$4) | W31: =IF(U31=0,"",U31+V31) | AB31: =IF(W31="","",'Name List'!$I$4) | AD31: 18 | AE31: 13 | AF31: =IF(AD31=0,"",AD31+AE31) -> 31 | AG31: 0 | AH31: 1 | AI31: 5 | AJ31: 3 | AK31: =IF(AF31="","",'Name List'!$I$4) -> 5 | AM31: 17 | AN31: 16 | AO31: =IF(AM31=0,"",AM31+AN31) -> 33 | AP31: 0 | AQ31: 0 | AR31: 9 | AS31: 3 | AT31: =IF(AO31="","",'Name List'!$I$4) -> 5 | AX31: =IF(AV31=0,"",AV31+AW31) | BC31: =IF(AX31="","",'Name List'!$I$4) | BG31: =IF(BE31=0,"",BE31+BF31) | BL31: =IF(BG31="","",'Name List'!$I$4) | BY31: =IF(BW31=0,"",BW31+BX31) | CD31: =IF(BY31="","",'Name List'!$I$4) | CF31: 17 | CG31: 15 | CH31: =IF(CF31=0,"",CF31+CG31) -> 32 | CI31: 0 | CJ31: 0 | CK31: 5 | CL31: 0 | CM31: =IF(CH31="","",'Name List'!$I$4) -> 5 | CQ31: =IF(CO31=0,"",CO31+CP31) | CV31: =IF(CQ31="","",'Name List'!$I$4) | CX31: 17 | CY31: 20 | CZ31: =IF(CX31=0,"",CX31+CY31) -> 37 | DA31: 0 | DB31: 1 | DC31: 8 | DD31: 2 | DE31: =IF(CZ31="","",'Name List'!$I$4) -> 5 | DG31: 17 | DH31: 17 | DI31: =IF(DG31=0,"",DG31+DH31) -> 34 | DJ31: 0 | DK31: 2 | DL31: 5 | DM31: 2 | DN31: =IF(DI31="","",'Name List'!$I$4) -> 5 | DR31: =IF(DP31=0,"",DP31+DQ31) | DW31: =IF(DR31="","",'Name List'!$I$4) | EA31: =IF(DY31=0,"",DY31+DZ31) | EF31: =IF(EA31="","",'Name List'!$I$4) | EJ31: =IF(EH31=0,"",EH31+EI31) | EO31: =IF(EJ31="","",'Name List'!$I$4) | ES31: 95 | ET31: 0 | EU31: 0 | EV31: 5 | EX31: =IF(ES31="","",'Name List'!$I$4) -> 5 | FK31: =IF(FI31=0,"",FI31+FJ31) | FP31: =IF(FK31="","",'Name List'!$I$4) | FT31: =IF(FR31=0,"",FR31+FS31) | FY31: =IF(FT31="","",'Name List'!$I$4) | GC31: =IF(GA31=0,"",GA31+GB31) | GH31: =IF(GC31="","",'Name List'!$I$4) | GJ31: 17 | GK31: 18 | GL31: =IF(GJ31=0,"",GJ31+GK31) -> 35 | GM31: 0 | GN31: 0 | GO31: 8 | GP31: 1 | GQ31: =IF(GL31="","",'Name List'!$I$4) -> 5 | HD31: =IF(HB31=0,"",HB31+HC31) | HI31: =IF(HD31="","",'Name List'!$I$4) | HK31: 20 | HL31: 18 | HM31: =IF(HK31=0,"",HK31+HL31) -> 38 | HN31: 0 | HO31: 0 | HP31: 10 | HQ31: 0 | HR31: =IF(HM31="","",'Name List'!$I$4) -> 5 | IJ31: =IF(IE31="","",'Name List'!$I$4) | QR31: =IF(QM31="","",'Name List'!$I$4) | QT31: =SUM(F31+O31+X31+AG31+AP31+AY31+BH31+BQ31+BZ31+CI31+CR31+DA31+DJ31+DS31+EB31+EK31+ET31+FC31+FL31+FU31+GD31+GM31+GV31+HE31+HN31+HW31+IF31+IO31+IX31+JG31+JP31+JY31+KH31+KQ31+KZ31+LI31+LR31+MA31+MJ31+MS31+NB31+NK31+NT31+OC31+OL31+OU31+PD31+PM31+PV31+QE31+QN31) -> 0 | QU31: =SUM(G31+P31+Y31+AH31+AQ31+AZ31+BI31+BR31+CA31+CJ31+CS31+DB31+DK31+DT31+EC31+EL31+EU31+FD31+FM31+FV31+GE31+GN31+GW31+HF31+HO31+HX31+IG31+IP31+IY31+JH31+JQ31+JZ31+KI31+KR31+LA31+LJ31+LS31+MB31+MK31+MT31+NC31+NL31+NU31+OD31+OM31+OV31+PE31+PN31+PW31+QF31+QO31) -> 4 | QV31: =SUM(H31+Q31+Z31+AI31+AR31+BA31+BJ31+BS31+CB31+CK31+CT31+DC31+DL31+DU31+ED31+EM31+EV31+FE31+FN31+FW31+GF31+GO31+GX31+HG31+HP31+HY31+IH31+IQ31+IZ31+JI31+JR31+KA31+KJ31+KS31+LB31+LK31+LT31+MC31+ML31+MU31+ND31+NM31+NV31+OE31+ON31+OW31+PF31+PO31+PX31+QG31+QP31) -> 55 | QW31: =SUM(I31+R31+AA31+AJ31+AS31+BB31+BK31+BT31+CC31+CL31+CU31+DD31+DM31+DV31+EE31+EN31+EW31+FF31+FO31+FX31+GG31+GP31+GY31+HH31+HQ31+HZ31+II31+IR31+JA31+JJ31+JS31+KB31+KK31+KT31+LC31+LL31+LU31+MD31+MM31+MV31+NE31+NN31+NW31+OF31+OO31+OX31+PG31+PP31+PY31+QH31+QQ31) -> 11 | QY31: =SUM(J31,S31,AB31,AK31,AT31,BC31,BL31,BU31,CD31,CM31,CV31,DE31,DN31,DW31,EF31,EO31,FP31,FY31,GH31,GQ31,HI31,HR31,IS31,JB31,JK31,JT31,KC31,KL31,KU31,LD31,LM31,LV31,ME31,MN31,MW31,NF31,NO31,NX31,OG31,OP31,OY31,PH31,PZ31)/5 -> 7 | RA31: =MAX(C31,L31,AD31,AM31,AV31,BN31,BW31,CF31,CX31,DG31,DP31,DY31,EH31,FI31,FR31,GA31,GJ31,HK31,IL31,IU31,JD31,JM31,JV31,KE31,KW31,LO31,LX31,MG31,MP31,MY31,NH31,NQ31,OI31,PA31,PS31) -> 20 | RB31: =MAX(D31,M31,AE31,AN31,AW31,BO31,BX31,CG31,CY31,DH31,DQ31,DZ31,EI31,FJ31,FS31,GB31,GK31,HL31,IM31,IV31,JE31,JN31,JW31,KF31,KX31,LP31,LY31,MH31,MQ31,MZ31,NI31,NR31,OJ31,PB31,PT31) -> 20 | RC31: =MAX(E31,N31,AF31,AO31,AX31,BP31,BY31,CH31,CZ31,DI31,DR31,EA31,EJ31,FK31,FT31,GC31,GL31,HM31,IN31,IW31,JF31,JO31,JX31,KG31,KY31,LQ31,LZ31,MI31,MR31,NA31,NJ31,NS31,OK31,PC31,PU31) -> 38 | RD31: =MIN(C31,L31,AD31,AM31,AV31,BN31,BW31,CF31,CX31,DG31,DP31,DY31,EH31,FI31,FR31,GA31,GJ31,HK31,IL31,IU31,JD31,JM31,JV31,KE31,KW31,LO31,LX31,MG31,MP31,MY31,NH31,NQ31,OI31,PA31,PS31) -> 17 | RE31: =MIN(D31,M31,AE31,AN31,AW31,BO31,BX31,CG31,CY31,DH31,DQ31,DZ31,EI31,FJ31,FS31,GB31,GK31,HL31,IM31,IV31,JE31,JN31,JW31,KF31,KX31,LP31,LY31,MH31,MQ31,MZ31,NI31,NR31,OJ31,PB31,PT31) -> 13 | RF31: =MIN(E31,N31,AF31,AO31,AX31,BP31,BY31,CH31,CZ31,DI31,DR31,EA31,EJ31,FK31,FT31,GC31,GL31,HM31,IN31,IW31,JF31,JO31,JX31,KG31,KY31,LQ31,LZ31,MI31,MR31,NA31,NJ31,NS31,OK31,PC31,PU31) -> 31 | RH31: =MAX(W31,BG31,CQ31,HD31,LH31,OB31,OT31) -> 0 | RI31: =MIN(W31,BG31,CQ31,HD31,LH31,OB31,OT31) -> 0 | RK31: =IFERROR(SUM(E31,N31,W31,AF31,AO31,AX31,BG31,BP31,BY31,CH31,CQ31,CZ31,DI31,DR31,EA31,EJ31,FK31,GC31,GL31,HD31,HM31,IN31,IW31,JF31,JO31,JX31,KG31,KY31,LH31,LQ31,LZ31,MI31,MR31,NA31,NJ31,NS31,OB31,OK31,OT31,PC31,)/QY31,0) -> 34.285714 | RM31: =MAX(ES31,IE31) -> 95 | RN31: =MIN(ES31,IE31) -> 95 | RP31: =SUM(EX31,IJ31)/5 -> 1
A32: ='Name List'!B32 -> Neil Hart | E32: =IF(C32=0,"",C32+D32) | J32: =IF(E32="","",'Name List'!$I$4) | W32: =IF(U32=0,"",U32+V32) | AB32: =IF(W32="","",'Name List'!$I$4) | AF32: =IF(AD32=0,"",AD32+AE32) | AK32: =IF(AF32="","",'Name List'!$I$4) | AM32: 15 | AN32: 20 | AO32: =IF(AM32=0,"",AM32+AN32) -> 35 | AP32: 0 | AQ32: 2 | AR32: 11 | AS32: 0 | AT32: =IF(AO32="","",'Name List'!$I$4) -> 5 | AV32: 11 | AW32: 18 | AX32: =IF(AV32=0,"",AV32+AW32) -> 29 | AY32: 0 | AZ32: 3 | BA32: 7 | BB32: 3 | BC32: =IF(AX32="","",'Name List'!$I$4) -> 5 | BE32: 15 | BF32: 20 | BG32: =IF(BE32=0,"",BE32+BF32) -> 35 | BH32: 0 | BI32: 2 | BJ32: 10 | BK32: 0 | BL32: =IF(BG32="","",'Name List'!$I$4) -> 5 | BY32: =IF(BW32=0,"",BW32+BX32) | CD32: =IF(BY32="","",'Name List'!$I$4) | CH32: =IF(CF32=0,"",CF32+CG32) | CM32: =IF(CH32="","",'Name List'!$I$4) | CQ32: =IF(CO32=0,"",CO32+CP32) | CV32: =IF(CQ32="","",'Name List'!$I$4) | CZ32: =IF(CX32=0,"",CX32+CY32) | DE32: =IF(CZ32="","",'Name List'!$I$4) | DI32: =IF(DG32=0,"",DG32+DH32) | DN32: =IF(DI32="","",'Name List'!$I$4) | DP32: 15 | DQ32: 18 | DR32: =IF(DP32=0,"",DP32+DQ32) -> 33 | DS32: 0 | DT32: 2 | DU32: 9 | DV32: 0 | DW32: =IF(DR32="","",'Name List'!$I$4) -> 5 | EA32: =IF(DY32=0,"",DY32+DZ32) | EF32: =IF(EA32="","",'Name List'!$I$4) | EJ32: =IF(EH32=0,"",EH32+EI32) | EO32: =IF(EJ32="","",'Name List'!$I$4) | EX32: =IF(ES32="","",'Name List'!$I$4) | FK32: =IF(FI32=0,"",FI32+FJ32) | FP32: =IF(FK32="","",'Name List'!$I$4) | FT32: =IF(FR32=0,"",FR32+FS32) | FY32: =IF(FT32="","",'Name List'!$I$4) | GC32: =IF(GA32=0,"",GA32+GB32) | GH32: =IF(GC32="","",'Name List'!$I$4) | GJ32: 17 | GK32: 10 | GL32: =IF(GJ32=0,"",GJ32+GK32) -> 27 | GM32: 0 | GN32: 1 | GO32: 7 | GP32: 1 | GQ32: =IF(GL32="","",'Name List'!$I$4) -> 5 | HB32: 19 | HC32: 16 | HD32: =IF(HB32=0,"",HB32+HC32) -> 35 | HE32: 0 | HF32: 3 | HG32: 9 | HH32: 1 | HI32: =IF(HD32="","",'Name List'!$I$4) -> 5 | HM32: =IF(HK32=0,"",HK32+HL32) | HR32: =IF(HM32="","",'Name List'!$I$4) | IJ32: =IF(IE32="","",'Name List'!$I$4) | QR32: =IF(QM32="","",'Name List'!$I$4) | QT32: =SUM(F32+O32+X32+AG32+AP32+AY32+BH32+BQ32+BZ32+CI32+CR32+DA32+DJ32+DS32+EB32+EK32+ET32+FC32+FL32+FU32+GD32+GM32+GV32+HE32+HN32+HW32+IF32+IO32+IX32+JG32+JP32+JY32+KH32+KQ32+KZ32+LI32+LR32+MA32+MJ32+MS32+NB32+NK32+NT32+OC32+OL32+OU32+PD32+PM32+PV32+QE32+QN32) -> 0 | QU32: =SUM(G32+P32+Y32+AH32+AQ32+AZ32+BI32+BR32+CA32+CJ32+CS32+DB32+DK32+DT32+EC32+EL32+EU32+FD32+FM32+FV32+GE32+GN32+GW32+HF32+HO32+HX32+IG32+IP32+IY32+JH32+JQ32+JZ32+KI32+KR32+LA32+LJ32+LS32+MB32+MK32+MT32+NC32+NL32+NU32+OD32+OM32+OV32+PE32+PN32+PW32+QF32+QO32) -> 13 | QV32: =SUM(H32+Q32+Z32+AI32+AR32+BA32+BJ32+BS32+CB32+CK32+CT32+DC32+DL32+DU32+ED32+EM32+EV32+FE32+FN32+FW32+GF32+GO32+GX32+HG32+HP32+HY32+IH32+IQ32+IZ32+JI32+JR32+KA32+KJ32+KS32+LB32+LK32+LT32+MC32+ML32+MU32+ND32+NM32+NV32+OE32+ON32+OW32+PF32+PO32+PX32+QG32+QP32) -> 53 | QW32: =SUM(I32+R32+AA32+AJ32+AS32+BB32+BK32+BT32+CC32+CL32+CU32+DD32+DM32+DV32+EE32+EN32+EW32+FF32+FO32+FX32+GG32+GP32+GY32+HH32+HQ32+HZ32+II32+IR32+JA32+JJ32+JS32+KB32+KK32+KT32+LC32+LL32+LU32+MD32+MM32+MV32+NE32+NN32+NW32+OF32+OO32+OX32+PG32+PP32+PY32+QH32+QQ32) -> 5 | QY32: =SUM(J32,S32,AB32,AK32,AT32,BC32,BL32,BU32,CD32,CM32,CV32,DE32,DN32,DW32,EF32,EO32,FP32,FY32,GH32,GQ32,HI32,HR32,IS32,JB32,JK32,JT32,KC32,KL32,KU32,LD32,LM32,LV32,ME32,MN32,MW32,NF32,NO32,NX32,OG32,OP32,OY32,PH32,PZ32)/5 -> 6 | RA32: =MAX(C32,L32,AD32,AM32,AV32,BN32,BW32,CF32,CX32,DG32,DP32,DY32,EH32,FI32,FR32,GA32,GJ32,HK32,IL32,IU32,JD32,JM32,JV32,KE32,KW32,LO32,LX32,MG32,MP32,MY32,NH32,NQ32,OI32,PA32,PS32) -> 17 | RB32: =MAX(D32,M32,AE32,AN32,AW32,BO32,BX32,CG32,CY32,DH32,DQ32,DZ32,EI32,FJ32,FS32,GB32,GK32,HL32,IM32,IV32,JE32,JN32,JW32,KF32,KX32,LP32,LY32,MH32,MQ32,MZ32,NI32,NR32,OJ32,PB32,PT32) -> 20 | RC32: =MAX(E32,N32,AF32,AO32,AX32,BP32,BY32,CH32,CZ32,DI32,DR32,EA32,EJ32,FK32,FT32,GC32,GL32,HM32,IN32,IW32,JF32,JO32,JX32,KG32,KY32,LQ32,LZ32,MI32,MR32,NA32,NJ32,NS32,OK32,PC32,PU32) -> 35 | RD32: =MIN(C32,L32,AD32,AM32,AV32,BN32,BW32,CF32,CX32,DG32,DP32,DY32,EH32,FI32,FR32,GA32,GJ32,HK32,IL32,IU32,JD32,JM32,JV32,KE32,KW32,LO32,LX32,MG32,MP32,MY32,NH32,NQ32,OI32,PA32,PS32) -> 11 | RE32: =MIN(D32,M32,AE32,AN32,AW32,BO32,BX32,CG32,CY32,DH32,DQ32,DZ32,EI32,FJ32,FS32,GB32,GK32,HL32,IM32,IV32,JE32,JN32,JW32,KF32,KX32,LP32,LY32,MH32,MQ32,MZ32,NI32,NR32,OJ32,PB32,PT32) -> 10 | RF32: =MIN(E32,N32,AF32,AO32,AX32,BP32,BY32,CH32,CZ32,DI32,DR32,EA32,EJ32,FK32,FT32,GC32,GL32,HM32,IN32,IW32,JF32,JO32,JX32,KG32,KY32,LQ32,LZ32,MI32,MR32,NA32,NJ32,NS32,OK32,PC32,PU32) -> 27 | RH32: =MAX(W32,BG32,CQ32,HD32,LH32,OB32,OT32) -> 35 | RI32: =MIN(W32,BG32,CQ32,HD32,LH32,OB32,OT32) -> 35 | RK32: =IFERROR(SUM(E32,N32,W32,AF32,AO32,AX32,BG32,BP32,BY32,CH32,CQ32,CZ32,DI32,DR32,EA32,EJ32,FK32,GC32,GL32,HD32,HM32,IN32,IW32,JF32,JO32,JX32,KG32,KY32,LH32,LQ32,LZ32,MI32,MR32,NA32,NJ32,NS32,OB32,OK32,OT32,PC32,)/QY32,0) -> 32.333333 | RM32: =MAX(ES32,IE32) -> 0 | RN32: =MIN(ES32,IE32) -> 0 | RP32: =SUM(EX32,IJ32)/5 -> 0
A33: ='Name List'!B33 -> Tony Hearson | E33: =IF(C33=0,"",C33+D33) | J33: =IF(E33="","",'Name List'!$I$4) | W33: =IF(U33=0,"",U33+V33) | AB33: =IF(W33="","",'Name List'!$I$4) | AF33: =IF(AD33=0,"",AD33+AE33) | AK33: =IF(AF33="","",'Name List'!$I$4) | AO33: =IF(AM33=0,"",AM33+AN33) | AT33: =IF(AO33="","",'Name List'!$I$4) | AX33: =IF(AV33=0,"",AV33+AW33) | BC33: =IF(AX33="","",'Name List'!$I$4) | BG33: =IF(BE33=0,"",BE33+BF33) | BL33: =IF(BG33="","",'Name List'!$I$4) | BY33: =IF(BW33=0,"",BW33+BX33) | CD33: =IF(BY33="","",'Name List'!$I$4) | CH33: =IF(CF33=0,"",CF33+CG33) | CM33: =IF(CH33="","",'Name List'!$I$4) | CQ33: =IF(CO33=0,"",CO33+CP33) | CV33: =IF(CQ33="","",'Name List'!$I$4) | CZ33: =IF(CX33=0,"",CX33+CY33) | DE33: =IF(CZ33="","",'Name List'!$I$4) | DI33: =IF(DG33=0,"",DG33+DH33) | DN33: =IF(DI33="","",'Name List'!$I$4) | DR33: =IF(DP33=0,"",DP33+DQ33) | DW33: =IF(DR33="","",'Name List'!$I$4) | EA33: =IF(DY33=0,"",DY33+DZ33) | EF33: =IF(EA33="","",'Name List'!$I$4) | EJ33: =IF(EH33=0,"",EH33+EI33) | EO33: =IF(EJ33="","",'Name List'!$I$4) | EX33: =IF(ES33="","",'Name List'!$I$4) | FK33: =IF(FI33=0,"",FI33+FJ33) | FP33: =IF(FK33="","",'Name List'!$I$4) | FT33: =IF(FR33=0,"",FR33+FS33) | FY33: =IF(FT33="","",'Name List'!$I$4) | GC33: =IF(GA33=0,"",GA33+GB33) | GH33: =IF(GC33="","",'Name List'!$I$4) | GL33: =IF(GJ33=0,"",GJ33+GK33) | GQ33: =IF(GL33="","",'Name List'!$I$4) | HD33: =IF(HB33=0,"",HB33+HC33) | HI33: =IF(HD33="","",'Name List'!$I$4) | HM33: =IF(HK33=0,"",HK33+HL33) | HR33: =IF(HM33="","",'Name List'!$I$4) | IJ33: =IF(IE33="","",'Name List'!$I$4) | QR33: =IF(QM33="","",'Name List'!$I$4) | QT33: =SUM(F33+O33+X33+AG33+AP33+AY33+BH33+BQ33+BZ33+CI33+CR33+DA33+DJ33+DS33+EB33+EK33+ET33+FC33+FL33+FU33+GD33+GM33+GV33+HE33+HN33+HW33+IF33+IO33+IX33+JG33+JP33+JY33+KH33+KQ33+KZ33+LI33+LR33+MA33+MJ33+MS33+NB33+NK33+NT33+OC33+OL33+OU33+PD33+PM33+PV33+QE33+QN33) -> 0 | QU33: =SUM(G33+P33+Y33+AH33+AQ33+AZ33+BI33+BR33+CA33+CJ33+CS33+DB33+DK33+DT33+EC33+EL33+EU33+FD33+FM33+FV33+GE33+GN33+GW33+HF33+HO33+HX33+IG33+IP33+IY33+JH33+JQ33+JZ33+KI33+KR33+LA33+LJ33+LS33+MB33+MK33+MT33+NC33+NL33+NU33+OD33+OM33+OV33+PE33+PN33+PW33+QF33+QO33) -> 0 | QV33: =SUM(H33+Q33+Z33+AI33+AR33+BA33+BJ33+BS33+CB33+CK33+CT33+DC33+DL33+DU33+ED33+EM33+EV33+FE33+FN33+FW33+GF33+GO33+GX33+HG33+HP33+HY33+IH33+IQ33+IZ33+JI33+JR33+KA33+KJ33+KS33+LB33+LK33+LT33+MC33+ML33+MU33+ND33+NM33+NV33+OE33+ON33+OW33+PF33+PO33+PX33+QG33+QP33) -> 0 | QW33: =SUM(I33+R33+AA33+AJ33+AS33+BB33+BK33+BT33+CC33+CL33+CU33+DD33+DM33+DV33+EE33+EN33+EW33+FF33+FO33+FX33+GG33+GP33+GY33+HH33+HQ33+HZ33+II33+IR33+JA33+JJ33+JS33+KB33+KK33+KT33+LC33+LL33+LU33+MD33+MM33+MV33+NE33+NN33+NW33+OF33+OO33+OX33+PG33+PP33+PY33+QH33+QQ33) -> 0 | QY33: =SUM(J33,S33,AB33,AK33,AT33,BC33,BL33,BU33,CD33,CM33,CV33,DE33,DN33,DW33,EF33,EO33,FP33,FY33,GH33,GQ33,HI33,HR33,IS33,JB33,JK33,JT33,KC33,KL33,KU33,LD33,LM33,LV33,ME33,MN33,MW33,NF33,NO33,NX33,OG33,OP33,OY33,PH33,PZ33)/5 -> 0 | RA33: =MAX(C33,L33,AD33,AM33,AV33,BN33,BW33,CF33,CX33,DG33,DP33,DY33,EH33,FI33,FR33,GA33,GJ33,HK33,IL33,IU33,JD33,JM33,JV33,KE33,KW33,LO33,LX33,MG33,MP33,MY33,NH33,NQ33,OI33,PA33,PS33) -> 0 | RB33: =MAX(D33,M33,AE33,AN33,AW33,BO33,BX33,CG33,CY33,DH33,DQ33,DZ33,EI33,FJ33,FS33,GB33,GK33,HL33,IM33,IV33,JE33,JN33,JW33,KF33,KX33,LP33,LY33,MH33,MQ33,MZ33,NI33,NR33,OJ33,PB33,PT33) -> 0 | RC33: =MAX(E33,N33,AF33,AO33,AX33,BP33,BY33,CH33,CZ33,DI33,DR33,EA33,EJ33,FK33,FT33,GC33,GL33,HM33,IN33,IW33,JF33,JO33,JX33,KG33,KY33,LQ33,LZ33,MI33,MR33,NA33,NJ33,NS33,OK33,PC33,PU33) -> 0 | RD33: =MIN(C33,L33,AD33,AM33,AV33,BN33,BW33,CF33,CX33,DG33,DP33,DY33,EH33,FI33,FR33,GA33,GJ33,HK33,IL33,IU33,JD33,JM33,JV33,KE33,KW33,LO33,LX33,MG33,MP33,MY33,NH33,NQ33,OI33,PA33,PS33) -> 0 | RE33: =MIN(D33,M33,AE33,AN33,AW33,BO33,BX33,CG33,CY33,DH33,DQ33,DZ33,EI33,FJ33,FS33,GB33,GK33,HL33,IM33,IV33,JE33,JN33,JW33,KF33,KX33,LP33,LY33,MH33,MQ33,MZ33,NI33,NR33,OJ33,PB33,PT33) -> 0 | RF33: =MIN(E33,N33,AF33,AO33,AX33,BP33,BY33,CH33,CZ33,DI33,DR33,EA33,EJ33,FK33,FT33,GC33,GL33,HM33,IN33,IW33,JF33,JO33,JX33,KG33,KY33,LQ33,LZ33,MI33,MR33,NA33,NJ33,NS33,OK33,PC33,PU33) -> 0 | RH33: =MAX(W33,BG33,CQ33,HD33,LH33,OB33,OT33) -> 0 | RI33: =MIN(W33,BG33,CQ33,HD33,LH33,OB33,OT33) -> 0 | RK33: =IFERROR(SUM(E33,N33,W33,AF33,AO33,AX33,BG33,BP33,BY33,CH33,CQ33,CZ33,DI33,DR33,EA33,EJ33,FK33,GC33,GL33,HD33,HM33,IN33,IW33,JF33,JO33,JX33,KG33,KY33,LH33,LQ33,LZ33,MI33,MR33,NA33,NJ33,NS33,OB33,OK33,OT33,PC33,)/QY33,0) -> 0 | RM33: =MAX(ES33,IE33) -> 0 | RN33: =MIN(ES33,IE33) -> 0 | RP33: =SUM(EX33,IJ33)/5 -> 0
A34: ='Name List'!B34 -> David Hilton | E34: =IF(C34=0,"",C34+D34) | J34: =IF(E34="","",'Name List'!$I$4) | W34: =IF(U34=0,"",U34+V34) | AB34: =IF(W34="","",'Name List'!$I$4) | AF34: =IF(AD34=0,"",AD34+AE34) | AK34: =IF(AF34="","",'Name List'!$I$4) | AO34: =IF(AM34=0,"",AM34+AN34) | AT34: =IF(AO34="","",'Name List'!$I$4) | AX34: =IF(AV34=0,"",AV34+AW34) | BC34: =IF(AX34="","",'Name List'!$I$4) | BG34: =IF(BE34=0,"",BE34+BF34) | BL34: =IF(BG34="","",'Name List'!$I$4) | BY34: =IF(BW34=0,"",BW34+BX34) | CD34: =IF(BY34="","",'Name List'!$I$4) | CH34: =IF(CF34=0,"",CF34+CG34) | CM34: =IF(CH34="","",'Name List'!$I$4) | CQ34: =IF(CO34=0,"",CO34+CP34) | CV34: =IF(CQ34="","",'Name List'!$I$4) | CZ34: =IF(CX34=0,"",CX34+CY34) | DE34: =IF(CZ34="","",'Name List'!$I$4) | DI34: =IF(DG34=0,"",DG34+DH34) | DN34: =IF(DI34="","",'Name List'!$I$4) | DR34: =IF(DP34=0,"",DP34+DQ34) | DW34: =IF(DR34="","",'Name List'!$I$4) | EA34: =IF(DY34=0,"",DY34+DZ34) | EF34: =IF(EA34="","",'Name List'!$I$4) | EJ34: =IF(EH34=0,"",EH34+EI34) | EO34: =IF(EJ34="","",'Name List'!$I$4) | EX34: =IF(ES34="","",'Name List'!$I$4) | FK34: =IF(FI34=0,"",FI34+FJ34) | FP34: =IF(FK34="","",'Name List'!$I$4) | FT34: =IF(FR34=0,"",FR34+FS34) | FY34: =IF(FT34="","",'Name List'!$I$4) | GC34: =IF(GA34=0,"",GA34+GB34) | GH34: =IF(GC34="","",'Name List'!$I$4) | GJ34: 14 | GK34: 13 | GL34: =IF(GJ34=0,"",GJ34+GK34) -> 27 | GM34: 0 | GN34: 1 | GO34: 7 | GP34: 2 | GQ34: =IF(GL34="","",'Name List'!$I$4) -> 5 | HD34: =IF(HB34=0,"",HB34+HC34) | HI34: =IF(HD34="","",'Name List'!$I$4) | HM34: =IF(HK34=0,"",HK34+HL34) | HR34: =IF(HM34="","",'Name List'!$I$4) | IJ34: =IF(IE34="","",'Name List'!$I$4) | QR34: =IF(QM34="","",'Name List'!$I$4) | QT34: =SUM(F34+O34+X34+AG34+AP34+AY34+BH34+BQ34+BZ34+CI34+CR34+DA34+DJ34+DS34+EB34+EK34+ET34+FC34+FL34+FU34+GD34+GM34+GV34+HE34+HN34+HW34+IF34+IO34+IX34+JG34+JP34+JY34+KH34+KQ34+KZ34+LI34+LR34+MA34+MJ34+MS34+NB34+NK34+NT34+OC34+OL34+OU34+PD34+PM34+PV34+QE34+QN34) -> 0 | QU34: =SUM(G34+P34+Y34+AH34+AQ34+AZ34+BI34+BR34+CA34+CJ34+CS34+DB34+DK34+DT34+EC34+EL34+EU34+FD34+FM34+FV34+GE34+GN34+GW34+HF34+HO34+HX34+IG34+IP34+IY34+JH34+JQ34+JZ34+KI34+KR34+LA34+LJ34+LS34+MB34+MK34+MT34+NC34+NL34+NU34+OD34+OM34+OV34+PE34+PN34+PW34+QF34+QO34) -> 1 | QV34: =SUM(H34+Q34+Z34+AI34+AR34+BA34+BJ34+BS34+CB34+CK34+CT34+DC34+DL34+DU34+ED34+EM34+EV34+FE34+FN34+FW34+GF34+GO34+GX34+HG34+HP34+HY34+IH34+IQ34+IZ34+JI34+JR34+KA34+KJ34+KS34+LB34+LK34+LT34+MC34+ML34+MU34+ND34+NM34+NV34+OE34+ON34+OW34+PF34+PO34+PX34+QG34+QP34) -> 7 | QW34: =SUM(I34+R34+AA34+AJ34+AS34+BB34+BK34+BT34+CC34+CL34+CU34+DD34+DM34+DV34+EE34+EN34+EW34+FF34+FO34+FX34+GG34+GP34+GY34+HH34+HQ34+HZ34+II34+IR34+JA34+JJ34+JS34+KB34+KK34+KT34+LC34+LL34+LU34+MD34+MM34+MV34+NE34+NN34+NW34+OF34+OO34+OX34+PG34+PP34+PY34+QH34+QQ34) -> 2 | QY34: =SUM(J34,S34,AB34,AK34,AT34,BC34,BL34,BU34,CD34,CM34,CV34,DE34,DN34,DW34,EF34,EO34,FP34,FY34,GH34,GQ34,HI34,HR34,IS34,JB34,JK34,JT34,KC34,KL34,KU34,LD34,LM34,LV34,ME34,MN34,MW34,NF34,NO34,NX34,OG34,OP34,OY34,PH34,PZ34)/5 -> 1 | RA34: =MAX(C34,L34,AD34,AM34,AV34,BN34,BW34,CF34,CX34,DG34,DP34,DY34,EH34,FI34,FR34,GA34,GJ34,HK34,IL34,IU34,JD34,JM34,JV34,KE34,KW34,LO34,LX34,MG34,MP34,MY34,NH34,NQ34,OI34,PA34,PS34) -> 14 | RB34: =MAX(D34,M34,AE34,AN34,AW34,BO34,BX34,CG34,CY34,DH34,DQ34,DZ34,EI34,FJ34,FS34,GB34,GK34,HL34,IM34,IV34,JE34,JN34,JW34,KF34,KX34,LP34,LY34,MH34,MQ34,MZ34,NI34,NR34,OJ34,PB34,PT34) -> 13 | RC34: =MAX(E34,N34,AF34,AO34,AX34,BP34,BY34,CH34,CZ34,DI34,DR34,EA34,EJ34,FK34,FT34,GC34,GL34,HM34,IN34,IW34,JF34,JO34,JX34,KG34,KY34,LQ34,LZ34,MI34,MR34,NA34,NJ34,NS34,OK34,PC34,PU34) -> 27 | RD34: =MIN(C34,L34,AD34,AM34,AV34,BN34,BW34,CF34,CX34,DG34,DP34,DY34,EH34,FI34,FR34,GA34,GJ34,HK34,IL34,IU34,JD34,JM34,JV34,KE34,KW34,LO34,LX34,MG34,MP34,MY34,NH34,NQ34,OI34,PA34,PS34) -> 14 | RE34: =MIN(D34,M34,AE34,AN34,AW34,BO34,BX34,CG34,CY34,DH34,DQ34,DZ34,EI34,FJ34,FS34,GB34,GK34,HL34,IM34,IV34,JE34,JN34,JW34,KF34,KX34,LP34,LY34,MH34,MQ34,MZ34,NI34,NR34,OJ34,PB34,PT34) -> 13 | RF34: =MIN(E34,N34,AF34,AO34,AX34,BP34,BY34,CH34,CZ34,DI34,DR34,EA34,EJ34,FK34,FT34,GC34,GL34,HM34,IN34,IW34,JF34,JO34,JX34,KG34,KY34,LQ34,LZ34,MI34,MR34,NA34,NJ34,NS34,OK34,PC34,PU34) -> 27 | RH34: =MAX(W34,BG34,CQ34,HD34,LH34,OB34,OT34) -> 0 | RI34: =MIN(W34,BG34,CQ34,HD34,LH34,OB34,OT34) -> 0 | RK34: =IFERROR(SUM(E34,N34,W34,AF34,AO34,AX34,BG34,BP34,BY34,CH34,CQ34,CZ34,DI34,DR34,EA34,EJ34,FK34,GC34,GL34,HD34,HM34,IN34,IW34,JF34,JO34,JX34,KG34,KY34,LH34,LQ34,LZ34,MI34,MR34,NA34,NJ34,NS34,OB34,OK34,OT34,PC34,)/QY34,0) -> 27 | RM34: =MAX(ES34,IE34) -> 0 | RN34: =MIN(ES34,IE34) -> 0 | RP34: =SUM(EX34,IJ34)/5 -> 0
A35: ='Name List'!B35 -> Eoghan Hilton | E35: =IF(C35=0,"",C35+D35) | J35: =IF(E35="","",'Name List'!$I$4) | W35: =IF(U35=0,"",U35+V35) | AB35: =IF(W35="","",'Name List'!$I$4) | AF35: =IF(AD35=0,"",AD35+AE35) | AK35: =IF(AF35="","",'Name List'!$I$4) | AM35: 11 | AN35: 14 | AO35: =IF(AM35=0,"",AM35+AN35) -> 25 | AP35: 0 | AQ35: 2 | AR35: 2 | AS35: 3 | AT35: =IF(AO35="","",'Name List'!$I$4) -> 5 | AX35: =IF(AV35=0,"",AV35+AW35) | BC35: =IF(AX35="","",'Name List'!$I$4) | BG35: =IF(BE35=0,"",BE35+BF35) | BL35: =IF(BG35="","",'Name List'!$I$4) | BY35: =IF(BW35=0,"",BW35+BX35) | CD35: =IF(BY35="","",'Name List'!$I$4) | CH35: =IF(CF35=0,"",CF35+CG35) | CM35: =IF(CH35="","",'Name List'!$I$4) | CQ35: =IF(CO35=0,"",CO35+CP35) | CV35: =IF(CQ35="","",'Name List'!$I$4) | CZ35: =IF(CX35=0,"",CX35+CY35) | DE35: =IF(CZ35="","",'Name List'!$I$4) | DI35: =IF(DG35=0,"",DG35+DH35) | DN35: =IF(DI35="","",'Name List'!$I$4) | DR35: =IF(DP35=0,"",DP35+DQ35) | DW35: =IF(DR35="","",'Name List'!$I$4) | EA35: =IF(DY35=0,"",DY35+DZ35) | EF35: =IF(EA35="","",'Name List'!$I$4) | EJ35: =IF(EH35=0,"",EH35+EI35) | EO35: =IF(EJ35="","",'Name List'!$I$4) | EX35: =IF(ES35="","",'Name List'!$I$4) | FK35: =IF(FI35=0,"",FI35+FJ35) | FP35: =IF(FK35="","",'Name List'!$I$4) | FT35: =IF(FR35=0,"",FR35+FS35) | FY35: =IF(FT35="","",'Name List'!$I$4) | GC35: =IF(GA35=0,"",GA35+GB35) | GH35: =IF(GC35="","",'Name List'!$I$4) | GJ35: 21 | GK35: 17 | GL35: =IF(GJ35=0,"",GJ35+GK35) -> 38 | GM35: 0 | GN35: 2 | GO35: 10 | GP35: 1 | GQ35: =IF(GL35="","",'Name List'!$I$4) -> 5 | HD35: =IF(HB35=0,"",HB35+HC35) | HI35: =IF(HD35="","",'Name List'!$I$4) | HM35: =IF(HK35=0,"",HK35+HL35) | HR35: =IF(HM35="","",'Name List'!$I$4) | IJ35: =IF(IE35="","",'Name List'!$I$4) | QR35: =IF(QM35="","",'Name List'!$I$4) | QT35: =SUM(F35+O35+X35+AG35+AP35+AY35+BH35+BQ35+BZ35+CI35+CR35+DA35+DJ35+DS35+EB35+EK35+ET35+FC35+FL35+FU35+GD35+GM35+GV35+HE35+HN35+HW35+IF35+IO35+IX35+JG35+JP35+JY35+KH35+KQ35+KZ35+LI35+LR35+MA35+MJ35+MS35+NB35+NK35+NT35+OC35+OL35+OU35+PD35+PM35+PV35+QE35+QN35) -> 0 | QU35: =SUM(G35+P35+Y35+AH35+AQ35+AZ35+BI35+BR35+CA35+CJ35+CS35+DB35+DK35+DT35+EC35+EL35+EU35+FD35+FM35+FV35+GE35+GN35+GW35+HF35+HO35+HX35+IG35+IP35+IY35+JH35+JQ35+JZ35+KI35+KR35+LA35+LJ35+LS35+MB35+MK35+MT35+NC35+NL35+NU35+OD35+OM35+OV35+PE35+PN35+PW35+QF35+QO35) -> 4 | QV35: =SUM(H35+Q35+Z35+AI35+AR35+BA35+BJ35+BS35+CB35+CK35+CT35+DC35+DL35+DU35+ED35+EM35+EV35+FE35+FN35+FW35+GF35+GO35+GX35+HG35+HP35+HY35+IH35+IQ35+IZ35+JI35+JR35+KA35+KJ35+KS35+LB35+LK35+LT35+MC35+ML35+MU35+ND35+NM35+NV35+OE35+ON35+OW35+PF35+PO35+PX35+QG35+QP35) -> 12 | QW35: =SUM(I35+R35+AA35+AJ35+AS35+BB35+BK35+BT35+CC35+CL35+CU35+DD35+DM35+DV35+EE35+EN35+EW35+FF35+FO35+FX35+GG35+GP35+GY35+HH35+HQ35+HZ35+II35+IR35+JA35+JJ35+JS35+KB35+KK35+KT35+LC35+LL35+LU35+MD35+MM35+MV35+NE35+NN35+NW35+OF35+OO35+OX35+PG35+PP35+PY35+QH35+QQ35) -> 4 | QY35: =SUM(J35,S35,AB35,AK35,AT35,BC35,BL35,BU35,CD35,CM35,CV35,DE35,DN35,DW35,EF35,EO35,FP35,FY35,GH35,GQ35,HI35,HR35,IS35,JB35,JK35,JT35,KC35,KL35,KU35,LD35,LM35,LV35,ME35,MN35,MW35,NF35,NO35,NX35,OG35,OP35,OY35,PH35,PZ35)/5 -> 2 | RA35: =MAX(C35,L35,AD35,AM35,AV35,BN35,BW35,CF35,CX35,DG35,DP35,DY35,EH35,FI35,FR35,GA35,GJ35,HK35,IL35,IU35,JD35,JM35,JV35,KE35,KW35,LO35,LX35,MG35,MP35,MY35,NH35,NQ35,OI35,PA35,PS35) -> 21 | RB35: =MAX(D35,M35,AE35,AN35,AW35,BO35,BX35,CG35,CY35,DH35,DQ35,DZ35,EI35,FJ35,FS35,GB35,GK35,HL35,IM35,IV35,JE35,JN35,JW35,KF35,KX35,LP35,LY35,MH35,MQ35,MZ35,NI35,NR35,OJ35,PB35,PT35) -> 17 | RC35: =MAX(E35,N35,AF35,AO35,AX35,BP35,BY35,CH35,CZ35,DI35,DR35,EA35,EJ35,FK35,FT35,GC35,GL35,HM35,IN35,IW35,JF35,JO35,JX35,KG35,KY35,LQ35,LZ35,MI35,MR35,NA35,NJ35,NS35,OK35,PC35,PU35) -> 38 | RD35: =MIN(C35,L35,AD35,AM35,AV35,BN35,BW35,CF35,CX35,DG35,DP35,DY35,EH35,FI35,FR35,GA35,GJ35,HK35,IL35,IU35,JD35,JM35,JV35,KE35,KW35,LO35,LX35,MG35,MP35,MY35,NH35,NQ35,OI35,PA35,PS35) -> 11 | RE35: =MIN(D35,M35,AE35,AN35,AW35,BO35,BX35,CG35,CY35,DH35,DQ35,DZ35,EI35,FJ35,FS35,GB35,GK35,HL35,IM35,IV35,JE35,JN35,JW35,KF35,KX35,LP35,LY35,MH35,MQ35,MZ35,NI35,NR35,OJ35,PB35,PT35) -> 14 | RF35: =MIN(E35,N35,AF35,AO35,AX35,BP35,BY35,CH35,CZ35,DI35,DR35,EA35,EJ35,FK35,FT35,GC35,GL35,HM35,IN35,IW35,JF35,JO35,JX35,KG35,KY35,LQ35,LZ35,MI35,MR35,NA35,NJ35,NS35,OK35,PC35,PU35) -> 25 | RH35: =MAX(W35,BG35,CQ35,HD35,LH35,OB35,OT35) -> 0 | RI35: =MIN(W35,BG35,CQ35,HD35,LH35,OB35,OT35) -> 0 | RK35: =IFERROR(SUM(E35,N35,W35,AF35,AO35,AX35,BG35,BP35,BY35,CH35,CQ35,CZ35,DI35,DR35,EA35,EJ35,FK35,GC35,GL35,HD35,HM35,IN35,IW35,JF35,JO35,JX35,KG35,KY35,LH35,LQ35,LZ35,MI35,MR35,NA35,NJ35,NS35,OB35,OK35,OT35,PC35,)/QY35,0) -> 31.5 | RM35: =MAX(ES35,IE35) -> 0 | RN35: =MIN(ES35,IE35) -> 0 | RP35: =SUM(EX35,IJ35)/5 -> 0
A36: ='Name List'!B36 -> Martin Holder | E36: =IF(C36=0,"",C36+D36) | J36: =IF(E36="","",'Name List'!$I$4) | W36: =IF(U36=0,"",U36+V36) | AB36: =IF(W36="","",'Name List'!$I$4) | AF36: =IF(AD36=0,"",AD36+AE36) | AK36: =IF(AF36="","",'Name List'!$I$4) | AO36: =IF(AM36=0,"",AM36+AN36) | AT36: =IF(AO36="","",'Name List'!$I$4) | AX36: =IF(AV36=0,"",AV36+AW36) | BC36: =IF(AX36="","",'Name List'!$I$4) | BG36: =IF(BE36=0,"",BE36+BF36) | BL36: =IF(BG36="","",'Name List'!$I$4) | BY36: =IF(BW36=0,"",BW36+BX36) | CD36: =IF(BY36="","",'Name List'!$I$4) | CH36: =IF(CF36=0,"",CF36+CG36) | CM36: =IF(CH36="","",'Name List'!$I$4) | CQ36: =IF(CO36=0,"",CO36+CP36) | CV36: =IF(CQ36="","",'Name List'!$I$4) | CZ36: =IF(CX36=0,"",CX36+CY36) | DE36: =IF(CZ36="","",'Name List'!$I$4) | DI36: =IF(DG36=0,"",DG36+DH36) | DN36: =IF(DI36="","",'Name List'!$I$4) | DR36: =IF(DP36=0,"",DP36+DQ36) | DW36: =IF(DR36="","",'Name List'!$I$4) | EA36: =IF(DY36=0,"",DY36+DZ36) | EF36: =IF(EA36="","",'Name List'!$I$4) | EJ36: =IF(EH36=0,"",EH36+EI36) | EO36: =IF(EJ36="","",'Name List'!$I$4) | EX36: =IF(ES36="","",'Name List'!$I$4) | FK36: =IF(FI36=0,"",FI36+FJ36) | FP36: =IF(FK36="","",'Name List'!$I$4) | FT36: =IF(FR36=0,"",FR36+FS36) | FY36: =IF(FT36="","",'Name List'!$I$4) | GC36: =IF(GA36=0,"",GA36+GB36) | GH36: =IF(GC36="","",'Name List'!$I$4) | GL36: =IF(GJ36=0,"",GJ36+GK36) | GQ36: =IF(GL36="","",'Name List'!$I$4) | HD36: =IF(HB36=0,"",HB36+HC36) | HI36: =IF(HD36="","",'Name List'!$I$4) | HM36: =IF(HK36=0,"",HK36+HL36) | HR36: =IF(HM36="","",'Name List'!$I$4) | IJ36: =IF(IE36="","",'Name List'!$I$4) | QR36: =IF(QM36="","",'Name List'!$I$4) | QT36: =SUM(F36+O36+X36+AG36+AP36+AY36+BH36+BQ36+BZ36+CI36+CR36+DA36+DJ36+DS36+EB36+EK36+ET36+FC36+FL36+FU36+GD36+GM36+GV36+HE36+HN36+HW36+IF36+IO36+IX36+JG36+JP36+JY36+KH36+KQ36+KZ36+LI36+LR36+MA36+MJ36+MS36+NB36+NK36+NT36+OC36+OL36+OU36+PD36+PM36+PV36+QE36+QN36) -> 0 | QU36: =SUM(G36+P36+Y36+AH36+AQ36+AZ36+BI36+BR36+CA36+CJ36+CS36+DB36+DK36+DT36+EC36+EL36+EU36+FD36+FM36+FV36+GE36+GN36+GW36+HF36+HO36+HX36+IG36+IP36+IY36+JH36+JQ36+JZ36+KI36+KR36+LA36+LJ36+LS36+MB36+MK36+MT36+NC36+NL36+NU36+OD36+OM36+OV36+PE36+PN36+PW36+QF36+QO36) -> 0 | QV36: =SUM(H36+Q36+Z36+AI36+AR36+BA36+BJ36+BS36+CB36+CK36+CT36+DC36+DL36+DU36+ED36+EM36+EV36+FE36+FN36+FW36+GF36+GO36+GX36+HG36+HP36+HY36+IH36+IQ36+IZ36+JI36+JR36+KA36+KJ36+KS36+LB36+LK36+LT36+MC36+ML36+MU36+ND36+NM36+NV36+OE36+ON36+OW36+PF36+PO36+PX36+QG36+QP36) -> 0 | QW36: =SUM(I36+R36+AA36+AJ36+AS36+BB36+BK36+BT36+CC36+CL36+CU36+DD36+DM36+DV36+EE36+EN36+EW36+FF36+FO36+FX36+GG36+GP36+GY36+HH36+HQ36+HZ36+II36+IR36+JA36+JJ36+JS36+KB36+KK36+KT36+LC36+LL36+LU36+MD36+MM36+MV36+NE36+NN36+NW36+OF36+OO36+OX36+PG36+PP36+PY36+QH36+QQ36) -> 0 | QY36: =SUM(J36,S36,AB36,AK36,AT36,BC36,BL36,BU36,CD36,CM36,CV36,DE36,DN36,DW36,EF36,EO36,FP36,FY36,GH36,GQ36,HI36,HR36,IS36,JB36,JK36,JT36,KC36,KL36,KU36,LD36,LM36,LV36,ME36,MN36,MW36,NF36,NO36,NX36,OG36,OP36,OY36,PH36,PZ36)/5 -> 0 | RA36: =MAX(C36,L36,AD36,AM36,AV36,BN36,BW36,CF36,CX36,DG36,DP36,DY36,EH36,FI36,FR36,GA36,GJ36,HK36,IL36,IU36,JD36,JM36,JV36,KE36,KW36,LO36,LX36,MG36,MP36,MY36,NH36,NQ36,OI36,PA36,PS36) -> 0 | RB36: =MAX(D36,M36,AE36,AN36,AW36,BO36,BX36,CG36,CY36,DH36,DQ36,DZ36,EI36,FJ36,FS36,GB36,GK36,HL36,IM36,IV36,JE36,JN36,JW36,KF36,KX36,LP36,LY36,MH36,MQ36,MZ36,NI36,NR36,OJ36,PB36,PT36) -> 0 | RC36: =MAX(E36,N36,AF36,AO36,AX36,BP36,BY36,CH36,CZ36,DI36,DR36,EA36,EJ36,FK36,FT36,GC36,GL36,HM36,IN36,IW36,JF36,JO36,JX36,KG36,KY36,LQ36,LZ36,MI36,MR36,NA36,NJ36,NS36,OK36,PC36,PU36) -> 0 | RD36: =MIN(C36,L36,AD36,AM36,AV36,BN36,BW36,CF36,CX36,DG36,DP36,DY36,EH36,FI36,FR36,GA36,GJ36,HK36,IL36,IU36,JD36,JM36,JV36,KE36,KW36,LO36,LX36,MG36,MP36,MY36,NH36,NQ36,OI36,PA36,PS36) -> 0 | RE36: =MIN(D36,M36,AE36,AN36,AW36,BO36,BX36,CG36,CY36,DH36,DQ36,DZ36,EI36,FJ36,FS36,GB36,GK36,HL36,IM36,IV36,JE36,JN36,JW36,KF36,KX36,LP36,LY36,MH36,MQ36,MZ36,NI36,NR36,OJ36,PB36,PT36) -> 0 | RF36: =MIN(E36,N36,AF36,AO36,AX36,BP36,BY36,CH36,CZ36,DI36,DR36,EA36,EJ36,FK36,FT36,GC36,GL36,HM36,IN36,IW36,JF36,JO36,JX36,KG36,KY36,LQ36,LZ36,MI36,MR36,NA36,NJ36,NS36,OK36,PC36,PU36) -> 0 | RH36: =MAX(W36,BG36,CQ36,HD36,LH36,OB36,OT36) -> 0 | RI36: =MIN(W36,BG36,CQ36,HD36,LH36,OB36,OT36) -> 0 | RK36: =IFERROR(SUM(E36,N36,W36,AF36,AO36,AX36,BG36,BP36,BY36,CH36,CQ36,CZ36,DI36,DR36,EA36,EJ36,FK36,GC36,GL36,HD36,HM36,IN36,IW36,JF36,JO36,JX36,KG36,KY36,LH36,LQ36,LZ36,MI36,MR36,NA36,NJ36,NS36,OB36,OK36,OT36,PC36,)/QY36,0) -> 0 | RM36: =MAX(ES36,IE36) -> 0 | RN36: =MIN(ES36,IE36) -> 0 | RP36: =SUM(EX36,IJ36)/5 -> 0
A37: ='Name List'!B37 -> Justin Hunt | E37: =IF(C37=0,"",C37+D37) | J37: =IF(E37="","",'Name List'!$I$4) | U37: 16 | V37: 18 | W37: =IF(U37=0,"",U37+V37) -> 34 | X37: 0 | Y37: 0 | Z37: 10 | AA37: 1 | AB37: =IF(W37="","",'Name List'!$I$4) -> 5 | AD37: 17 | AE37: 17 | AF37: =IF(AD37=0,"",AD37+AE37) -> 34 | AG37: 0 | AH37: 1 | AI37: 9 | AJ37: 0 | AK37: =IF(AF37="","",'Name List'!$I$4) -> 5 | AO37: =IF(AM37=0,"",AM37+AN37) | AT37: =IF(AO37="","",'Name List'!$I$4) | AX37: =IF(AV37=0,"",AV37+AW37) | BC37: =IF(AX37="","",'Name List'!$I$4) | BE37: 14 | BF37: 18 | BG37: =IF(BE37=0,"",BE37+BF37) -> 32 | BH37: 0 | BI37: 1 | BJ37: 5 | BK37: 1 | BL37: =IF(BG37="","",'Name List'!$I$4) -> 5 | BW37: 14 | BX37: 14 | BY37: =IF(BW37=0,"",BW37+BX37) -> 28 | BZ37: 0 | CA37: 0 | CB37: 7 | CC37: 1 | CD37: =IF(BY37="","",'Name List'!$I$4) -> 5 | CH37: =IF(CF37=0,"",CF37+CG37) | CM37: =IF(CH37="","",'Name List'!$I$4) | CQ37: =IF(CO37=0,"",CO37+CP37) | CV37: =IF(CQ37="","",'Name List'!$I$4) | CZ37: =IF(CX37=0,"",CX37+CY37) | DE37: =IF(CZ37="","",'Name List'!$I$4) | DG37: 19 | DH37: 12 | DI37: =IF(DG37=0,"",DG37+DH37) -> 31 | DJ37: 0 | DK37: 2 | DL37: 4 | DM37: 2 | DN37: =IF(DI37="","",'Name List'!$I$4) -> 5 | DP37: 19 | DQ37: 23 | DR37: =IF(DP37=0,"",DP37+DQ37) -> 42 | DS37: 1 | DT37: 5 | DU37: 4 | DV37: 1 | DW37: =IF(DR37="","",'Name List'!$I$4) -> 5 | EA37: =IF(DY37=0,"",DY37+DZ37) | EF37: =IF(EA37="","",'Name List'!$I$4) | EH37: 21 | EI37: 15 | EJ37: =IF(EH37=0,"",EH37+EI37) -> 36 | EK37: 0 | EL37: 0 | EM37: 12 | EN37: 0 | EO37: =IF(EJ37="","",'Name List'!$I$4) -> 5 | ES37: 82 | ET37: 0 | EU37: 2 | EV37: 9 | EX37: =IF(ES37="","",'Name List'!$I$4) -> 5 | FK37: =IF(FI37=0,"",FI37+FJ37) | FP37: =IF(FK37="","",'Name List'!$I$4) | FT37: =IF(FR37=0,"",FR37+FS37) | FY37: =IF(FT37="","",'Name List'!$I$4) | GA37: 19 | GB37: 17 | GC37: =IF(GA37=0,"",GA37+GB37) -> 36 | GD37: 0 | GE37: 2 | GF37: 9 | GG37: 1 | GH37: =IF(GC37="","",'Name List'!$I$4) -> 5 | GJ37: 17 | GK37: 20 | GL37: =IF(GJ37=0,"",GJ37+GK37) -> 37 | GM37: 0 | GN37: 2 | GO37: 11 | GP37: 1 | GQ37: =IF(GL37="","",'Name List'!$I$4) -> 5 | HD37: =IF(HB37=0,"",HB37+HC37) | HI37: =IF(HD37="","",'Name List'!$I$4) | HM37: =IF(HK37=0,"",HK37+HL37) | HR37: =IF(HM37="","",'Name List'!$I$4) | IJ37: =IF(IE37="","",'Name List'!$I$4) | QR37: =IF(QM37="","",'Name List'!$I$4) | QT37: =SUM(F37+O37+X37+AG37+AP37+AY37+BH37+BQ37+BZ37+CI37+CR37+DA37+DJ37+DS37+EB37+EK37+ET37+FC37+FL37+FU37+GD37+GM37+GV37+HE37+HN37+HW37+IF37+IO37+IX37+JG37+JP37+JY37+KH37+KQ37+KZ37+LI37+LR37+MA37+MJ37+MS37+NB37+NK37+NT37+OC37+OL37+OU37+PD37+PM37+PV37+QE37+QN37) -> 1 | QU37: =SUM(G37+P37+Y37+AH37+AQ37+AZ37+BI37+BR37+CA37+CJ37+CS37+DB37+DK37+DT37+EC37+EL37+EU37+FD37+FM37+FV37+GE37+GN37+GW37+HF37+HO37+HX37+IG37+IP37+IY37+JH37+JQ37+JZ37+KI37+KR37+LA37+LJ37+LS37+MB37+MK37+MT37+NC37+NL37+NU37+OD37+OM37+OV37+PE37+PN37+PW37+QF37+QO37) -> 15 | QV37: =SUM(H37+Q37+Z37+AI37+AR37+BA37+BJ37+BS37+CB37+CK37+CT37+DC37+DL37+DU37+ED37+EM37+EV37+FE37+FN37+FW37+GF37+GO37+GX37+HG37+HP37+HY37+IH37+IQ37+IZ37+JI37+JR37+KA37+KJ37+KS37+LB37+LK37+LT37+MC37+ML37+MU37+ND37+NM37+NV37+OE37+ON37+OW37+PF37+PO37+PX37+QG37+QP37) -> 80 | QW37: =SUM(I37+R37+AA37+AJ37+AS37+BB37+BK37+BT37+CC37+CL37+CU37+DD37+DM37+DV37+EE37+EN37+EW37+FF37+FO37+FX37+GG37+GP37+GY37+HH37+HQ37+HZ37+II37+IR37+JA37+JJ37+JS37+KB37+KK37+KT37+LC37+LL37+LU37+MD37+MM37+MV37+NE37+NN37+NW37+OF37+OO37+OX37+PG37+PP37+PY37+QH37+QQ37) -> 8 | QY37: =SUM(J37,S37,AB37,AK37,AT37,BC37,BL37,BU37,CD37,CM37,CV37,DE37,DN37,DW37,EF37,EO37,FP37,FY37,GH37,GQ37,HI37,HR37,IS37,JB37,JK37,JT37,KC37,KL37,KU37,LD37,LM37,LV37,ME37,MN37,MW37,NF37,NO37,NX37,OG37,OP37,OY37,PH37,PZ37)/5 -> 9 | RA37: =MAX(C37,L37,AD37,AM37,AV37,BN37,BW37,CF37,CX37,DG37,DP37,DY37,EH37,FI37,FR37,GA37,GJ37,HK37,IL37,IU37,JD37,JM37,JV37,KE37,KW37,LO37,LX37,MG37,MP37,MY37,NH37,NQ37,OI37,PA37,PS37) -> 21 | RB37: =MAX(D37,M37,AE37,AN37,AW37,BO37,BX37,CG37,CY37,DH37,DQ37,DZ37,EI37,FJ37,FS37,GB37,GK37,HL37,IM37,IV37,JE37,JN37,JW37,KF37,KX37,LP37,LY37,MH37,MQ37,MZ37,NI37,NR37,OJ37,PB37,PT37) -> 23 | RC37: =MAX(E37,N37,AF37,AO37,AX37,BP37,BY37,CH37,CZ37,DI37,DR37,EA37,EJ37,FK37,FT37,GC37,GL37,HM37,IN37,IW37,JF37,JO37,JX37,KG37,KY37,LQ37,LZ37,MI37,MR37,NA37,NJ37,NS37,OK37,PC37,PU37) -> 42 | RD37: =MIN(C37,L37,AD37,AM37,AV37,BN37,BW37,CF37,CX37,DG37,DP37,DY37,EH37,FI37,FR37,GA37,GJ37,HK37,IL37,IU37,JD37,JM37,JV37,KE37,KW37,LO37,LX37,MG37,MP37,MY37,NH37,NQ37,OI37,PA37,PS37) -> 14 | RE37: =MIN(D37,M37,AE37,AN37,AW37,BO37,BX37,CG37,CY37,DH37,DQ37,DZ37,EI37,FJ37,FS37,GB37,GK37,HL37,IM37,IV37,JE37,JN37,JW37,KF37,KX37,LP37,LY37,MH37,MQ37,MZ37,NI37,NR37,OJ37,PB37,PT37) -> 12 | RF37: =MIN(E37,N37,AF37,AO37,AX37,BP37,BY37,CH37,CZ37,DI37,DR37,EA37,EJ37,FK37,FT37,GC37,GL37,HM37,IN37,IW37,JF37,JO37,JX37,KG37,KY37,LQ37,LZ37,MI37,MR37,NA37,NJ37,NS37,OK37,PC37,PU37) -> 28 | RH37: =MAX(W37,BG37,CQ37,HD37,LH37,OB37,OT37) -> 34 | RI37: =MIN(W37,BG37,CQ37,HD37,LH37,OB37,OT37) -> 32 | RK37: =IFERROR(SUM(E37,N37,W37,AF37,AO37,AX37,BG37,BP37,BY37,CH37,CQ37,CZ37,DI37,DR37,EA37,EJ37,FK37,GC37,GL37,HD37,HM37,IN37,IW37,JF37,JO37,JX37,KG37,KY37,LH37,LQ37,LZ37,MI37,MR37,NA37,NJ37,NS37,OB37,OK37,OT37,PC37,)/QY37,0) -> 34.444444 | RM37: =MAX(ES37,IE37) -> 82 | RN37: =MIN(ES37,IE37) -> 82 | RP37: =SUM(EX37,IJ37)/5 -> 1
A38: ='Name List'!B38 -> Mark Hutchinson | E38: =IF(C38=0,"",C38+D38) | J38: =IF(E38="","",'Name List'!$I$4) | W38: =IF(U38=0,"",U38+V38) | AB38: =IF(W38="","",'Name List'!$I$4) | AF38: =IF(AD38=0,"",AD38+AE38) | AK38: =IF(AF38="","",'Name List'!$I$4) | AO38: =IF(AM38=0,"",AM38+AN38) | AT38: =IF(AO38="","",'Name List'!$I$4) | AX38: =IF(AV38=0,"",AV38+AW38) | BC38: =IF(AX38="","",'Name List'!$I$4) | BG38: =IF(BE38=0,"",BE38+BF38) | BL38: =IF(BG38="","",'Name List'!$I$4) | BY38: =IF(BW38=0,"",BW38+BX38) | CD38: =IF(BY38="","",'Name List'!$I$4) | CH38: =IF(CF38=0,"",CF38+CG38) | CM38: =IF(CH38="","",'Name List'!$I$4) | CQ38: =IF(CO38=0,"",CO38+CP38) | CV38: =IF(CQ38="","",'Name List'!$I$4) | CZ38: =IF(CX38=0,"",CX38+CY38) | DE38: =IF(CZ38="","",'Name List'!$I$4) | DI38: =IF(DG38=0,"",DG38+DH38) | DN38: =IF(DI38="","",'Name List'!$I$4) | DR38: =IF(DP38=0,"",DP38+DQ38) | DW38: =IF(DR38="","",'Name List'!$I$4) | EA38: =IF(DY38=0,"",DY38+DZ38) | EF38: =IF(EA38="","",'Name List'!$I$4) | EJ38: =IF(EH38=0,"",EH38+EI38) | EO38: =IF(EJ38="","",'Name List'!$I$4) | EX38: =IF(ES38="","",'Name List'!$I$4) | FK38: =IF(FI38=0,"",FI38+FJ38) | FP38: =IF(FK38="","",'Name List'!$I$4) | FT38: =IF(FR38=0,"",FR38+FS38) | FY38: =IF(FT38="","",'Name List'!$I$4) | GC38: =IF(GA38=0,"",GA38+GB38) | GH38: =IF(GC38="","",'Name List'!$I$4) | GL38: =IF(GJ38=0,"",GJ38+GK38) | GQ38: =IF(GL38="","",'Name List'!$I$4) | HD38: =IF(HB38=0,"",HB38+HC38) | HI38: =IF(HD38="","",'Name List'!$I$4) | HM38: =IF(HK38=0,"",HK38+HL38) | HR38: =IF(HM38="","",'Name List'!$I$4) | IJ38: =IF(IE38="","",'Name List'!$I$4) | QR38: =IF(QM38="","",'Name List'!$I$4) | QT38: =SUM(F38+O38+X38+AG38+AP38+AY38+BH38+BQ38+BZ38+CI38+CR38+DA38+DJ38+DS38+EB38+EK38+ET38+FC38+FL38+FU38+GD38+GM38+GV38+HE38+HN38+HW38+IF38+IO38+IX38+JG38+JP38+JY38+KH38+KQ38+KZ38+LI38+LR38+MA38+MJ38+MS38+NB38+NK38+NT38+OC38+OL38+OU38+PD38+PM38+PV38+QE38+QN38) -> 0 | QU38: =SUM(G38+P38+Y38+AH38+AQ38+AZ38+BI38+BR38+CA38+CJ38+CS38+DB38+DK38+DT38+EC38+EL38+EU38+FD38+FM38+FV38+GE38+GN38+GW38+HF38+HO38+HX38+IG38+IP38+IY38+JH38+JQ38+JZ38+KI38+KR38+LA38+LJ38+LS38+MB38+MK38+MT38+NC38+NL38+NU38+OD38+OM38+OV38+PE38+PN38+PW38+QF38+QO38) -> 0 | QV38: =SUM(H38+Q38+Z38+AI38+AR38+BA38+BJ38+BS38+CB38+CK38+CT38+DC38+DL38+DU38+ED38+EM38+EV38+FE38+FN38+FW38+GF38+GO38+GX38+HG38+HP38+HY38+IH38+IQ38+IZ38+JI38+JR38+KA38+KJ38+KS38+LB38+LK38+LT38+MC38+ML38+MU38+ND38+NM38+NV38+OE38+ON38+OW38+PF38+PO38+PX38+QG38+QP38) -> 0 | QW38: =SUM(I38+R38+AA38+AJ38+AS38+BB38+BK38+BT38+CC38+CL38+CU38+DD38+DM38+DV38+EE38+EN38+EW38+FF38+FO38+FX38+GG38+GP38+GY38+HH38+HQ38+HZ38+II38+IR38+JA38+JJ38+JS38+KB38+KK38+KT38+LC38+LL38+LU38+MD38+MM38+MV38+NE38+NN38+NW38+OF38+OO38+OX38+PG38+PP38+PY38+QH38+QQ38) -> 0 | QY38: =SUM(J38,S38,AB38,AK38,AT38,BC38,BL38,BU38,CD38,CM38,CV38,DE38,DN38,DW38,EF38,EO38,FP38,FY38,GH38,GQ38,HI38,HR38,IS38,JB38,JK38,JT38,KC38,KL38,KU38,LD38,LM38,LV38,ME38,MN38,MW38,NF38,NO38,NX38,OG38,OP38,OY38,PH38,PZ38)/5 -> 0 | RA38: =MAX(C38,L38,AD38,AM38,AV38,BN38,BW38,CF38,CX38,DG38,DP38,DY38,EH38,FI38,FR38,GA38,GJ38,HK38,IL38,IU38,JD38,JM38,JV38,KE38,KW38,LO38,LX38,MG38,MP38,MY38,NH38,NQ38,OI38,PA38,PS38) -> 0 | RB38: =MAX(D38,M38,AE38,AN38,AW38,BO38,BX38,CG38,CY38,DH38,DQ38,DZ38,EI38,FJ38,FS38,GB38,GK38,HL38,IM38,IV38,JE38,JN38,JW38,KF38,KX38,LP38,LY38,MH38,MQ38,MZ38,NI38,NR38,OJ38,PB38,PT38) -> 0 | RC38: =MAX(E38,N38,AF38,AO38,AX38,BP38,BY38,CH38,CZ38,DI38,DR38,EA38,EJ38,FK38,FT38,GC38,GL38,HM38,IN38,IW38,JF38,JO38,JX38,KG38,KY38,LQ38,LZ38,MI38,MR38,NA38,NJ38,NS38,OK38,PC38,PU38) -> 0 | RD38: =MIN(C38,L38,AD38,AM38,AV38,BN38,BW38,CF38,CX38,DG38,DP38,DY38,EH38,FI38,FR38,GA38,GJ38,HK38,IL38,IU38,JD38,JM38,JV38,KE38,KW38,LO38,LX38,MG38,MP38,MY38,NH38,NQ38,OI38,PA38,PS38) -> 0 | RE38: =MIN(D38,M38,AE38,AN38,AW38,BO38,BX38,CG38,CY38,DH38,DQ38,DZ38,EI38,FJ38,FS38,GB38,GK38,HL38,IM38,IV38,JE38,JN38,JW38,KF38,KX38,LP38,LY38,MH38,MQ38,MZ38,NI38,NR38,OJ38,PB38,PT38) -> 0 | RF38: =MIN(E38,N38,AF38,AO38,AX38,BP38,BY38,CH38,CZ38,DI38,DR38,EA38,EJ38,FK38,FT38,GC38,GL38,HM38,IN38,IW38,JF38,JO38,JX38,KG38,KY38,LQ38,LZ38,MI38,MR38,NA38,NJ38,NS38,OK38,PC38,PU38) -> 0 | RH38: =MAX(W38,BG38,CQ38,HD38,LH38,OB38,OT38) -> 0 | RI38: =MIN(W38,BG38,CQ38,HD38,LH38,OB38,OT38) -> 0 | RK38: =IFERROR(SUM(E38,N38,W38,AF38,AO38,AX38,BG38,BP38,BY38,CH38,CQ38,CZ38,DI38,DR38,EA38,EJ38,FK38,GC38,GL38,HD38,HM38,IN38,IW38,JF38,JO38,JX38,KG38,KY38,LH38,LQ38,LZ38,MI38,MR38,NA38,NJ38,NS38,OB38,OK38,OT38,PC38,)/QY38,0) -> 0 | RM38: =MAX(ES38,IE38) -> 0 | RN38: =MIN(ES38,IE38) -> 0 | RP38: =SUM(EX38,IJ38)/5 -> 0
A39: ='Name List'!B39 -> Andy Johnson | E39: =IF(C39=0,"",C39+D39) | J39: =IF(E39="","",'Name List'!$I$4) | U39: 14 | V39: 13 | W39: =IF(U39=0,"",U39+V39) -> 27 | X39: 0 | Y39: 1 | Z39: 5 | AA39: 2 | AB39: =IF(W39="","",'Name List'!$I$4) -> 5 | AF39: =IF(AD39=0,"",AD39+AE39) | AK39: =IF(AF39="","",'Name List'!$I$4) | AM39: 16 | AN39: 19 | AO39: =IF(AM39=0,"",AM39+AN39) -> 35 | AP39: 0 | AQ39: 1 | AR39: 11 | AS39: 0 | AT39: =IF(AO39="","",'Name List'!$I$4) -> 5 | AX39: =IF(AV39=0,"",AV39+AW39) | BC39: =IF(AX39="","",'Name List'!$I$4) | BE39: 15 | BF39: 15 | BG39: =IF(BE39=0,"",BE39+BF39) -> 30 | BH39: 0 | BI39: 0 | BJ39: 8 | BK39: 2 | BL39: =IF(BG39="","",'Name List'!$I$4) -> 5 | BW39: 16 | BX39: 16 | BY39: =IF(BW39=0,"",BW39+BX39) -> 32 | BZ39: 0 | CA39: 1 | CB39: 9 | CC39: 2 | CD39: =IF(BY39="","",'Name List'!$I$4) -> 5 | CF39: 18 | CG39: 17 | CH39: =IF(CF39=0,"",CF39+CG39) -> 35 | CI39: 0 | CJ39: 1 | CK39: 10 | CL39: 0 | CM39: =IF(CH39="","",'Name List'!$I$4) -> 5 | CQ39: =IF(CO39=0,"",CO39+CP39) | CV39: =IF(CQ39="","",'Name List'!$I$4) | CZ39: =IF(CX39=0,"",CX39+CY39) | DE39: =IF(CZ39="","",'Name List'!$I$4) | DG39: 21 | DH39: 17 | DI39: =IF(DG39=0,"",DG39+DH39) -> 38 | DJ39: 0 | DK39: 4 | DL39: 7 | DM39: 0 | DN39: =IF(DI39="","",'Name List'!$I$4) -> 5 | DP39: 14 | DQ39: 12 | DR39: =IF(DP39=0,"",DP39+DQ39) -> 26 | DS39: 0 | DT39: 0 | DU39: 9 | DV39: 2 | DW39: =IF(DR39="","",'Name List'!$I$4) -> 5 | EA39: =IF(DY39=0,"",DY39+DZ39) | EF39: =IF(EA39="","",'Name List'!$I$4) | EH39: 16 | EI39: 18 | EJ39: =IF(EH39=0,"",EH39+EI39) -> 34 | EK39: 0 | EL39: 3 | EM39: 7 | EN39: 1 | EO39: =IF(EJ39="","",'Name List'!$I$4) -> 5 | ES39: 93 | ET39: 0 | EU39: 0 | EV39: 0 | EX39: =IF(ES39="","",'Name List'!$I$4) -> 5 | FK39: =IF(FI39=0,"",FI39+FJ39) | FP39: =IF(FK39="","",'Name List'!$I$4) | FR39: 17 | FS39: 14 | FT39: =IF(FR39=0,"",FR39+FS39) -> 31 | FU39: 0 | FV39: 2 | FW39: 6 | FX39: 2 | FY39: =IF(FT39="","",'Name List'!$I$4) -> 5 | GC39: =IF(GA39=0,"",GA39+GB39) | GH39: =IF(GC39="","",'Name List'!$I$4) | GJ39: 15 | GK39: 12 | GL39: =IF(GJ39=0,"",GJ39+GK39) -> 27 | GM39: 0 | GN39: 1 | GO39: 7 | GP39: 1 | GQ39: =IF(GL39="","",'Name List'!$I$4) -> 5 | HB39: 17 | HC39: 20 | HD39: =IF(HB39=0,"",HB39+HC39) -> 37 | HE39: 0 | HF39: 2 | HG39: 10 | HH39: 1 | HI39: =IF(HD39="","",'Name List'!$I$4) -> 5 | HK39: 19 | HL39: 17 | HM39: =IF(HK39=0,"",HK39+HL39) -> 36 | HN39: 0 | HO39: 1 | HP39: 11 | HQ39: 1 | HR39: =IF(HM39="","",'Name List'!$I$4) -> 5 | IJ39: =IF(IE39="","",'Name List'!$I$4) | QR39: =IF(QM39="","",'Name List'!$I$4) | QT39: =SUM(F39+O39+X39+AG39+AP39+AY39+BH39+BQ39+BZ39+CI39+CR39+DA39+DJ39+DS39+EB39+EK39+ET39+FC39+FL39+FU39+GD39+GM39+GV39+HE39+HN39+HW39+IF39+IO39+IX39+JG39+JP39+JY39+KH39+KQ39+KZ39+LI39+LR39+MA39+MJ39+MS39+NB39+NK39+NT39+OC39+OL39+OU39+PD39+PM39+PV39+QE39+QN39) -> 0 | QU39: =SUM(G39+P39+Y39+AH39+AQ39+AZ39+BI39+BR39+CA39+CJ39+CS39+DB39+DK39+DT39+EC39+EL39+EU39+FD39+FM39+FV39+GE39+GN39+GW39+HF39+HO39+HX39+IG39+IP39+IY39+JH39+JQ39+JZ39+KI39+KR39+LA39+LJ39+LS39+MB39+MK39+MT39+NC39+NL39+NU39+OD39+OM39+OV39+PE39+PN39+PW39+QF39+QO39) -> 17 | QV39: =SUM(H39+Q39+Z39+AI39+AR39+BA39+BJ39+BS39+CB39+CK39+CT39+DC39+DL39+DU39+ED39+EM39+EV39+FE39+FN39+FW39+GF39+GO39+GX39+HG39+HP39+HY39+IH39+IQ39+IZ39+JI39+JR39+KA39+KJ39+KS39+LB39+LK39+LT39+MC39+ML39+MU39+ND39+NM39+NV39+OE39+ON39+OW39+PF39+PO39+PX39+QG39+QP39) -> 100 | QW39: =SUM(I39+R39+AA39+AJ39+AS39+BB39+BK39+BT39+CC39+CL39+CU39+DD39+DM39+DV39+EE39+EN39+EW39+FF39+FO39+FX39+GG39+GP39+GY39+HH39+HQ39+HZ39+II39+IR39+JA39+JJ39+JS39+KB39+KK39+KT39+LC39+LL39+LU39+MD39+MM39+MV39+NE39+NN39+NW39+OF39+OO39+OX39+PG39+PP39+PY39+QH39+QQ39) -> 14 | QY39: =SUM(J39,S39,AB39,AK39,AT39,BC39,BL39,BU39,CD39,CM39,CV39,DE39,DN39,DW39,EF39,EO39,FP39,FY39,GH39,GQ39,HI39,HR39,IS39,JB39,JK39,JT39,KC39,KL39,KU39,LD39,LM39,LV39,ME39,MN39,MW39,NF39,NO39,NX39,OG39,OP39,OY39,PH39,PZ39)/5 -> 12 | RA39: =MAX(C39,L39,AD39,AM39,AV39,BN39,BW39,CF39,CX39,DG39,DP39,DY39,EH39,FI39,FR39,GA39,GJ39,HK39,IL39,IU39,JD39,JM39,JV39,KE39,KW39,LO39,LX39,MG39,MP39,MY39,NH39,NQ39,OI39,PA39,PS39) -> 21 | RB39: =MAX(D39,M39,AE39,AN39,AW39,BO39,BX39,CG39,CY39,DH39,DQ39,DZ39,EI39,FJ39,FS39,GB39,GK39,HL39,IM39,IV39,JE39,JN39,JW39,KF39,KX39,LP39,LY39,MH39,MQ39,MZ39,NI39,NR39,OJ39,PB39,PT39) -> 19 | RC39: =MAX(E39,N39,AF39,AO39,AX39,BP39,BY39,CH39,CZ39,DI39,DR39,EA39,EJ39,FK39,FT39,GC39,GL39,HM39,IN39,IW39,JF39,JO39,JX39,KG39,KY39,LQ39,LZ39,MI39,MR39,NA39,NJ39,NS39,OK39,PC39,PU39) -> 38 | RD39: =MIN(C39,L39,AD39,AM39,AV39,BN39,BW39,CF39,CX39,DG39,DP39,DY39,EH39,FI39,FR39,GA39,GJ39,HK39,IL39,IU39,JD39,JM39,JV39,KE39,KW39,LO39,LX39,MG39,MP39,MY39,NH39,NQ39,OI39,PA39,PS39) -> 14 | RE39: =MIN(D39,M39,AE39,AN39,AW39,BO39,BX39,CG39,CY39,DH39,DQ39,DZ39,EI39,FJ39,FS39,GB39,GK39,HL39,IM39,IV39,JE39,JN39,JW39,KF39,KX39,LP39,LY39,MH39,MQ39,MZ39,NI39,NR39,OJ39,PB39,PT39) -> 12 | RF39: =MIN(E39,N39,AF39,AO39,AX39,BP39,BY39,CH39,CZ39,DI39,DR39,EA39,EJ39,FK39,FT39,GC39,GL39,HM39,IN39,IW39,JF39,JO39,JX39,KG39,KY39,LQ39,LZ39,MI39,MR39,NA39,NJ39,NS39,OK39,PC39,PU39) -> 26 | RH39: =MAX(W39,BG39,CQ39,HD39,LH39,OB39,OT39) -> 37 | RI39: =MIN(W39,BG39,CQ39,HD39,LH39,OB39,OT39) -> 27 | RK39: =IFERROR(SUM(E39,N39,W39,AF39,AO39,AX39,BG39,BP39,BY39,CH39,CQ39,CZ39,DI39,DR39,EA39,EJ39,FK39,GC39,GL39,HD39,HM39,IN39,IW39,JF39,JO39,JX39,KG39,KY39,LH39,LQ39,LZ39,MI39,MR39,NA39,NJ39,NS39,OB39,OK39,OT39,PC39,)/QY39,0) -> 29.75 | RM39: =MAX(ES39,IE39) -> 93 | RN39: =MIN(ES39,IE39) -> 93 | RP39: =SUM(EX39,IJ39)/5 -> 1
A40: ='Name List'!B40 -> Oli Lloyd | E40: =IF(C40=0,"",C40+D40) | J40: =IF(E40="","",'Name List'!$I$4) | W40: =IF(U40=0,"",U40+V40) | AB40: =IF(W40="","",'Name List'!$I$4) | AF40: =IF(AD40=0,"",AD40+AE40) | AK40: =IF(AF40="","",'Name List'!$I$4) | AO40: =IF(AM40=0,"",AM40+AN40) | AT40: =IF(AO40="","",'Name List'!$I$4) | AX40: =IF(AV40=0,"",AV40+AW40) | BC40: =IF(AX40="","",'Name List'!$I$4) | BG40: =IF(BE40=0,"",BE40+BF40) | BL40: =IF(BG40="","",'Name List'!$I$4) | BY40: =IF(BW40=0,"",BW40+BX40) | CD40: =IF(BY40="","",'Name List'!$I$4) | CH40: =IF(CF40=0,"",CF40+CG40) | CM40: =IF(CH40="","",'Name List'!$I$4) | CO40: 15 | CP40: 17 | CQ40: =IF(CO40=0,"",CO40+CP40) -> 32 | CR40: 0 | CS40: 0 | CT40: 9 | CU40: 2 | CV40: =IF(CQ40="","",'Name List'!$I$4) -> 5 | CX40: 14 | CY40: 14 | CZ40: =IF(CX40=0,"",CX40+CY40) -> 28 | DA40: 0 | DB40: 1 | DC40: 8 | DD40: 2 | DE40: =IF(CZ40="","",'Name List'!$I$4) -> 5 | DI40: =IF(DG40=0,"",DG40+DH40) | DN40: =IF(DI40="","",'Name List'!$I$4) | DR40: =IF(DP40=0,"",DP40+DQ40) | DW40: =IF(DR40="","",'Name List'!$I$4) | EA40: =IF(DY40=0,"",DY40+DZ40) | EF40: =IF(EA40="","",'Name List'!$I$4) | EJ40: =IF(EH40=0,"",EH40+EI40) | EO40: =IF(EJ40="","",'Name List'!$I$4) | EX40: =IF(ES40="","",'Name List'!$I$4) | FK40: =IF(FI40=0,"",FI40+FJ40) | FP40: =IF(FK40="","",'Name List'!$I$4) | FT40: =IF(FR40=0,"",FR40+FS40) | FY40: =IF(FT40="","",'Name List'!$I$4) | GC40: =IF(GA40=0,"",GA40+GB40) | GH40: =IF(GC40="","",'Name List'!$I$4) | GL40: =IF(GJ40=0,"",GJ40+GK40) | GQ40: =IF(GL40="","",'Name List'!$I$4) | HD40: =IF(HB40=0,"",HB40+HC40) | HI40: =IF(HD40="","",'Name List'!$I$4) | HM40: =IF(HK40=0,"",HK40+HL40) | HR40: =IF(HM40="","",'Name List'!$I$4) | IJ40: =IF(IE40="","",'Name List'!$I$4) | QR40: =IF(QM40="","",'Name List'!$I$4) | QT40: =SUM(F40+O40+X40+AG40+AP40+AY40+BH40+BQ40+BZ40+CI40+CR40+DA40+DJ40+DS40+EB40+EK40+ET40+FC40+FL40+FU40+GD40+GM40+GV40+HE40+HN40+HW40+IF40+IO40+IX40+JG40+JP40+JY40+KH40+KQ40+KZ40+LI40+LR40+MA40+MJ40+MS40+NB40+NK40+NT40+OC40+OL40+OU40+PD40+PM40+PV40+QE40+QN40) -> 0 | QU40: =SUM(G40+P40+Y40+AH40+AQ40+AZ40+BI40+BR40+CA40+CJ40+CS40+DB40+DK40+DT40+EC40+EL40+EU40+FD40+FM40+FV40+GE40+GN40+GW40+HF40+HO40+HX40+IG40+IP40+IY40+JH40+JQ40+JZ40+KI40+KR40+LA40+LJ40+LS40+MB40+MK40+MT40+NC40+NL40+NU40+OD40+OM40+OV40+PE40+PN40+PW40+QF40+QO40) -> 1 | QV40: =SUM(H40+Q40+Z40+AI40+AR40+BA40+BJ40+BS40+CB40+CK40+CT40+DC40+DL40+DU40+ED40+EM40+EV40+FE40+FN40+FW40+GF40+GO40+GX40+HG40+HP40+HY40+IH40+IQ40+IZ40+JI40+JR40+KA40+KJ40+KS40+LB40+LK40+LT40+MC40+ML40+MU40+ND40+NM40+NV40+OE40+ON40+OW40+PF40+PO40+PX40+QG40+QP40) -> 17 | QW40: =SUM(I40+R40+AA40+AJ40+AS40+BB40+BK40+BT40+CC40+CL40+CU40+DD40+DM40+DV40+EE40+EN40+EW40+FF40+FO40+FX40+GG40+GP40+GY40+HH40+HQ40+HZ40+II40+IR40+JA40+JJ40+JS40+KB40+KK40+KT40+LC40+LL40+LU40+MD40+MM40+MV40+NE40+NN40+NW40+OF40+OO40+OX40+PG40+PP40+PY40+QH40+QQ40) -> 4 | QY40: =SUM(J40,S40,AB40,AK40,AT40,BC40,BL40,BU40,CD40,CM40,CV40,DE40,DN40,DW40,EF40,EO40,FP40,FY40,GH40,GQ40,HI40,HR40,IS40,JB40,JK40,JT40,KC40,KL40,KU40,LD40,LM40,LV40,ME40,MN40,MW40,NF40,NO40,NX40,OG40,OP40,OY40,PH40,PZ40)/5 -> 2 | RA40: =MAX(C40,L40,AD40,AM40,AV40,BN40,BW40,CF40,CX40,DG40,DP40,DY40,EH40,FI40,FR40,GA40,GJ40,HK40,IL40,IU40,JD40,JM40,JV40,KE40,KW40,LO40,LX40,MG40,MP40,MY40,NH40,NQ40,OI40,PA40,PS40) -> 14 | RB40: =MAX(D40,M40,AE40,AN40,AW40,BO40,BX40,CG40,CY40,DH40,DQ40,DZ40,EI40,FJ40,FS40,GB40,GK40,HL40,IM40,IV40,JE40,JN40,JW40,KF40,KX40,LP40,LY40,MH40,MQ40,MZ40,NI40,NR40,OJ40,PB40,PT40) -> 14 | RC40: =MAX(E40,N40,AF40,AO40,AX40,BP40,BY40,CH40,CZ40,DI40,DR40,EA40,EJ40,FK40,FT40,GC40,GL40,HM40,IN40,IW40,JF40,JO40,JX40,KG40,KY40,LQ40,LZ40,MI40,MR40,NA40,NJ40,NS40,OK40,PC40,PU40) -> 28 | RD40: =MIN(C40,L40,AD40,AM40,AV40,BN40,BW40,CF40,CX40,DG40,DP40,DY40,EH40,FI40,FR40,GA40,GJ40,HK40,IL40,IU40,JD40,JM40,JV40,KE40,KW40,LO40,LX40,MG40,MP40,MY40,NH40,NQ40,OI40,PA40,PS40) -> 14 | RE40: =MIN(D40,M40,AE40,AN40,AW40,BO40,BX40,CG40,CY40,DH40,DQ40,DZ40,EI40,FJ40,FS40,GB40,GK40,HL40,IM40,IV40,JE40,JN40,JW40,KF40,KX40,LP40,LY40,MH40,MQ40,MZ40,NI40,NR40,OJ40,PB40,PT40) -> 14 | RF40: =MIN(E40,N40,AF40,AO40,AX40,BP40,BY40,CH40,CZ40,DI40,DR40,EA40,EJ40,FK40,FT40,GC40,GL40,HM40,IN40,IW40,JF40,JO40,JX40,KG40,KY40,LQ40,LZ40,MI40,MR40,NA40,NJ40,NS40,OK40,PC40,PU40) -> 28 | RH40: =MAX(W40,BG40,CQ40,HD40,LH40,OB40,OT40) -> 32 | RI40: =MIN(W40,BG40,CQ40,HD40,LH40,OB40,OT40) -> 32 | RK40: =IFERROR(SUM(E40,N40,W40,AF40,AO40,AX40,BG40,BP40,BY40,CH40,CQ40,CZ40,DI40,DR40,EA40,EJ40,FK40,GC40,GL40,HD40,HM40,IN40,IW40,JF40,JO40,JX40,KG40,KY40,LH40,LQ40,LZ40,MI40,MR40,NA40,NJ40,NS40,OB40,OK40,OT40,PC40,)/QY40,0) -> 30 | RM40: =MAX(ES40,IE40) -> 0 | RN40: =MIN(ES40,IE40) -> 0 | RP40: =SUM(EX40,IJ40)/5 -> 0
A41: ='Name List'!B41 -> Andy Lucey | E41: =IF(C41=0,"",C41+D41) | J41: =IF(E41="","",'Name List'!$I$4) | W41: =IF(U41=0,"",U41+V41) | AB41: =IF(W41="","",'Name List'!$I$4) | AF41: =IF(AD41=0,"",AD41+AE41) | AK41: =IF(AF41="","",'Name List'!$I$4) | AO41: =IF(AM41=0,"",AM41+AN41) | AT41: =IF(AO41="","",'Name List'!$I$4) | AX41: =IF(AV41=0,"",AV41+AW41) | BC41: =IF(AX41="","",'Name List'!$I$4) | BG41: =IF(BE41=0,"",BE41+BF41) | BL41: =IF(BG41="","",'Name List'!$I$4) | BY41: =IF(BW41=0,"",BW41+BX41) | CD41: =IF(BY41="","",'Name List'!$I$4) | CH41: =IF(CF41=0,"",CF41+CG41) | CM41: =IF(CH41="","",'Name List'!$I$4) | CQ41: =IF(CO41=0,"",CO41+CP41) | CV41: =IF(CQ41="","",'Name List'!$I$4) | CZ41: =IF(CX41=0,"",CX41+CY41) | DE41: =IF(CZ41="","",'Name List'!$I$4) | DI41: =IF(DG41=0,"",DG41+DH41) | DN41: =IF(DI41="","",'Name List'!$I$4) | DR41: =IF(DP41=0,"",DP41+DQ41) | DW41: =IF(DR41="","",'Name List'!$I$4) | EA41: =IF(DY41=0,"",DY41+DZ41) | EF41: =IF(EA41="","",'Name List'!$I$4) | EJ41: =IF(EH41=0,"",EH41+EI41) | EO41: =IF(EJ41="","",'Name List'!$I$4) | EX41: =IF(ES41="","",'Name List'!$I$4) | FK41: =IF(FI41=0,"",FI41+FJ41) | FP41: =IF(FK41="","",'Name List'!$I$4) | FT41: =IF(FR41=0,"",FR41+FS41) | FY41: =IF(FT41="","",'Name List'!$I$4) | GC41: =IF(GA41=0,"",GA41+GB41) | GH41: =IF(GC41="","",'Name List'!$I$4) | GL41: =IF(GJ41=0,"",GJ41+GK41) | GQ41: =IF(GL41="","",'Name List'!$I$4) | HD41: =IF(HB41=0,"",HB41+HC41) | HI41: =IF(HD41="","",'Name List'!$I$4) | HM41: =IF(HK41=0,"",HK41+HL41) | HR41: =IF(HM41="","",'Name List'!$I$4) | IJ41: =IF(IE41="","",'Name List'!$I$4) | QR41: =IF(QM41="","",'Name List'!$I$4) | QT41: =SUM(F41+O41+X41+AG41+AP41+AY41+BH41+BQ41+BZ41+CI41+CR41+DA41+DJ41+DS41+EB41+EK41+ET41+FC41+FL41+FU41+GD41+GM41+GV41+HE41+HN41+HW41+IF41+IO41+IX41+JG41+JP41+JY41+KH41+KQ41+KZ41+LI41+LR41+MA41+MJ41+MS41+NB41+NK41+NT41+OC41+OL41+OU41+PD41+PM41+PV41+QE41+QN41) -> 0 | QU41: =SUM(G41+P41+Y41+AH41+AQ41+AZ41+BI41+BR41+CA41+CJ41+CS41+DB41+DK41+DT41+EC41+EL41+EU41+FD41+FM41+FV41+GE41+GN41+GW41+HF41+HO41+HX41+IG41+IP41+IY41+JH41+JQ41+JZ41+KI41+KR41+LA41+LJ41+LS41+MB41+MK41+MT41+NC41+NL41+NU41+OD41+OM41+OV41+PE41+PN41+PW41+QF41+QO41) -> 0 | QV41: =SUM(H41+Q41+Z41+AI41+AR41+BA41+BJ41+BS41+CB41+CK41+CT41+DC41+DL41+DU41+ED41+EM41+EV41+FE41+FN41+FW41+GF41+GO41+GX41+HG41+HP41+HY41+IH41+IQ41+IZ41+JI41+JR41+KA41+KJ41+KS41+LB41+LK41+LT41+MC41+ML41+MU41+ND41+NM41+NV41+OE41+ON41+OW41+PF41+PO41+PX41+QG41+QP41) -> 0 | QW41: =SUM(I41+R41+AA41+AJ41+AS41+BB41+BK41+BT41+CC41+CL41+CU41+DD41+DM41+DV41+EE41+EN41+EW41+FF41+FO41+FX41+GG41+GP41+GY41+HH41+HQ41+HZ41+II41+IR41+JA41+JJ41+JS41+KB41+KK41+KT41+LC41+LL41+LU41+MD41+MM41+MV41+NE41+NN41+NW41+OF41+OO41+OX41+PG41+PP41+PY41+QH41+QQ41) -> 0 | QY41: =SUM(J41,S41,AB41,AK41,AT41,BC41,BL41,BU41,CD41,CM41,CV41,DE41,DN41,DW41,EF41,EO41,FP41,FY41,GH41,GQ41,HI41,HR41,IS41,JB41,JK41,JT41,KC41,KL41,KU41,LD41,LM41,LV41,ME41,MN41,MW41,NF41,NO41,NX41,OG41,OP41,OY41,PH41,PZ41)/5 -> 0 | RA41: =MAX(C41,L41,AD41,AM41,AV41,BN41,BW41,CF41,CX41,DG41,DP41,DY41,EH41,FI41,FR41,GA41,GJ41,HK41,IL41,IU41,JD41,JM41,JV41,KE41,KW41,LO41,LX41,MG41,MP41,MY41,NH41,NQ41,OI41,PA41,PS41) -> 0 | RB41: =MAX(D41,M41,AE41,AN41,AW41,BO41,BX41,CG41,CY41,DH41,DQ41,DZ41,EI41,FJ41,FS41,GB41,GK41,HL41,IM41,IV41,JE41,JN41,JW41,KF41,KX41,LP41,LY41,MH41,MQ41,MZ41,NI41,NR41,OJ41,PB41,PT41) -> 0 | RC41: =MAX(E41,N41,AF41,AO41,AX41,BP41,BY41,CH41,CZ41,DI41,DR41,EA41,EJ41,FK41,FT41,GC41,GL41,HM41,IN41,IW41,JF41,JO41,JX41,KG41,KY41,LQ41,LZ41,MI41,MR41,NA41,NJ41,NS41,OK41,PC41,PU41) -> 0 | RD41: =MIN(C41,L41,AD41,AM41,AV41,BN41,BW41,CF41,CX41,DG41,DP41,DY41,EH41,FI41,FR41,GA41,GJ41,HK41,IL41,IU41,JD41,JM41,JV41,KE41,KW41,LO41,LX41,MG41,MP41,MY41,NH41,NQ41,OI41,PA41,PS41) -> 0 | RE41: =MIN(D41,M41,AE41,AN41,AW41,BO41,BX41,CG41,CY41,DH41,DQ41,DZ41,EI41,FJ41,FS41,GB41,GK41,HL41,IM41,IV41,JE41,JN41,JW41,KF41,KX41,LP41,LY41,MH41,MQ41,MZ41,NI41,NR41,OJ41,PB41,PT41) -> 0 | RF41: =MIN(E41,N41,AF41,AO41,AX41,BP41,BY41,CH41,CZ41,DI41,DR41,EA41,EJ41,FK41,FT41,GC41,GL41,HM41,IN41,IW41,JF41,JO41,JX41,KG41,KY41,LQ41,LZ41,MI41,MR41,NA41,NJ41,NS41,OK41,PC41,PU41) -> 0 | RH41: =MAX(W41,BG41,CQ41,HD41,LH41,OB41,OT41) -> 0 | RI41: =MIN(W41,BG41,CQ41,HD41,LH41,OB41,OT41) -> 0 | RK41: =IFERROR(SUM(E41,N41,W41,AF41,AO41,AX41,BG41,BP41,BY41,CH41,CQ41,CZ41,DI41,DR41,EA41,EJ41,FK41,GC41,GL41,HD41,HM41,IN41,IW41,JF41,JO41,JX41,KG41,KY41,LH41,LQ41,LZ41,MI41,MR41,NA41,NJ41,NS41,OB41,OK41,OT41,PC41,)/QY41,0) -> 0 | RM41: =MAX(ES41,IE41) -> 0 | RN41: =MIN(ES41,IE41) -> 0 | RP41: =SUM(EX41,IJ41)/5 -> 0
A42: ='Name List'!B42 -> Paul Martin | E42: =IF(C42=0,"",C42+D42) | J42: =IF(E42="","",'Name List'!$I$4) | W42: =IF(U42=0,"",U42+V42) | AB42: =IF(W42="","",'Name List'!$I$4) | AF42: =IF(AD42=0,"",AD42+AE42) | AK42: =IF(AF42="","",'Name List'!$I$4) | AO42: =IF(AM42=0,"",AM42+AN42) | AT42: =IF(AO42="","",'Name List'!$I$4) | AV42: 16 | AW42: 15 | AX42: =IF(AV42=0,"",AV42+AW42) -> 31 | AY42: 0 | AZ42: 1 | BA42: 11 | BB42: 2 | BC42: =IF(AX42="","",'Name List'!$I$4) -> 5 | BG42: =IF(BE42=0,"",BE42+BF42) | BL42: =IF(BG42="","",'Name List'!$I$4) | BY42: =IF(BW42=0,"",BW42+BX42) | CD42: =IF(BY42="","",'Name List'!$I$4) | CH42: =IF(CF42=0,"",CF42+CG42) | CM42: =IF(CH42="","",'Name List'!$I$4) | CQ42: =IF(CO42=0,"",CO42+CP42) | CV42: =IF(CQ42="","",'Name List'!$I$4) | CZ42: =IF(CX42=0,"",CX42+CY42) | DE42: =IF(CZ42="","",'Name List'!$I$4) | DG42: 16 | DH42: 20 | DI42: =IF(DG42=0,"",DG42+DH42) -> 36 | DJ42: 0 | DK42: 2 | DL42: 12 | DM42: 0 | DN42: =IF(DI42="","",'Name List'!$I$4) -> 5 | DR42: =IF(DP42=0,"",DP42+DQ42) | DW42: =IF(DR42="","",'Name List'!$I$4) | EA42: =IF(DY42=0,"",DY42+DZ42) | EF42: =IF(EA42="","",'Name List'!$I$4) | EJ42: =IF(EH42=0,"",EH42+EI42) | EO42: =IF(EJ42="","",'Name List'!$I$4) | ES42: 84 | ET42: 0 | EU42: 1 | EV42: 6 | EX42: =IF(ES42="","",'Name List'!$I$4) -> 5 | FK42: =IF(FI42=0,"",FI42+FJ42) | FP42: =IF(FK42="","",'Name List'!$I$4) | FT42: =IF(FR42=0,"",FR42+FS42) | FY42: =IF(FT42="","",'Name List'!$I$4) | GC42: =IF(GA42=0,"",GA42+GB42) | GH42: =IF(GC42="","",'Name List'!$I$4) | GL42: =IF(GJ42=0,"",GJ42+GK42) | GQ42: =IF(GL42="","",'Name List'!$I$4) | HD42: =IF(HB42=0,"",HB42+HC42) | HI42: =IF(HD42="","",'Name List'!$I$4) | HM42: =IF(HK42=0,"",HK42+HL42) | HR42: =IF(HM42="","",'Name List'!$I$4) | IJ42: =IF(IE42="","",'Name List'!$I$4) | QR42: =IF(QM42="","",'Name List'!$I$4) | QT42: =SUM(F42+O42+X42+AG42+AP42+AY42+BH42+BQ42+BZ42+CI42+CR42+DA42+DJ42+DS42+EB42+EK42+ET42+FC42+FL42+FU42+GD42+GM42+GV42+HE42+HN42+HW42+IF42+IO42+IX42+JG42+JP42+JY42+KH42+KQ42+KZ42+LI42+LR42+MA42+MJ42+MS42+NB42+NK42+NT42+OC42+OL42+OU42+PD42+PM42+PV42+QE42+QN42) -> 0 | QU42: =SUM(G42+P42+Y42+AH42+AQ42+AZ42+BI42+BR42+CA42+CJ42+CS42+DB42+DK42+DT42+EC42+EL42+EU42+FD42+FM42+FV42+GE42+GN42+GW42+HF42+HO42+HX42+IG42+IP42+IY42+JH42+JQ42+JZ42+KI42+KR42+LA42+LJ42+LS42+MB42+MK42+MT42+NC42+NL42+NU42+OD42+OM42+OV42+PE42+PN42+PW42+QF42+QO42) -> 4 | QV42: =SUM(H42+Q42+Z42+AI42+AR42+BA42+BJ42+BS42+CB42+CK42+CT42+DC42+DL42+DU42+ED42+EM42+EV42+FE42+FN42+FW42+GF42+GO42+GX42+HG42+HP42+HY42+IH42+IQ42+IZ42+JI42+JR42+KA42+KJ42+KS42+LB42+LK42+LT42+MC42+ML42+MU42+ND42+NM42+NV42+OE42+ON42+OW42+PF42+PO42+PX42+QG42+QP42) -> 29 | QW42: =SUM(I42+R42+AA42+AJ42+AS42+BB42+BK42+BT42+CC42+CL42+CU42+DD42+DM42+DV42+EE42+EN42+EW42+FF42+FO42+FX42+GG42+GP42+GY42+HH42+HQ42+HZ42+II42+IR42+JA42+JJ42+JS42+KB42+KK42+KT42+LC42+LL42+LU42+MD42+MM42+MV42+NE42+NN42+NW42+OF42+OO42+OX42+PG42+PP42+PY42+QH42+QQ42) -> 2 | QY42: =SUM(J42,S42,AB42,AK42,AT42,BC42,BL42,BU42,CD42,CM42,CV42,DE42,DN42,DW42,EF42,EO42,FP42,FY42,GH42,GQ42,HI42,HR42,IS42,JB42,JK42,JT42,KC42,KL42,KU42,LD42,LM42,LV42,ME42,MN42,MW42,NF42,NO42,NX42,OG42,OP42,OY42,PH42,PZ42)/5 -> 2 | RA42: =MAX(C42,L42,AD42,AM42,AV42,BN42,BW42,CF42,CX42,DG42,DP42,DY42,EH42,FI42,FR42,GA42,GJ42,HK42,IL42,IU42,JD42,JM42,JV42,KE42,KW42,LO42,LX42,MG42,MP42,MY42,NH42,NQ42,OI42,PA42,PS42) -> 16 | RB42: =MAX(D42,M42,AE42,AN42,AW42,BO42,BX42,CG42,CY42,DH42,DQ42,DZ42,EI42,FJ42,FS42,GB42,GK42,HL42,IM42,IV42,JE42,JN42,JW42,KF42,KX42,LP42,LY42,MH42,MQ42,MZ42,NI42,NR42,OJ42,PB42,PT42) -> 20 | RC42: =MAX(E42,N42,AF42,AO42,AX42,BP42,BY42,CH42,CZ42,DI42,DR42,EA42,EJ42,FK42,FT42,GC42,GL42,HM42,IN42,IW42,JF42,JO42,JX42,KG42,KY42,LQ42,LZ42,MI42,MR42,NA42,NJ42,NS42,OK42,PC42,PU42) -> 36 | RD42: =MIN(C42,L42,AD42,AM42,AV42,BN42,BW42,CF42,CX42,DG42,DP42,DY42,EH42,FI42,FR42,GA42,GJ42,HK42,IL42,IU42,JD42,JM42,JV42,KE42,KW42,LO42,LX42,MG42,MP42,MY42,NH42,NQ42,OI42,PA42,PS42) -> 16 | RE42: =MIN(D42,M42,AE42,AN42,AW42,BO42,BX42,CG42,CY42,DH42,DQ42,DZ42,EI42,FJ42,FS42,GB42,GK42,HL42,IM42,IV42,JE42,JN42,JW42,KF42,KX42,LP42,LY42,MH42,MQ42,MZ42,NI42,NR42,OJ42,PB42,PT42) -> 15 | RF42: =MIN(E42,N42,AF42,AO42,AX42,BP42,BY42,CH42,CZ42,DI42,DR42,EA42,EJ42,FK42,FT42,GC42,GL42,HM42,IN42,IW42,JF42,JO42,JX42,KG42,KY42,LQ42,LZ42,MI42,MR42,NA42,NJ42,NS42,OK42,PC42,PU42) -> 31 | RH42: =MAX(W42,BG42,CQ42,HD42,LH42,OB42,OT42) -> 0 | RI42: =MIN(W42,BG42,CQ42,HD42,LH42,OB42,OT42) -> 0 | RK42: =IFERROR(SUM(E42,N42,W42,AF42,AO42,AX42,BG42,BP42,BY42,CH42,CQ42,CZ42,DI42,DR42,EA42,EJ42,FK42,GC42,GL42,HD42,HM42,IN42,IW42,JF42,JO42,JX42,KG42,KY42,LH42,LQ42,LZ42,MI42,MR42,NA42,NJ42,NS42,OB42,OK42,OT42,PC42,)/QY42,0) -> 33.5 | RM42: =MAX(ES42,IE42) -> 84 | RN42: =MIN(ES42,IE42) -> 84 | RP42: =SUM(EX42,IJ42)/5 -> 1
A43: ='Name List'!B43 -> Edward Money | E43: =IF(C43=0,"",C43+D43) | J43: =IF(E43="","",'Name List'!$I$4) | W43: =IF(U43=0,"",U43+V43) | AB43: =IF(W43="","",'Name List'!$I$4) | AD43: 15 | AE43: 12 | AF43: =IF(AD43=0,"",AD43+AE43) -> 27 | AG43: 0 | AH43: 1 | AI43: 6 | AJ43: 1 | AK43: =IF(AF43="","",'Name List'!$I$4) -> 5 | AO43: =IF(AM43=0,"",AM43+AN43) | AT43: =IF(AO43="","",'Name List'!$I$4) | AX43: =IF(AV43=0,"",AV43+AW43) | BC43: =IF(AX43="","",'Name List'!$I$4) | BG43: =IF(BE43=0,"",BE43+BF43) | BL43: =IF(BG43="","",'Name List'!$I$4) | BY43: =IF(BW43=0,"",BW43+BX43) | CD43: =IF(BY43="","",'Name List'!$I$4) | CH43: =IF(CF43=0,"",CF43+CG43) | CM43: =IF(CH43="","",'Name List'!$I$4) | CQ43: =IF(CO43=0,"",CO43+CP43) | CV43: =IF(CQ43="","",'Name List'!$I$4) | CZ43: =IF(CX43=0,"",CX43+CY43) | DE43: =IF(CZ43="","",'Name List'!$I$4) | DI43: =IF(DG43=0,"",DG43+DH43) | DN43: =IF(DI43="","",'Name List'!$I$4) | DP43: 18 | DQ43: 11 | DR43: =IF(DP43=0,"",DP43+DQ43) -> 29 | DS43: 0 | DT43: 1 | DU43: 6 | DV43: 2 | DW43: =IF(DR43="","",'Name List'!$I$4) -> 5 | EA43: =IF(DY43=0,"",DY43+DZ43) | EF43: =IF(EA43="","",'Name List'!$I$4) | EJ43: =IF(EH43=0,"",EH43+EI43) | EO43: =IF(EJ43="","",'Name List'!$I$4) | EX43: =IF(ES43="","",'Name List'!$I$4) | FK43: =IF(FI43=0,"",FI43+FJ43) | FP43: =IF(FK43="","",'Name List'!$I$4) | FT43: =IF(FR43=0,"",FR43+FS43) | FY43: =IF(FT43="","",'Name List'!$I$4) | GC43: =IF(GA43=0,"",GA43+GB43) | GH43: =IF(GC43="","",'Name List'!$I$4) | GJ43: 16 | GK43: 17 | GL43: =IF(GJ43=0,"",GJ43+GK43) -> 33 | GM43: 1 | GN43: 0 | GO43: 9 | GP43: 1 | GQ43: =IF(GL43="","",'Name List'!$I$4) -> 5 | HD43: =IF(HB43=0,"",HB43+HC43) | HI43: =IF(HD43="","",'Name List'!$I$4) | HM43: =IF(HK43=0,"",HK43+HL43) | HR43: =IF(HM43="","",'Name List'!$I$4) | IJ43: =IF(IE43="","",'Name List'!$I$4) | QR43: =IF(QM43="","",'Name List'!$I$4) | QT43: =SUM(F43+O43+X43+AG43+AP43+AY43+BH43+BQ43+BZ43+CI43+CR43+DA43+DJ43+DS43+EB43+EK43+ET43+FC43+FL43+FU43+GD43+GM43+GV43+HE43+HN43+HW43+IF43+IO43+IX43+JG43+JP43+JY43+KH43+KQ43+KZ43+LI43+LR43+MA43+MJ43+MS43+NB43+NK43+NT43+OC43+OL43+OU43+PD43+PM43+PV43+QE43+QN43) -> 1 | QU43: =SUM(G43+P43+Y43+AH43+AQ43+AZ43+BI43+BR43+CA43+CJ43+CS43+DB43+DK43+DT43+EC43+EL43+EU43+FD43+FM43+FV43+GE43+GN43+GW43+HF43+HO43+HX43+IG43+IP43+IY43+JH43+JQ43+JZ43+KI43+KR43+LA43+LJ43+LS43+MB43+MK43+MT43+NC43+NL43+NU43+OD43+OM43+OV43+PE43+PN43+PW43+QF43+QO43) -> 2 | QV43: =SUM(H43+Q43+Z43+AI43+AR43+BA43+BJ43+BS43+CB43+CK43+CT43+DC43+DL43+DU43+ED43+EM43+EV43+FE43+FN43+FW43+GF43+GO43+GX43+HG43+HP43+HY43+IH43+IQ43+IZ43+JI43+JR43+KA43+KJ43+KS43+LB43+LK43+LT43+MC43+ML43+MU43+ND43+NM43+NV43+OE43+ON43+OW43+PF43+PO43+PX43+QG43+QP43) -> 21 | QW43: =SUM(I43+R43+AA43+AJ43+AS43+BB43+BK43+BT43+CC43+CL43+CU43+DD43+DM43+DV43+EE43+EN43+EW43+FF43+FO43+FX43+GG43+GP43+GY43+HH43+HQ43+HZ43+II43+IR43+JA43+JJ43+JS43+KB43+KK43+KT43+LC43+LL43+LU43+MD43+MM43+MV43+NE43+NN43+NW43+OF43+OO43+OX43+PG43+PP43+PY43+QH43+QQ43) -> 4 | QY43: =SUM(J43,S43,AB43,AK43,AT43,BC43,BL43,BU43,CD43,CM43,CV43,DE43,DN43,DW43,EF43,EO43,FP43,FY43,GH43,GQ43,HI43,HR43,IS43,JB43,JK43,JT43,KC43,KL43,KU43,LD43,LM43,LV43,ME43,MN43,MW43,NF43,NO43,NX43,OG43,OP43,OY43,PH43,PZ43)/5 -> 3 | RA43: =MAX(C43,L43,AD43,AM43,AV43,BN43,BW43,CF43,CX43,DG43,DP43,DY43,EH43,FI43,FR43,GA43,GJ43,HK43,IL43,IU43,JD43,JM43,JV43,KE43,KW43,LO43,LX43,MG43,MP43,MY43,NH43,NQ43,OI43,PA43,PS43) -> 18 | RB43: =MAX(D43,M43,AE43,AN43,AW43,BO43,BX43,CG43,CY43,DH43,DQ43,DZ43,EI43,FJ43,FS43,GB43,GK43,HL43,IM43,IV43,JE43,JN43,JW43,KF43,KX43,LP43,LY43,MH43,MQ43,MZ43,NI43,NR43,OJ43,PB43,PT43) -> 17 | RC43: =MAX(E43,N43,AF43,AO43,AX43,BP43,BY43,CH43,CZ43,DI43,DR43,EA43,EJ43,FK43,FT43,GC43,GL43,HM43,IN43,IW43,JF43,JO43,JX43,KG43,KY43,LQ43,LZ43,MI43,MR43,NA43,NJ43,NS43,OK43,PC43,PU43) -> 33 | RD43: =MIN(C43,L43,AD43,AM43,AV43,BN43,BW43,CF43,CX43,DG43,DP43,DY43,EH43,FI43,FR43,GA43,GJ43,HK43,IL43,IU43,JD43,JM43,JV43,KE43,KW43,LO43,LX43,MG43,MP43,MY43,NH43,NQ43,OI43,PA43,PS43) -> 15 | RE43: =MIN(D43,M43,AE43,AN43,AW43,BO43,BX43,CG43,CY43,DH43,DQ43,DZ43,EI43,FJ43,FS43,GB43,GK43,HL43,IM43,IV43,JE43,JN43,JW43,KF43,KX43,LP43,LY43,MH43,MQ43,MZ43,NI43,NR43,OJ43,PB43,PT43) -> 11 | RF43: =MIN(E43,N43,AF43,AO43,AX43,BP43,BY43,CH43,CZ43,DI43,DR43,EA43,EJ43,FK43,FT43,GC43,GL43,HM43,IN43,IW43,JF43,JO43,JX43,KG43,KY43,LQ43,LZ43,MI43,MR43,NA43,NJ43,NS43,OK43,PC43,PU43) -> 27 | RH43: =MAX(W43,BG43,CQ43,HD43,LH43,OB43,OT43) -> 0 | RI43: =MIN(W43,BG43,CQ43,HD43,LH43,OB43,OT43) -> 0 | RK43: =IFERROR(SUM(E43,N43,W43,AF43,AO43,AX43,BG43,BP43,BY43,CH43,CQ43,CZ43,DI43,DR43,EA43,EJ43,FK43,GC43,GL43,HD43,HM43,IN43,IW43,JF43,JO43,JX43,KG43,KY43,LH43,LQ43,LZ43,MI43,MR43,NA43,NJ43,NS43,OB43,OK43,OT43,PC43,)/QY43,0) -> 29.666667 | RM43: =MAX(ES43,IE43) -> 0 | RN43: =MIN(ES43,IE43) -> 0 | RP43: =SUM(EX43,IJ43)/5 -> 0
